Workbook
Name _PT1: '[1]datos decreto y Resol'!#REF!
Name aaaaaaaaaaa: #REF!
Name ACTIVOS3333: #REF!
Name Adquisición: [2]Listas!$B$9:$B$14
Name Adquisición: [3]Listas!$B$9:$B$14
Name Avaluo: [4]Listas!$B$19:$B$20
Name Avaluo: [5]Listas!$B$19:$B$20
Name AVALÚO: [6]Listas!$B$19:$B$20
Name AVALÚO: [7]Listas!$B$19:$B$20
Name BALASAS2: #REF!
Name BALASAS3: #REF!
Name ClasificaciónNIIF: [8]Listas!$B$13:$B$17
Name cuota3..: '[1]datos decreto y Resol'!#REF!
Name D: #REF!
Name DCA: #REF!
Name DCAC: #REF!
Name DCAC: #REF!
Name DCAC: #REF!
Name DCAC: #REF!
Name DCAC: #REF!
Name DCAD: #REF!
Name DCGD: #REF!
Name DCGD: [9]Listas!#REF!
Name DD: #REF!
Name DD: #REF!
Name DD: #REF!
Name DD: #REF!
Name DD: #REF!
Name DDD: #REF!
Name DDD: #REF!
Name DDD: #REF!
Name DDD: #REF!
Name DDD: #REF!
Name DDDA: #REF!
Name DDDA: #REF!
Name DDDA: #REF!
Name DDDA: #REF!
Name DDDA: #REF!
Name DDDD: #REF!
Name DDDD: #REF!
Name DDDD: #REF!
Name DDDD: #REF!
Name DDDD: #REF!
Name DDDD1: #REF!
Name Declaraciones: #REF!
Name Declaraciones: #REF!
Name Declaraciones: #REF!
Name Declaraciones: #REF!
Name Declaraciones: #REF!
Name ded: #REF!
Name ded: #REF!
Name ded: #REF!
Name ded: #REF!
Name ded: #REF!
Name Diarios: #REF!
Name Diarios: #REF!
Name Diarios: #REF!
Name Diarios: #REF!
Name Diarios: #REF!
Name e: #REF!

Sheet DATOS
A1: TODOS LOS VALORES SE DIGITAN POSITIVOS EXEPTO DEPRECIACIONES
A3: PUC SOLO UNA GUIA NO ES IGUAL EN TODOS | C3: 2026 | E3: 2025
A4: 1 | B4: ACTIVO | C4: =C5+C10+C17+C20+C27+C29+C31 -> 3462278 | E4: =E5+E10+E17+E20+E27+E29+E31 -> 2947383
A5: 11 | B5: EFECTIVO Y EQUIV. AL EFECTIVO | C5: =SUM(C6:C9) -> 576780 | E5: =+SUM(E6:E9) -> 316343
A6: 1105 | B6: CAJA | C6: =+SUMIF('6.BP2026'!A:A,DATOS!A6,'6.BP2026'!I:I) -> 462620 | E6: =+SUMIF('7.BP2025'!A:A,DATOS!A6,'7.BP2025'!I:I) -> 214239 | G6: EMPRESA | H6: GRUPO DE LOLITA SAS
A7: 1110 | B7: BANCOS | C7: =+SUMIF('6.BP2026'!A:A,DATOS!A7,'6.BP2026'!I:I) -> 34966 | E7: =+SUMIF('7.BP2025'!A:A,DATOS!A7,'7.BP2025'!I:I) -> 81216 | G7: NIT | H7: NIT: 900.307.969-5
A8: 1120 | B8: CUENTAS DE AHORROS | C8: =+SUMIF('6.BP2026'!A:A,DATOS!A8,'6.BP2026'!I:I) -> 37524 | E8: =+SUMIF('7.BP2025'!A:A,DATOS!A8,'7.BP2025'!I:I) -> 18936 | G8: FECHA DE CORTE | H8: A 30 DE JUNIO DE 2026 Y 2025
A9: 1130 | B9: EQUIVALENTES AL EFECTIVO | C9: =+SUMIF('6.BP2026'!A:A,DATOS!A9,'6.BP2026'!I:I) -> 41670 | E9: =+SUMIF('7.BP2025'!A:A,DATOS!A9,'7.BP2025'!I:I) -> 1952 | G9: MES | H9: 6
A10: 13 | B10: CUENTAS POR COBRAR | C10: =SUM(C11:C16) -> 437305 | E10: =SUM(E11:E16) -> 232928 | G10: FECHA E.F | H10: 2026-06
A11: 1305 | B11: CLIENTES | C11: =+SUMIF('6.BP2026'!A:A,DATOS!A11,'6.BP2026'!I:I) -> 21421 | E11: =+SUMIF('7.BP2025'!A:A,DATOS!A11,'7.BP2025'!I:I) -> 6032 | G11: FECHA E.F COMP | H11: 2025-06
A12: 1325 | B12: CXC SOCIOS Y ACCIONISTAS | C12: =+SUMIF('6.BP2026'!A:A,DATOS!A12,'6.BP2026'!I:I) -> 0 | E12: =+SUMIF('7.BP2025'!A:A,DATOS!A12,'7.BP2025'!I:I) -> 0 | G12: Representante Legal | H12: MARIO FERNANDO FILEVICH
A13: 1330 | B13: ANTICIPOS Y AVANCES | C13: =+SUMIF('6.BP2026'!A:A,DATOS!A13,'6.BP2026'!I:I) -> 327590 | E13: =+SUMIF('7.BP2025'!A:A,DATOS!A13,'7.BP2025'!I:I) -> 184647 | G13: Cedula Rep Legal | H13: C.E 274.113
A14: 1355 | B14: ANTICIPO IMPUESTOS Y CONTRIB | C14: =+SUMIF('6.BP2026'!A:A,DATOS!A14,'6.BP2026'!I:I) -> 0 | E14: =+SUMIF('7.BP2025'!A:A,DATOS!A14,'7.BP2025'!I:I) -> 0
A15: 1365 | B15: PRESTAMOS A EMPLEADOS | C15: =+SUMIF('6.BP2026'!A:A,DATOS!A15,'6.BP2026'!I:I) -> 363 | E15: =+SUMIF('7.BP2025'!A:A,DATOS!A15,'7.BP2025'!I:I) -> 1998 | G15: Contador | H15: LUZ AIDA HERNANDEZ GARCIA
A16: 1380 | B16: DEUDORES VARIOS | C16: =+SUMIF('6.BP2026'!A:A,DATOS!A16,'6.BP2026'!I:I) -> 87931 | E16: =+SUMIF('7.BP2025'!A:A,DATOS!A16,'7.BP2025'!I:I) -> 40251 | G16: T.P: | H16: 159803-T
A17: 14 | B17: INVENTARIOS | C17: =SUM(C18:C19) -> 78249 | E17: =SUM(E18:E19) -> 81850 | G17: Revisor Fiscal
A18: 1435 | B18: MERCANCIAS NO FABRICADAS POR L | C18: =+SUMIF('6.BP2026'!A:A,DATOS!A18,'6.BP2026'!I:I) -> 78249 | E18: =+SUMIF('7.BP2025'!A:A,DATOS!A18,'7.BP2025'!I:I) -> 81850 | G18: T.P:
A19: 1436 | B19: OTROS INVENTARIOS | C19: =+SUMIF('6.BP2026'!A:A,DATOS!A19,'6.BP2026'!I:I) -> 0 | E19: =+SUMIF('7.BP2025'!A:A,DATOS!A19,'7.BP2025'!I:I) -> 0 | G19: TASA DE MERCADO | H19: 0.01
A20: 15 | B20: PROPIEDAD PLANTA Y EQUIPO | C20: =SUM(C21:C26) -> 1983687 | E20: =SUM(E21:E26) -> 2028380
A21: 1510 | B21: MEJORAS A PROPIEDADES AJENAS | C21: =+SUMIF('6.BP2026'!A:A,DATOS!A21,'6.BP2026'!I:I) -> 339255 | E21: =+SUMIF('7.BP2025'!A:A,DATOS!A21,'7.BP2025'!I:I) -> 355856
A22: 1516 | B22: CONSTRUCCIONES Y ED | C22: =+SUMIF('6.BP2026'!A:A,DATOS!A22,'6.BP2026'!I:I)-(SUMIF('6.BP2026'!A:A,151692,'6.BP2026'!I:I)/2) -> 1286225.5 | E22: =+SUMIF('7.BP2025'!A:A,DATOS!A22,'7.BP2025'!I:I)-(SUMIF('7.BP2025'!A:A,151692,'7.BP2025'!I:I)/2) -> 1286226
A23: 1520 | B23: MAQUINARIA Y EQUIPO | C23: =+SUMIF('6.BP2026'!A:A,DATOS!A23,'6.BP2026'!I:I)-(SUMIF('6.BP2026'!A:A,152092,'6.BP2026'!I:I)/2) -> 463303 | E23: =+SUMIF('7.BP2025'!A:A,DATOS!A23,'7.BP2025'!I:I)-(SUMIF('7.BP2025'!A:A,152092,'7.BP2025'!I:I)/2) -> 455027
A24: 1524 | B24: EQUIPO DE OFICINA | C24: =+SUMIF('6.BP2026'!A:A,DATOS!A24,'6.BP2026'!I:I)-(SUMIF('6.BP2026'!A:A,152492,'6.BP2026'!I:I)/2) -> 210990 | E24: =+SUMIF('7.BP2025'!A:A,DATOS!A24,'7.BP2025'!I:I)-(SUMIF('7.BP2025'!A:A,152492,'7.BP2025'!I:I)/2) -> 210990
A25: 1528 | B25: EQUIPOS DE PROCESAMIENTO DE DA | C25: =+SUMIF('6.BP2026'!A:A,DATOS!A25,'6.BP2026'!I:I)-(SUMIF('6.BP2026'!A:A,152892,'6.BP2026'!I:I)/2) -> 42702 | E25: =+SUMIF('7.BP2025'!A:A,DATOS!A25,'7.BP2025'!I:I)-(SUMIF('7.BP2025'!A:A,152892,'7.BP2025'!I:I)/2) -> 42702
A26: 1592 | B26: DEPRECIACION ACUMULADA | C26: =+SUMIF('6.BP2026'!A:A,DATOS!A26,'6.BP2026'!I:I)+(SUMIF('6.BP2026'!A:A,151692,'6.BP2026'!I:I)/2)+(SUMIF('6.BP2026'!A:A,152092,'6.BP2026'!I:I)/2)+(SUMIF('6.BP2026'!A:A,152492,'6.BP2026'!I:I)/2)+(SUMIF('6.BP2026'!A:A,152892,'6.BP2026'!I:I)/2) -> -358788.5 | E26: =+SUMIF('7.BP2025'!A:A,DATOS!A26,'7.BP2025'!I:I)+(SUMIF('7.BP2025'!A:A,151092,'7.BP2025'!I:I)/2)+(SUMIF('7.BP2025'!A:A,151692,'7.BP2025'!I:I)/2)+(SUMIF('7.BP2025'!A:A,152092,'7.BP2025'!I:I)/2)+(SUMIF('7.BP2025'!A:A,152492,'7.BP2025'!I:I)/2)+(SUMIF('7.BP2025'!A:A,152892,'7.BP2025'!I:I)/2) -> -322421
A27: 16 | B27: INTANGIBLES | C27: =SUM(C28:C28) -> 184351 | E27: =SUM(E28:E28) -> 220000
A28: 16 | B28: CONCESIONES Y FRANQUICIAS | C28: =+SUMIF('6.BP2026'!A:A,DATOS!A28,'6.BP2026'!I:I) -> 184351 | E28: =+SUMIF('7.BP2025'!A:A,DATOS!A28,'7.BP2025'!I:I) -> 220000
A29: 17 | B29: OTROS ACTIVOS | C29: =SUM(C30:C30) -> 7521 | E29: =SUM(E30:E30) -> 0
A30: 17 | B30: GASTOS PAGADOS POR ANTICIPADO | C30: =+SUMIF('6.BP2026'!A:A,DATOS!A30,'6.BP2026'!I:I) -> 7521 | E30: =+SUMIF('7.BP2025'!A:A,DATOS!A30,'7.BP2025'!I:I) -> 0
A31: 19 | B31: ACTIVOS POR IMPUESTOS | C31: =+C32 -> 194385 | E31: =+E32 -> 67882
A32: 1955 | B32: ANTICIPO DE IMPUESTO Y SALDOS A FAVOR | C32: =+SUMIF('6.BP2026'!A:A,DATOS!A32,'6.BP2026'!I:I) -> 194385 | E32: =+SUMIF('7.BP2025'!A:A,DATOS!A32,'7.BP2025'!I:I) -> 67882
A33: 2 | B33: PASIVO | C33: =C34+C38+C40+C46+C56+C67+C69 -> 1131133 | E33: =+E34+E38+E40+E46+E56+E67+E69 -> 781353
A34: 21 | B34: OBLIGACIONES FINANCIERAS | C34: =SUM(C35:C37) -> 330754 | E34: =SUM(E35:E37) -> 330620
A35: 2105 | B35: OBLIGACIONES FINANCIERAS | C35: =-SUMIF('6.BP2026'!A:A,DATOS!A35,'6.BP2026'!I:I) -> 269433 | E35: =-SUMIF('7.BP2025'!A:A,DATOS!A35,'7.BP2025'!I:I) -> 302914
A36: 2120 | B36: COMPAÑIAS DE FINANCIAMIENTO CO | C36: =-SUMIF('6.BP2026'!A:A,DATOS!A36,'6.BP2026'!I:I) -> 3420 | E36: =-SUMIF('7.BP2025'!A:A,DATOS!A36,'7.BP2025'!I:I) -> 3420
A37: 2195 | B37: OTRAS OBLIGACIONES | C37: =-SUMIF('6.BP2026'!A:A,DATOS!A37,'6.BP2026'!I:I) -> 57901 | E37: =-SUMIF('7.BP2025'!A:A,DATOS!A37,'7.BP2025'!I:I) -> 24286
A38: 22 | B38: PROVEEDORES | C38: =SUM(C39:C39) -> 497599 | E38: =SUM(E39:E39) -> 198797
A39: 2205 | B39: NACIONALES | C39: =-SUMIF('6.BP2026'!A:A,DATOS!A39,'6.BP2026'!I:I) -> 497599 | E39: =-SUMIF('7.BP2025'!A:A,DATOS!A39,'7.BP2025'!I:I) -> 198797
A40: 23 | B40: CUENTAS POR PAGAR | C40: =SUM(C41:C45) -> 29514 | E40: =SUM(E41:E45) -> 5579
A41: 2335 | B41: COSTOS Y GASTOS POR PAGAR | C41: =-SUMIF('6.BP2026'!A:A,DATOS!A41,'6.BP2026'!I:I) -> 0 | E41: =-SUMIF('7.BP2025'!A:A,DATOS!A41,'7.BP2025'!I:I) -> 0
A42: 2367 | B42: RETENCIONES EN EL IVA | C42: =-SUMIF('6.BP2026'!A:A,DATOS!A42,'6.BP2026'!I:I) -> 0 | E42: =-SUMIF('7.BP2025'!A:A,DATOS!A42,'7.BP2025'!I:I) -> 0
A43: 2369 | B43: AUTORRETENCION | C43: =-SUMIF('6.BP2026'!A:A,DATOS!A43,'6.BP2026'!I:I) -> 0 | E43: =-SUMIF('7.BP2025'!A:A,DATOS!A43,'7.BP2025'!I:I) -> 0
A44: 2370 | B44: RETENCIONES Y APORTES DE NOMIN | C44: =-SUMIF('6.BP2026'!A:A,DATOS!A44,'6.BP2026'!I:I) -> 571 | E44: =-SUMIF('7.BP2025'!A:A,DATOS!A44,'7.BP2025'!I:I) -> -2150
A45: 2380 | B45: ACREEDORES VARIOS | C45: =-SUMIF('6.BP2026'!A:A,DATOS!A45,'6.BP2026'!I:I) -> 28943 | E45: =-SUMIF('7.BP2025'!A:A,DATOS!A45,'7.BP2025'!I:I) -> 7729
A46: 24 | B46: PASIVO POR IMPUESTOS | C46: =+C48+C51+C47+C54 -> 178380 | E46: =+E48+E51+E47+E54 -> 130347
A47: 2402 | B47: IMPUESTO DIFERIDO | C47: =-SUMIF('6.BP2026'!A:A,DATOS!A47,'6.BP2026'!I:I) -> 4118 | E47: =-SUMIF('7.BP2025'!A:A,DATOS!A47,'7.BP2025'!I:I) -> 4118
A48: 2404 | B48: IMPUESTO DE RENTA | C48: =+SUM(C49:C50) -> 16683 | E48: =+SUM(E49:E50) -> 26671
A49: 24040501 | B49: IMPUESTO DE RENTA AÑO ANT | C49: =-SUMIF('6.BP2026'!A:A,DATOS!A49,'6.BP2026'!I:I) -> 0 | E49: =-SUMIF('7.BP2025'!A:A,DATOS!A49,'7.BP2025'!I:I) -> 0
A50: 24040502 | B50: VIGENCIA FISCAL CORRIENTE | C50: =-SUMIF('6.BP2026'!A:A,DATOS!A50,'6.BP2026'!I:I) -> 16683 | E50: =-SUMIF('7.BP2025'!A:A,DATOS!A50,'7.BP2025'!I:I) -> 26671
A51: 2406 | B51: ACREEDORES OFICIALES | C51: =SUM(C52:C53) -> 157579 | E51: =SUM(E52:E53) -> 26515
A52: 240605 | B52: RETENCION EN LA FUENTE | C52: =-SUMIF('6.BP2026'!A:A,DATOS!A52,'6.BP2026'!I:I)/2 -> 14503 | E52: =-SUMIF('7.BP2025'!A:A,DATOS!A52,'7.BP2025'!I:I)/2 -> 26515
A53: 240610 | B53: IVA POR PAGAR | C53: =-SUMIF('6.BP2026'!A:A,DATOS!A53,'6.BP2026'!I:I)/2 -> 143076 | E53: =-SUMIF('7.BP2025'!A:A,DATOS!A53,'7.BP2025'!I:I)/2 -> 0
A54: 2408 | B54: IMPUESTO SOBRE LAS VENTAS | C54: =SUM(C55:C55) -> 0 | E54: =SUM(E55:E55) -> 73043
A55: 240805 | B55: IVA 19% | C55: =-SUMIF('6.BP2026'!A:A,2408,'6.BP2026'!I:I) -> 0 | E55: =-SUMIF('7.BP2025'!A:A,2408,'7.BP2025'!I:I) -> 73043
A56: 25 | B56: BENEFICIOS A EMPLEADOS | C56: =SUM(C57:C66) -> 77625 | E56: =SUM(E57:E66) -> 79650 | F56: -32586
A57: 2505 | B57: SALARIOS POR PAGAR | C57: =-SUMIF('6.BP2026'!A:A,DATOS!A57,'6.BP2026'!I:I) -> 0 | E57: =-SUMIF('7.BP2025'!A:A,DATOS!A57,'7.BP2025'!I:I) -> 428
A58: 2510 | B58: CESANTIAS CONSOLIDADAS | C58: =-SUMIF('6.BP2026'!A:A,DATOS!A58,'6.BP2026'!I:I) -> 0 | E58: =-SUMIF('7.BP2025'!A:A,DATOS!A58,'7.BP2025'!I:I) -> 0
A59: 2515 | B59: INTERESES CESANTIAS | C59: =-SUMIF('6.BP2026'!A:A,DATOS!A59,'6.BP2026'!I:I) -> 0 | E59: =-SUMIF('7.BP2025'!A:A,DATOS!A59,'7.BP2025'!I:I) -> 0
A60: 2520 | B60: PRIMA DE SERVICIOS | C60: =-SUMIF('6.BP2026'!A:A,DATOS!A60,'6.BP2026'!I:I) -> 0 | E60: =-SUMIF('7.BP2025'!A:A,DATOS!A60,'7.BP2025'!I:I) -> 0
A61: 2525 | B61: VACACIONES CONSOLIDADAS | C61: =-SUMIF('6.BP2026'!A:A,DATOS!A61,'6.BP2026'!I:I) -> 15875 | E61: =-SUMIF('7.BP2025'!A:A,DATOS!A61,'7.BP2025'!I:I) -> 7015
A62: 253005 | B62: CESANTIAS | C62: =-SUMIF('6.BP2026'!A:A,DATOS!A62,'6.BP2026'!I:I) -> 25449 | E62: =-SUMIF('7.BP2025'!A:A,DATOS!A62,'7.BP2025'!I:I) -> 28955
A63: 253010 | B63: INT CESANTIAS | C63: =-SUMIF('6.BP2026'!A:A,DATOS!A63,'6.BP2026'!I:I) -> 1493 | E63: =-SUMIF('7.BP2025'!A:A,DATOS!A63,'7.BP2025'!I:I) -> 1946
A64: 253015 | B64: VACACIONES | C64: =-SUMIF('6.BP2026'!A:A,DATOS!A64,'6.BP2026'!I:I) -> 16819 | E64: =-SUMIF('7.BP2025'!A:A,DATOS!A64,'7.BP2025'!I:I) -> 20099
A65: 253020 | B65: PRIMA DE SERVICIOS | C65: =-SUMIF('6.BP2026'!A:A,DATOS!A65,'6.BP2026'!I:I) -> 0 | E65: =-SUMIF('7.BP2025'!A:A,DATOS!A65,'7.BP2025'!I:I) -> -189
A66: 2550 | B66: RETENCION Y APORTES DE NOMIN | C66: =-SUMIF('6.BP2026'!A:A,DATOS!A66,'6.BP2026'!I:I) -> 17989 | E66: =-SUMIF('7.BP2025'!A:A,DATOS!A66,'7.BP2025'!I:I)-SUMIF('7.BP2025'!A:A,2570,'7.BP2025'!I:I) -> 21396
A67: 26 | B67: PASIVOS ESTIMADOS Y PROVISIONES | C67: =+C68 -> 14938 | E67: =+E68 -> 32648
A68: 2615 | B68: PARA OBLIGACIONES FISCALES | C68: =-SUMIF('6.BP2026'!A:A,DATOS!A68,'6.BP2026'!I:I)-SUMIF('6.BP2026'!A:A,2610,'6.BP2026'!I:I) -> 14938 | E68: =-SUMIF('7.BP2025'!A:A,DATOS!A68,'7.BP2025'!I:I) -> 32648
A69: 28 | B69: OTROS PASIVOS | C69: =+C70 -> 2323 | E69: =+E70 -> 3712
A70: 2805 | B70: ANTICIPOS Y AVANCES RECIBIDOS | C70: =-SUMIF('6.BP2026'!A:A,DATOS!A70,'6.BP2026'!I:I) -> 2323 | E70: =-SUMIF('7.BP2025'!A:A,DATOS!A70,'7.BP2025'!I:I) -> 3712
A71: 3 | B71: PATRIMONIO | C71: =+C72+C73+C75 -> 2291401 | E71: =SUM(E72:E75) -> 2133409
A72: 3105 | B72: CAPITAL SUSCRITO Y PAGADO | C72: =-SUMIF('6.BP2026'!A:A,DATOS!A72,'6.BP2026'!I:I) -> 1737000 | E72: =-SUMIF('7.BP2025'!A:A,DATOS!A72,'7.BP2025'!I:I) -> 1737000
A73: 3305 | B73: RESERVAS OBLIGATORIAS | C73: =-SUMIF('6.BP2026'!A:A,DATOS!A73,'6.BP2026'!I:I) -> 89882 | E73: =-SUMIF('7.BP2025'!A:A,DATOS!A73,'7.BP2025'!I:I) -> 73935
A74: 36 | B74: UTILIDAD DEL EJERCICIO | C74: =-SUMIF('6.BP2026'!A:A,DATOS!A74,'6.BP2026'!I:I) -> 0 | E74: =-SUMIF('7.BP2025'!A:A,DATOS!A74,'7.BP2025'!I:I) -> 0
A75: 37 | B75: RESULTADOS DE EJERC. ANTERIORE | C75: =+C76+C77+C78 -> 464519 | E75: =+E76+E77+E78 -> 322474
A76: 3705 | B76: UTILIDADES ACUMULADAS | C76: =-SUMIF('6.BP2026'!A:A,DATOS!A76,'6.BP2026'!I:I) -> 521697 | E76: =-SUMIF('7.BP2025'!A:A,DATOS!A76,'7.BP2025'!I:I) -> 379652
A77: 3710 | B77: PERDIDAS ACUMULADAS | C77: =-SUMIF('6.BP2026'!A:A,DATOS!A77,'6.BP2026'!I:I) -> -40142 | E77: =-SUMIF('7.BP2025'!A:A,DATOS!A77,'7.BP2025'!I:I) -> -40142
A78: 3715 | B78: IMPACTOS POR TRANSICION | C78: =-SUMIF('6.BP2026'!A:A,DATOS!A78,'6.BP2026'!I:I) -> -17036 | E78: =-SUMIF('7.BP2025'!A:A,DATOS!A78,'7.BP2025'!I:I) -> -17036
B79: RESULTADO ACUMULADO | C79: =+D86-D109-D212 -> 39750 | E79: =+G86-G109-G212 -> 32624
B80: RESULTADO MES | C80: =+C86-C109-C212 -> -692.5 | E80: =+F86-F109-F212 -> -5686.5
B81: ECUACION CONTABLE | C81: =+C4-C33-C71-C79 -> -6 | D81: ok | E81: =+E4-E33-E71-E79 -> -3 | F81: ok
C84: 2025 | F84: 2024
B85: RESULTADOS | C85: MES | D85: ACUMULADO | F85: MES | G85: ACUMULADO
A86: 4 | B86: INGRESOS | C86: =+C87+C96+C105 -> 490828 | D86: =+D87+D96+D105 -> 3100509.5 | F86: =+F87+F96+F105 -> 517465 | G86: =+G87+G96+G105 -> 2950553
A87: 41 | B87: INGRESOS OPERACIONALES | C87: =+C88+C89+C90+C91+C92+C94-C95 -> 479990 | D87: =+D89+D88+D90+D91+D92+D94-D95 -> 3042065.5 | F87: =+F89+F91+F92+F93+F94-F95 -> 515196.5 | G87: =+G89+G90+G91+G92+G93+G94-G95 -> 2938932.5
A88: 4120 | B88: FLETES | C88: =+(SUMIF('6.BP2026'!A:A,DATOS!A88,'6.BP2026'!H:H))-(SUMIF('6.BP2026'!A:A,DATOS!A88,'6.BP2026'!G:G)) -> 150 | D88: =-SUMIF('6.BP2026'!A:A,DATOS!A88,'6.BP2026'!I:I) -> 2300 | F88: =+(SUMIF('7.BP2025'!A:A,DATOS!A88,'7.BP2025'!H:H)/2)-(SUMIF('7.BP2025'!A:A,DATOS!A88,'7.BP2025'!G:G)/2) -> 0 | G88: =-SUMIF('7.BP2025'!A:A,DATOS!A88,'7.BP2025'!I:I)/2 -> 0
A89: 41359503 | B89: VENTAS RESTAURANTE | C89: =+(SUMIF('6.BP2026'!A:A,DATOS!A89,'6.BP2026'!H:H)/2)-(SUMIF('6.BP2026'!A:A,DATOS!A89,'6.BP2026'!G:G)/2) -> 481388 | D89: =-SUMIF('6.BP2026'!A:A,DATOS!A89,'6.BP2026'!I:I)/2 -> 3046464.5 | F89: =+(SUMIF('7.BP2025'!A:A,DATOS!A89,'7.BP2025'!H:H)/2)-(SUMIF('7.BP2025'!A:A,DATOS!A89,'7.BP2025'!G:G)/2) -> 518220 | G89: =-SUMIF('7.BP2025'!A:A,DATOS!A89,'7.BP2025'!I:I)/2 -> 2937443
A90: 41359507 | B90: INGRESOS EXCLUIDOS | C90: =+(SUMIF('6.BP2026'!A:A,DATOS!A90,'6.BP2026'!H:H)/2)-(SUMIF('6.BP2026'!A:A,DATOS!A90,'6.BP2026'!G:G)/2) -> 0 | D90: =-SUMIF('6.BP2026'!A:A,DATOS!A90,'6.BP2026'!I:I)/2 -> 0 | F90: =+(SUMIF('7.BP2025'!A:A,DATOS!A90,'7.BP2025'!H:H)/2)-(SUMIF('7.BP2025'!A:A,DATOS!A90,'7.BP2025'!G:G)/2) -> 0 | G90: =-SUMIF('7.BP2025'!A:A,DATOS!A90,'7.BP2025'!I:I)/2 -> 0
A91: 41359511 | B91: VENTAS DE BODEGA | C91: =+(SUMIF('6.BP2026'!A:A,DATOS!A91,'6.BP2026'!H:H)/2)-(SUMIF('6.BP2026'!A:A,DATOS!A91,'6.BP2026'!G:G)/2) -> 0 | D91: =-SUMIF('6.BP2026'!A:A,DATOS!A91,'6.BP2026'!I:I)/2 -> 166 | F91: =+(SUMIF('7.BP2025'!A:A,DATOS!A91,'7.BP2025'!H:H)/2)-(SUMIF('7.BP2025'!A:A,DATOS!A91,'7.BP2025'!G:G)/2) -> 132.5 | G91: =-SUMIF('7.BP2025'!A:A,DATOS!A91,'7.BP2025'!I:I)/2 -> 1482.5
A92: 41359512 | B92: VENTAS A CREDITO | C92: =+(SUMIF('6.BP2026'!A:A,DATOS!A92,'6.BP2026'!H:H)/2)-(SUMIF('6.BP2026'!A:A,DATOS!A92,'6.BP2026'!G:G)/2) -> 0 | D92: =-SUMIF('6.BP2026'!A:A,DATOS!A92,'6.BP2026'!I:I)/2 -> 0 | F92: =+(SUMIF('7.BP2025'!A:A,DATOS!A92,'7.BP2025'!H:H)/2)-(SUMIF('7.BP2025'!A:A,DATOS!A92,'7.BP2025'!G:G)/2) -> 0 | G92: =-SUMIF('7.BP2025'!A:A,DATOS!A92,'7.BP2025'!I:I)/2 -> 0
A93: 41359513 | B93: VENTAS INSTITUCIONALES NO GRAVADAS | C93: =+(SUMIF('6.BP2026'!A:A,DATOS!A93,'6.BP2026'!H:H)/2)-(SUMIF('6.BP2026'!A:A,DATOS!A93,'6.BP2026'!G:G)/2) -> 0 | D93: =-SUMIF('6.BP2026'!A:A,DATOS!A93,'6.BP2026'!I:I)/2 -> 0 | F93: =+(SUMIF('7.BP2025'!A:A,DATOS!A93,'7.BP2025'!H:H)/2)-(SUMIF('7.BP2025'!A:A,DATOS!A93,'7.BP2025'!G:G)/2) -> 0 | G93: =-SUMIF('7.BP2025'!A:A,DATOS!A93,'7.BP2025'!I:I)/2 -> 0
A94: 41359599 | B94: VENTAS (AJU) | C94: =+(SUMIF('6.BP2026'!A:A,DATOS!A94,'6.BP2026'!H:H)/2)-(SUMIF('6.BP2026'!A:A,DATOS!A94,'6.BP2026'!G:G)/2) -> -311 | D94: =-SUMIF('6.BP2026'!A:A,DATOS!A94,'6.BP2026'!I:I)/2 -> -865 | F94: =+(SUMIF('7.BP2025'!A:A,DATOS!A94,'7.BP2025'!H:H)/2)-(SUMIF('7.BP2025'!A:A,DATOS!A94,'7.BP2025'!G:G)/2) -> -2453 | G94: =-SUMIF('7.BP2025'!A:A,DATOS!A94,'7.BP2025'!I:I)/2 -> 4446
A95: 4175 | B95: DEVOLUCIONES EN VENTAS | C95: =-(SUMIF('6.BP2026'!A:A,DATOS!A95,'6.BP2026'!H:H))+(SUMIF('6.BP2026'!A:A,DATOS!A95,'6.BP2026'!G:G)) -> 1237 | D95: =SUMIF('6.BP2026'!A:A,DATOS!A95,'6.BP2026'!I:I) -> 6000 | F95: =+SUMIF('7.BP2025'!A:A,DATOS!A95,'7.BP2025'!G:G)-SUMIF('7.BP2025'!A:A,DATOS!A95,'7.BP2025'!H:H) -> 703 | G95: =SUMIF('7.BP2025'!A:A,DATOS!A95,'7.BP2025'!I:I) -> 4439
A96: 42 | B96: INGRESOS NO OPERACIONALES | C96: =SUM(C97:C104) -> 10755 | D96: =SUM(D97:D104) -> 56488 | F96: =SUM(F97:F104) -> 1944 | G96: =SUM(G97:G104) -> 9959
A97: 4210 | B97: FINANCIEROS | C97: =+(SUMIF('6.BP2026'!A:A,DATOS!A97,'6.BP2026'!H:H))-(SUMIF('6.BP2026'!A:A,DATOS!A97,'6.BP2026'!G:G)) -> 0 | D97: =-SUMIF('6.BP2026'!A:A,DATOS!A97,'6.BP2026'!I:I) -> 0 | F97: =+(SUMIF('7.BP2025'!A:A,DATOS!A97,'7.BP2025'!H:H))-(SUMIF('7.BP2025'!A:A,DATOS!A97,'7.BP2025'!G:G)) -> 0 | G97: =-SUMIF('7.BP2025'!A:A,DATOS!A97,'7.BP2025'!I:I) -> 0
A98: 4220 | B98: ARRENDAMIENTOS | C98: =+(SUMIF('6.BP2026'!A:A,DATOS!A98,'6.BP2026'!H:H))-(SUMIF('6.BP2026'!A:A,DATOS!A98,'6.BP2026'!G:G)) -> 9133 | D98: =-SUMIF('6.BP2026'!A:A,DATOS!A98,'6.BP2026'!I:I) -> 34625 | F98: =+(SUMIF('7.BP2025'!A:A,DATOS!A98,'7.BP2025'!H:H))-(SUMIF('7.BP2025'!A:A,DATOS!A98,'7.BP2025'!G:G)) -> 0 | G98: =-SUMIF('7.BP2025'!A:A,DATOS!A98,'7.BP2025'!I:I) -> 0
A99: 4235 | B99: SERVICIOS | C99: =+(SUMIF('6.BP2026'!A:A,DATOS!A99,'6.BP2026'!H:H))-(SUMIF('6.BP2026'!A:A,DATOS!A99,'6.BP2026'!G:G)) -> 899 | D99: =-SUMIF('6.BP2026'!A:A,DATOS!A99,'6.BP2026'!I:I) -> 16792 | F99: =+(SUMIF('7.BP2025'!A:A,DATOS!A99,'7.BP2025'!H:H))-(SUMIF('7.BP2025'!A:A,DATOS!A99,'7.BP2025'!G:G)) -> 1421 | G99: =-SUMIF('7.BP2025'!A:A,DATOS!A99,'7.BP2025'!I:I) -> 4161
A100: 4245 | B100: ACTIVO FIJO | C100: =+(SUMIF('6.BP2026'!A:A,DATOS!A100,'6.BP2026'!H:H))-(SUMIF('6.BP2026'!A:A,DATOS!A100,'6.BP2026'!G:G)) -> 0 | D100: =-SUMIF('6.BP2026'!A:A,DATOS!A100,'6.BP2026'!I:I) -> 400 | F100: =+(SUMIF('7.BP2025'!A:A,DATOS!A100,'7.BP2025'!H:H))-(SUMIF('7.BP2025'!A:A,DATOS!A100,'7.BP2025'!G:G)) -> 0 | G100: =-SUMIF('7.BP2025'!A:A,DATOS!A100,'7.BP2025'!I:I) -> 0
A101: 4250 | B101: RECUPERACIONES | C101: =+(SUMIF('6.BP2026'!A:A,DATOS!A101,'6.BP2026'!H:H))-(SUMIF('6.BP2026'!A:A,DATOS!A101,'6.BP2026'!G:G)) -> 3 | D101: =-SUMIF('6.BP2026'!A:A,DATOS!A101,'6.BP2026'!I:I) -> 18 | F101: =+(SUMIF('7.BP2025'!A:A,DATOS!A101,'7.BP2025'!H:H))-(SUMIF('7.BP2025'!A:A,DATOS!A101,'7.BP2025'!G:G)) -> 4 | G101: =-SUMIF('7.BP2025'!A:A,DATOS!A101,'7.BP2025'!I:I) -> 20
A102: 4255 | B102: INDEMNIZACIONES | C102: =+(SUMIF('6.BP2026'!A:A,DATOS!A102,'6.BP2026'!H:H))-(SUMIF('6.BP2026'!A:A,DATOS!A102,'6.BP2026'!G:G)) -> 0 | D102: =-SUMIF('6.BP2026'!A:A,DATOS!A102,'6.BP2026'!I:I) -> 606 | F102: =+(SUMIF('7.BP2025'!A:A,DATOS!A102,'7.BP2025'!H:H))-(SUMIF('7.BP2025'!A:A,DATOS!A102,'7.BP2025'!G:G)) -> 0 | G102: =-SUMIF('7.BP2025'!A:A,DATOS!A102,'7.BP2025'!I:I) -> 1051
A103: 4265 | B103: INGRESOS EJERCICIOS ANTERIORES | C103: =+(SUMIF('6.BP2026'!A:A,DATOS!A103,'6.BP2026'!H:H))-(SUMIF('6.BP2026'!A:A,DATOS!A103,'6.BP2026'!G:G)) -> 0 | D103: =-SUMIF('6.BP2026'!A:A,DATOS!A103,'6.BP2026'!I:I) -> 0 | F103: =+(SUMIF('7.BP2025'!A:A,DATOS!A103,'7.BP2025'!H:H))-(SUMIF('7.BP2025'!A:A,DATOS!A103,'7.BP2025'!G:G)) -> 0 | G103: =-SUMIF('7.BP2025'!A:A,DATOS!A103,'7.BP2025'!I:I) -> 0
...

Sheet RESULTADOS GRUPO
B1: =+B3 -> 2 | C1: =+C3 -> 3 | D1: =+D3 -> 2 | E1: =+E3 -> 5 | F1: =+F3 -> 12
A2: MES ENERO | B2: GRUPO DL | C2: INSPIRAMOS | D2: CONVOCAMOS | E2: OASIS | F2: TOTAL
A3: CANTIDAD OASIS | B3: 2 | C3: 3 | D3: 2 | E3: 5 | F3: =SUM(B3:E3) -> 12
A4: VENTAS ENERO | F4: =SUM(B4:E4) -> 0
A5: UTILIDAD ANTES DE IMPUESTO | F5: =SUM(B5:E5) -> 0
A6: UTILIDAD DESPUES DE IMPUESTO | F6: =SUM(B6:E6) -> 0
A7: VR FT SOCIOS | F7: =SUM(B7:E7) -> 0
A8: UTILIDAD REEXPRESADA ANTES DE IMP | B8: =+B6+B7 -> 0 | C8: =+C6+C7-5 -> -5 | D8: =+D6+D7 -> 0 | E8: =+E6+E7 -> 0 | F8: =SUM(B8:E8) -> -5 | H8: =+F4*5% -> 0 | I8: =+H8/F4 -> #DIV/0!
B9: =+B8/B4 -> #DIV/0! | C9: =+C8/C4 -> #DIV/0! | D9: =+D8/D4 -> #DIV/0! | E9: =+E8/E4 -> #DIV/0! | F9: =+F8/F4 -> #DIV/0!
A11: ACUMULADO | B11: GRUPO DL | C11: INSPIRAMOS | D11: CONVOCAMOS | E11: OASIS | F11: TOTAL
A12: TOTAL VENTAS ACUMULADAS | H12: =+B12-'2.E.R.I. MES-ACUMULADO'!CM13 -> -3042065.5 | I12: =+B13-'2.E.R.I. MES-ACUMULADO'!CM152 -> -56427 | J12: =+B15-'2.E.R.I. MES-ACUMULADO'!CM158 -> -39744
A13: UTILIDAD ANTES DE IMPUESTO | G13: =+F13/F12 -> #DIV/0! | H13: =+B13-'2.E.R.I. MES-ACUMULADO'!CM152 -> -56427
G14: 8% PARA TODAS LAS CIAS
A15: UTILIDAD DESPUES DE IMPUESTO | H15: =+B15-'2.E.R.I. MES-ACUMULADO'!CM158 -> -39744
A17: =+#REF! -> #REF!
A19: UTILIDAD REEXPRESADA ANTES IMP | H19: =+F13+F17 -> 0
A21: UTILIDAD PLANEADA 8% | B21: =+B12*8% -> 0 | C21: =+C12*8% -> 0 | D21: =+D12*8% -> 0 | E21: =+E12*8% -> 0 | F21: =+F12*8% -> 0
A22: VR A FACTURAR | B22: =-(+C22+D22+E22) -> 353000 | C22: =-75000-27000 -> -102000 | D22: =-23000-9000 -> -32000 | E22: =-165000-54000 -> -219000 | F22: =SUM(B22:E22) -> 0
B23: FT SOCIOS | C23: FT SOCIOS | D23: SOLO ANT EN CE
B24: ARRIENDOS | C24: FT-UTILIDADES | D24: ANT-UTILIDADES | E24: TOTAL
A25: VALORES MES MARZO | B25: 5801891 | C25: 5485827 | D25: =+C25 -> 5485827 | E25: =SUM(B25:D25) -> 16773545
A26: VR MAYO-AGTO | B26: =+B25*8 -> 46415128 | C26: =+C25*8 -> 43886616 | D26: =+D25*8 -> 43886616
B29: ANA MARIA | C29: FERNANDO | H29: ACTUAL | I29: AÑO 2023 ANA | J29: AÑO 2023 FERNANDO
A30: TOTAL VENTAS ACUMULADAS | B30: 34152 | C30: 48152 | H30: INGRESOS | I30: =+B30/3*12 -> 136608 | J30: =+C30/3*12 -> 192608
A31: CTOS Y DEDUCCIONES | B31: =34152+5471 -> 39623 | C31: 28220 | H31: CTOS | I31: =+B31/3*12 -> 158492 | J31: =+C31/3*12 -> 112880
A32: UTILIDAD ANTES DE IMPUESTO | B32: -5471 | C32: 19932 | H32: UTILIDAD | I32: =+I30-I31 -> -21884 | J32: =+J30-J31 -> 79728
B33: =+B32/B30 -> -0.1601956 | C33: =+C32/C30 -> 0.41393919 | H33: IMP | I33: 0 | J33: 3322
J34: =+J33/J32 -> 0.041666667
A35: VENTAS X MES | B35: =+B30/3 -> 11384 | C35: =+C30/3 -> 16050.667
A36: UTILIDAD PROMEDIO MES | B36: =+B32/3 -> -1823.6667 | C36: =+C32/3 -> 6644
H37: PLANEACION | I37: =+I29 -> AÑO 2023 ANA | J37: =+J29 -> AÑO 2023 FERNANDO
H38: INGRESOS | I38: =+I30+(5801*8)+(5486*8) -> 226904 | J38: =+J30 -> 192608
H39: CTOS | I39: =+I31 -> 158492 | J39: =+J31 -> 112880
H40: UTILIDAD | I40: =+I38-I39 -> 68412 | J40: =+J38-J39 -> 79728
H41: IMP | I41: 1121 | J41: =+J33 -> 3322
I42: =+I41/I40 -> 0.016386014 | J42: =+J41/J40 -> 0.041666667
A45: GRUPO DL FACTURA ABRIL 30
A46: FLETES | C46: =+$C$22*0.6 -> -61200 | D46: =+$D$22*0.6 -> -19200 | E46: =+$E$22*0.6 -> -131400
A47: PANES | C47: =+$C$22*0.4 -> -40800 | D47: =+$D$22*0.4 -> -12800 | E47: =+$E$22*0.4 -> -87600
A48: TOTAL | C48: =SUM(C46:C47) -> -102000 | D48: =SUM(D46:D47) -> -32000 | E48: =SUM(E46:E47) -> -219000 | F48: =SUM(C48:E48) -> -353000
B49: =+'2.E.R.I. MES-ACUMULADO'!CM168 -> 58028
A52: APROBADO Q FACTURE ANA A PARTIR DE MAYO
A53: APROBADO BALANCEAR A 8% TODOS LOS RESULTADOS

Sheet 2.E.R.I.MES
B2: =+DATOS!H6 -> GRUPO DE LOLITA SAS | M2: PUNTO DE EQUILIBRIO CONTABLE | P2: PRUEBA DEL PUNTO DE EQUILIBRIO | R2: VERIFICACION CON EL MES | T2: PROYECCION PROXIMO MES
B3: =+DATOS!H7 -> NIT: 900.307.969-5 | M3: INGRESOS | N3: =+C13 -> #REF! | O3: =+N3/N3 -> #REF! | P3: =+M3 -> INGRESOS | Q3: =-+N7 -> #REF! | R3: =+P3 -> INGRESOS | S3: =+N3 -> #REF! | T3: =+P3 -> INGRESOS | U3: 0
B4: ESTADO DE RESULTADOS INTEGRAL MENSUAL | M4: CMV VARIABLE | N4: =+C15 -> 0 | O4: =+N4/N3 -> #REF! | P4: =+M4 -> CMV VARIABLE | Q4: =Q3*O4 -> #REF! | R4: =+P4 -> CMV VARIABLE | S4: =S3*O4 -> #REF! | T4: =+P4 -> CMV VARIABLE | U4: =+U3*O4 -> #REF!
B5: =+DATOS!H8 -> A 30 DE JUNIO DE 2026 Y 2025 | M5: U.DESPUES DE GTOS VBLES | N5: =+N3+N4 -> #REF! | O5: =+N5/N3 -> #REF! | P5: =+M5 -> U.DESPUES DE GTOS VBLES | Q5: =SUM(Q3:Q4) -> #REF! | R5: =+P5 -> U.DESPUES DE GTOS VBLES | S5: =SUM(S3:S4) -> #REF! | T5: =+P5 -> U.DESPUES DE GTOS VBLES | U5: =SUM(U3:U4) -> #REF!
B6: (Cifras Expresadas en Miles de Pesos Colombianos) | M6: GTOS FIJOS | N6: =+C19+C20+C26+C34+C48+C64+C71+C75 -> #REF! | P6: =+M6 -> GTOS FIJOS | Q6: =+N6 -> #REF! | R6: =+P6 -> GTOS FIJOS | S6: =+N6 -> #REF! | T6: =+P6 -> GTOS FIJOS | U6: =+Q6 -> #REF!
M7: P.EQ | N7: =+N6/O5 -> #REF! | P7: =+M7 -> P.EQ | Q7: =+Q5+Q6 -> #REF! | T7: RESULTADO PROYECTADO | U7: =+U5+U6 -> #REF!
C8: =+DATOS!H10 -> 2026-06 | D8: A.V | F8: =+DATOS!H11 -> 2025-06 | G8: A.V | I8: VARIACION | J8: A.H | M8: VENTAS PARA PTO DE.EQ | N8: =+N6/O5 -> #REF! | P8: RESULTADO | Q8: =+Q5+Q6 -> #REF! | R8: RESULTADO | S8: =SUM(S5:S6) -> #REF!
A9: 4120 | B9: Industria manufacturera | C9: =DATOS!#REF! -> #REF! | D9: =C9/$C$13 -> #REF! | F9: =DATOS!#REF! -> #REF! | G9: =+F9/$F$13 -> #REF! | I9: =+C9-F9 -> #REF! | J9: =+I9/F9 -> #REF!
A10: 4121 | B10: Ingresos por exportaciones | C10: =DATOS!#REF! -> #REF! | D10: =C10/$C$13 -> #REF! | F10: =DATOS!#REF! -> #REF! | G10: =+F10/$F$13 -> #REF! | I10: =+C10-F10 -> #REF! | J10: =IFERROR(I10/F10,0%) -> 0
A11: 4135 | B11: Comercio al por mayor y por menor | C11: =DATOS!C89 -> 481388 | D11: =C11/$C$13 -> #REF! | F11: =DATOS!F89 -> 518220 | G11: =+F11/$F$13 -> #REF! | I11: =+C11-F11 -> -36832 | J11: =IFERROR(I11/F11,0%) -> -0.071074061
A12: 4175 | B12: Devoluciones en ventas | C12: =-+DATOS!C95 -> -1237 | D12: =C12/$C$13 -> #REF! | F12: =-DATOS!F95 -> -703 | G12: =+F12/$F$13 -> #REF! | I12: =+C12-F12 -> -534 | J12: =+I12/F12 -> 0.75960171
B13: Ingresos netos | C13: =SUM(C9:C12) -> #REF! | D13: =C13/$C$13 -> #REF! | F13: =SUM(F9:F12) -> #REF! | G13: =+F13/$F$13 -> #REF! | I13: =+C13-F13 -> #REF! | J13: =+I13/F13 -> #REF! | M13: PUNTO DE EQUILIBRIO DE CAJA | N13: =+(N6+C108)/O5 -> #REF!
G14: =+F14/$F$13 -> #REF!
B15: Costo de Materia Prima | C15: =+C16 -> 0 | D15: =C15/$C$13 -> #REF! | F15: =+F16 -> -221817 | G15: =+F15/$F$13 -> #REF! | I15: =+C15-F15 -> 221817 | J15: =+I15/F15 -> -1 | M15: cta 73
B16: Materia Prima | C16: =-DATOS!C201 -> 0 | D16: =C16/$C$13 -> #REF! | F16: =-DATOS!F211 -> -221817 | G16: =+F16/$F$13 -> #REF! | I16: =+C16-F16 -> 221817 | J16: =+I16/F16 -> -1 | M16: AUMENTO CIF (SIN DEPRECIACION)
B17: MARGEN DE CONTRIBUCION 1 | C17: =+C13+C15 -> #REF! | D17: =C17/$C$13 -> #REF! | F17: =+F13+F15 -> #REF! | G17: =+F17/$F$13 -> #REF! | I17: =+C17-F17 -> #REF! | J17: =+I17/F17 -> #REF! | N17: 2024 | O17: 2023 | P17: VARIACION
D18: =C18/$C$13 -> #REF!
A19: 72 | B19: MOD (Mano de obra directa) | C19: =-DATOS!C205 -> -143 | D19: =C19/$C$13 -> #REF! | F19: =+-DATOS!F215 -> 0 | G19: =+F19/$F$13 -> #REF! | I19: =+C19-F19 -> -143 | J19: =IFERROR(I19/F19,0%) -> 0 | M19: HONORARIOS | N19: 8172 | O19: 8740 | P19: =N19-O19 -> -568
A20: 73 | B20: CIF (Costos indirectos de fabricacion) | C20: =-DATOS!C206 -> -84 | D20: =C20/$C$13 -> #REF! | F20: =-DATOS!F216 -> 0 | G20: =+F20/$F$13 -> #REF! | I20: =C20-F20 -> -84 | J20: =IFERROR(I20/F20,0%) -> 0 | M20: IMPUESTOS | N20: 8435 | O20: 10699 | P20: =N20-O20 -> -2264
M21: ARRENDAMIENTOS | N21: 33768 | O21: 28101 | P21: =N21-O21 -> 5667
B22: CMV | C22: =+C15+C19+C20 -> -227 | D22: =C22/$C$13 -> #REF! | F22: =+F15+F19+F20 -> -221817 | G22: =+F22/$F$13 -> #REF! | I22: =C22-F22 -> 221590 | J22: =IFERROR(I22/F22,0%) -> -0.99897663 | M22: CONTRIBUCIONES | N22: -1386 | O22: 848 | P22: =N22-O22 -> -2234
M23: SEGUROS | O23: 993 | P23: =N23-O23 -> -993
B24: GANANCIA BRUTA 2 | C24: =+C17+C19+C20 -> #REF! | D24: =C24/$C$13 -> #REF! | F24: =+F17+F19+F20 -> #REF! | G24: =+F24/$F$13 -> #REF! | I24: =+C24-F24 -> #REF! | J24: =+I24/F24 -> #REF! | M24: SERVICIOS | N24: 34088 | O24: 39185 | P24: =N24-O24 -> -5097
M25: MANTENIMIENTOS | N25: 2890 | O25: 4465 | P25: =N25-O25 -> -1575
B26: Otros Ingresos | C26: =+SUM(C27:C33) -> #REF! | D26: =C26/$C$13 -> #REF! | F26: =SUM(F27:F33) -> #REF! | G26: =+F26/$F$13 -> #REF! | I26: =+C26-F26 -> #REF! | J26: =+I26/F26 -> #REF! | M26: ADECUACIONES | N26: 1973 | O26: 1553 | P26: =N26-O26 -> 420
A27: 4205 | B27: Otras Ventas | C27: =DATOS!#REF! -> #REF! | D27: =C27/$C$13 -> #REF! | F27: =+DATOS!#REF! -> #REF! | G27: =+F27/$F$13 -> #REF! | I27: =+C27-F27 -> #REF! | J27: =+I27/F27 -> #REF! | M27: LEGALES | P27: =N27-O27 -> 0
A28: 4235 | B28: Servicios | C28: =DATOS!C99 -> 899 | D28: =C28/$C$13 -> #REF! | F28: =+DATOS!F99 -> 1421 | G28: =+F28/$F$13 -> #REF! | I28: =+C28-F28 -> -522 | J28: =+I28/F28 -> -0.36734694
A29: 4245 | B29: Utilidad en venta de propiedad planta y equipo | C29: =DATOS!#REF! -> #REF! | D29: =C29/$C$13 -> #REF! | F29: =+DATOS!#REF! -> #REF! | G29: =+F29/$F$13 -> #REF! | I29: =+C29-F29 -> #REF! | J29: =+I29/F29 -> #REF!
A30: 4250 | B30: Recuperacion de costos y gastos | C30: =+DATOS!C101 -> 3 | D30: =C30/$C$13 -> #REF! | F30: =+DATOS!F101 -> 4 | G30: =+F30/$F$13 -> #REF! | I30: =+C30-F30 -> -1 | J30: =IFERROR(I30/F30,0%) -> -0.25
A31: 4255 | B31: Indemnizaciones (incapacidades) | C31: =DATOS!C102 -> 0 | D31: =C31/$C$13 -> #REF! | F31: =+DATOS!F102 -> 0 | G31: =+F31/$F$13 -> #REF! | I31: =+C31-F31 -> 0 | J31: =IFERROR(I31/F31,0%) -> 0
A32: 4265 | B32: Ingresos ejercicios anteriores | C32: =DATOS!C103 -> 0 | D32: =C32/$C$13 -> #REF! | F32: =+DATOS!F103 -> 0 | G32: =+F32/$F$13 -> #REF! | I32: =+C32-F32 -> 0 | J32: =IFERROR(I32/F32,0%) -> 0
A33: 4295 | B33: Diversos | C33: =DATOS!C104 -> 720 | D33: =C33/$C$13 -> #REF! | F33: =+DATOS!F104 -> 519 | G33: =+F33/$F$13 -> #REF! | I33: =+C33-F33 -> 201 | J33: =+I33/F33 -> 0.38728324
B34: Gastos de Ventas | C34: =+SUM(C35:C47) -> #REF! | D34: =C34/$C$13 -> #REF! | F34: =SUM(F35:F47) -> #REF! | G34: =+F34/$F$13 -> #REF! | I34: =+C34-F34 -> #REF! | J34: =+I34/F34 -> #REF! | M34: DIVERSOS | N34: 11486 | O34: 13373 | P34: =N34-O34 -> -1887
A35: 5204 | B35: Aportes sobre la nomina | C35: =-DATOS!C115 -> -1523 | D35: =C35/$C$13 -> #REF! | F35: =-DATOS!F115 -> -1540 | G35: =+F35/$F$13 -> #REF! | I35: =+C35-F35 -> 17 | J35: =+I35/F35 -> -0.011038961
A36: 5205 | B36: Gasto de personal | C36: =-DATOS!C119 -> -50039 | D36: =C36/$C$13 -> #REF! | F36: =-DATOS!F119 -> -51262 | G36: =+F36/$F$13 -> #REF! | I36: =+C36-F36 -> 1223 | J36: =+I36/F36 -> -0.023857828
A37: 5210 | B37: Honorarios | C37: =-DATOS!C138 -> -25821.5 | D37: =C37/$C$13 -> #REF! | F37: =-DATOS!F138 -> -25646 | G37: =+F37/$F$13 -> #REF! | I37: =+C37-F37 -> -175.5 | J37: =+I37/F37 -> 0.0068431724
A38: 5215 | B38: Impuestos | C38: =-DATOS!C142 -> -4810 | D38: =C38/$C$13 -> #REF! | F38: =-DATOS!F142 -> -7525 | G38: =+F38/$F$13 -> #REF! | I38: =+C38-F38 -> 2715 | J38: =+I38/F38 -> -0.36079734
A39: 5220 | B39: Arrendamientos | C39: =-DATOS!C146 -> -85409 | D39: =C39/$C$13 -> #REF! | F39: =-DATOS!F146 -> -65084 | G39: =+F39/$F$13 -> #REF! | I39: =+C39-F39 -> -20325 | J39: =+I39/F39 -> 0.31228873
A40: 5225 | B40: Contribuciones y afiliaciones | C40: =-DATOS!C147 -> -9181 | D40: =C40/$C$13 -> #REF! | F40: =-DATOS!F147 -> -12012 | G40: =+F40/$F$13 -> #REF! | I40: =+C40-F40 -> 2831 | J40: =+I40/F40 -> -0.23568099
A41: 5230 | B41: Seguros | C41: =-DATOS!C148 -> 0 | D41: =C41/$C$13 -> #REF! | F41: =-DATOS!F148 -> 0 | G41: =+F41/$F$13 -> #REF! | I41: =+C41-F41 -> 0 | J41: =IFERROR(I41/F41,0%) -> 0
A42: 5235 | B42: Servicios | C42: =-DATOS!#REF! -> #REF! | D42: =C42/$C$13 -> #REF! | F42: =-DATOS!#REF! -> #REF! | G42: =+F42/$F$13 -> #REF! | I42: =+C42-F42 -> #REF! | J42: =IFERROR(I42/F42,0%) -> 0
A43: 5240 | B43: Gastos Legales | C43: =-DATOS!C158 -> -6283.5 | D43: =C43/$C$13 -> #REF! | F43: =-DATOS!F158 -> -3352.5 | G43: =+F43/$F$13 -> #REF! | I43: =+C43-F43 -> -2931 | J43: =IFERROR(I43/F43,0%) -> 0.87427293
A44: 5245 | B44: Mantenimientos | C44: =-DATOS!C168 -> -12 | D44: =C44/$C$13 -> #REF! | F44: =-DATOS!F168 -> 0 | G44: =+F44/$F$13 -> #REF! | I44: =+C44-F44 -> -12 | J44: =IFERROR(I44/F44,0%) -> 0
A45: 5260 | B45: Depreciacion | C45: =-DATOS!#REF! -> #REF! | D45: =C45/$C$13 -> #REF! | F45: =-DATOS!#REF! -> #REF! | G45: =+F45/$F$13 -> #REF! | I45: =+C45-F45 -> #REF! | J45: =IFERROR(I45/F45,0%) -> 0
A46: 5265 | B46: Amortizacion | C46: =-DATOS!#REF! -> #REF! | D46: =C46/$C$13 -> #REF! | F46: =-DATOS!#REF! -> #REF! | G46: =+F46/$F$13 -> #REF! | I46: =+C46-F46 -> #REF! | J46: =IFERROR(I46/F46,0%) -> 0
A47: 5295 | B47: Diversos | C47: =-DATOS!C184 -> -174 | D47: =C47/$C$13 -> #REF! | F47: =-DATOS!F184 -> -152 | G47: =+F47/$F$13 -> #REF! | I47: =+C47-F47 -> -22 | J47: =IFERROR(I47/F47,0%) -> 0.14473684
B48: Gastos de Administracion | C48: =SUM(C49:C63) -> #REF! | D48: =C48/$C$13 -> #REF! | F48: =SUM(F49:F63) -> #REF! | G48: =+F48/$F$13 -> #REF! | I48: =+C48-F48 -> #REF! | J48: =IFERROR(I48/F48,0%) -> 0 | M48: ACTIVOS CUANTIA MENOR | O48: 14598 | P48: =N48-O48 -> -14598
A49: 5104 | B49: Aportes sobre la nomina | C49: =-DATOS!#REF! -> #REF! | D49: =C49/$C$13 -> #REF! | F49: =-DATOS!#REF! -> #REF! | G49: =+F49/$F$13 -> #REF! | I49: =+C49-F49 -> #REF! | J49: =IFERROR(I49/F49,0%) -> 0
A50: 5105 | B50: Gastos de personal | C50: =-DATOS!#REF! -> #REF! | D50: =C50/$C$13 -> #REF! | F50: =-DATOS!#REF! -> #REF! | G50: =+F50/$F$13 -> #REF! | I50: =+C50-F50 -> #REF! | J50: =IFERROR(I50/F50,0%) -> 0
A51: 5110 | B51: Honorarios | C51: =-DATOS!#REF! -> #REF! | D51: =C51/$C$13 -> #REF! | F51: =-DATOS!#REF! -> #REF! | G51: =+F51/$F$13 -> #REF! | I51: =+C51-F51 -> #REF! | J51: =IFERROR(I51/F51,0%) -> 0
A52: 5115 | B52: Impuestos | C52: =-DATOS!#REF! -> #REF! | D52: =C52/$C$13 -> #REF! | F52: =-DATOS!#REF! -> #REF! | G52: =+F52/$F$13 -> #REF! | I52: =+C52-F52 -> #REF! | J52: =IFERROR(I52/F52,0%) -> 0
A53: 5120 | B53: Arrendamientos | C53: =-DATOS!#REF! -> #REF! | D53: =C53/$C$13 -> #REF! | F53: =-DATOS!#REF! -> #REF! | G53: =+F53/$F$13 -> #REF! | I53: =+C53-F53 -> #REF! | J53: =IFERROR(I53/F53,0%) -> 0
A54: 5125 | B54: Contribuciones y afiliaciones | C54: =-DATOS!#REF! -> #REF! | D54: =C54/$C$13 -> #REF! | F54: =-DATOS!#REF! -> #REF! | G54: =+F54/$F$13 -> #REF! | I54: =+C54-F54 -> #REF! | J54: =IFERROR(I54/F54,0%) -> 0
A55: 5130 | B55: Seguros | C55: =-DATOS!#REF! -> #REF! | D55: =C55/$C$13 -> #REF! | F55: =-DATOS!#REF! -> #REF! | G55: =+F55/$F$13 -> #REF! | I55: =+C55-F55 -> #REF! | J55: =IFERROR(I55/F55,0%) -> 0
A56: 5135 | B56: Servicios | C56: =-DATOS!#REF! -> #REF! | D56: =C56/$C$13 -> #REF! | F56: =-DATOS!#REF! -> #REF! | G56: =+F56/$F$13 -> #REF! | I56: =+C56-F56 -> #REF! | J56: =IFERROR(I56/F56,0%) -> 0
A57: 5140 | B57: Gastos legales | C57: =-DATOS!#REF! -> #REF! | D57: =C57/$C$13 -> #REF! | F57: =-DATOS!#REF! -> #REF! | G57: =+F57/$F$13 -> #REF! | I57: =+C57-F57 -> #REF! | J57: =IFERROR(I57/F57,0%) -> 0
A58: 5145 | B58: Mantenimiento y reparaciones | C58: =-DATOS!#REF! -> #REF! | D58: =C58/$C$13 -> #REF! | F58: =-DATOS!#REF! -> #REF! | G58: =+F58/$F$13 -> #REF! | I58: =+C58-F58 -> #REF! | J58: =IFERROR(I58/F58,0%) -> 0
A59: 5150 | B59: Reparaciones locativas | C59: =-DATOS!#REF! -> #REF! | D59: =C59/$C$13 -> #REF! | F59: =-DATOS!#REF! -> #REF! | G59: =+F59/$F$13 -> #REF! | I59: =+C59-F59 -> #REF! | J59: =IFERROR(I59/F59,0%) -> 0
A60: 5155 | B60: Gastos de Viaje | C60: =-DATOS!#REF! -> #REF! | D60: =C60/$C$13 -> #REF! | F60: =-DATOS!#REF! -> #REF! | G60: =+F60/$F$13 -> #REF! | I60: =+C60-F60 -> #REF! | J60: =IFERROR(I60/F60,0%) -> 0
... A63: 5195 | B63: Diversos | C63: =-DATOS!#REF! -> #REF! | D63: =C63/$C$13 -> #REF! | F63: =-DATOS!#REF! -> #REF! | G63: =+F63/$F$13 -> #REF! | I63: =+C63-F63 -> #REF! | J63: =IFERROR(I63/F63,0%) -> 0
B64: Otros gastos | C64: =+SUM(C65:C68) -> #REF! | D64: =C64/$C$13 -> #REF! | F64: =SUM(F65:F67) -> #REF! | G64: =+F64/$F$13 -> #REF! | I64: =+C64-F64 -> #REF! | J64: =IFERROR(I64/F64,0%) -> 0 | M64: OTROS | N64: 20731 | P64: =N64-O64 -> 20731
A65: 5505 | B65: Diferencia en cambio | C65: =-DATOS!#REF! -> #REF! | D65: =C65/$C$13 -> #REF! | F65: =-DATOS!#REF! -> #REF! | G65: =+F65/$F$13 -> #REF! | I65: =+C65-F65 -> #REF! | J65: =IFERROR(I65/F65,0%) -> 0
A66: 5515 | B66: Gastos extraordinarios | C66: =-DATOS!C196-DATOS!C197 -> -9239 | D66: =C66/$C$13 -> #REF! | F66: =-DATOS!#REF!-DATOS!F209 -> #REF! | G66: =+F66/$F$13 -> #REF! | I66: =+C66-F66 -> #REF! | J66: =IFERROR(I66/F66,0%) -> 0
A67: 5595 | B67: Gastos diversos | C67: =-+DATOS!C199 -> -131 | D67: =C67/$C$13 -> #REF! | F67: =-DATOS!#REF! -> #REF! | G67: =+F67/$F$13 -> #REF! | I67: =+C67-F67 -> #REF! | J67: =IFERROR(I67/F67,0%) -> 0
M68: TOTAL | N68: =SUM(N19:N64) -> 120157 | O68: =SUM(O19:O64) -> 122555 | P68: =SUM(P19:P64) -> -2398
B69: GANANCIA (PERDIDA) POR ACT. DE OP. | C69: =+C24+C26+C34+C48+C64 -> #REF! | D69: =C69/$C$13 -> #REF! | F69: =+F24+F26+F34+F48+F64 -> #REF! | G69: =+F69/$F$13 -> #REF! | I69: =+C69-F69 -> #REF! | J69: =IFERROR(I69/F69,0%) -> 0
B71: Ingresos Financieros | C71: =+SUM(C72:C74) -> 83 | D71: =C71/$C$13 -> #REF! | F71: =SUM(F72:F74) -> 324.5 | G71: =+F71/$F$13 -> #REF! | I71: =+C71-F71 -> -241.5 | J71: =IFERROR(I71/F71,0%) -> -0.74422188
A72: 431005 | B72: Intereses | C72: =+DATOS!C106 -> 0 | D72: =C72/$C$13 -> #REF! | F72: =+DATOS!F106 -> 217 | G72: =+F72/$F$13 -> #REF! | I72: =+C72-F72 -> -217 | J72: =IFERROR(I72/F72,0%) -> -1
A73: 431020 | B73: Diferencia en cambio | C73: =DATOS!C107 -> 0 | D73: =C73/$C$13 -> #REF! | F73: =+DATOS!F107 -> 0 | G73: =+F73/$F$13 -> #REF! | I73: =+C73-F73 -> 0 | J73: =IFERROR(I73/F73,0%) -> 0
A74: 431040 | B74: Descuentos | C74: =+DATOS!C108 -> 83 | D74: =C74/$C$13 -> #REF! | F74: =+DATOS!F108 -> 107.5 | G74: =+F74/$F$13 -> #REF! | I74: =+C74-F74 -> -24.5 | J74: =IFERROR(I74/F74,0%) -> -0.22790698
B75: Costos Financieros | C75: =+SUM(C76:C81) -> #REF! | D75: =C75/$C$13 -> #REF! | F75: =SUM(F76:F81) -> #REF! | G75: =+F75/$F$13 -> #REF! | I75: =+C75-F75 -> #REF! | J75: =IFERROR(I75/F75,0%) -> 0
A76: 530505 | B76: Gastos bancarios | C76: =-DATOS!C186 -> -68 | D76: =C76/$C$13 -> #REF! | F76: =-DATOS!F186 -> 0 | G76: =+F76/$F$13 -> #REF! | I76: =+C76-F76 -> -68 | J76: =IFERROR(I76/F76,0%) -> 0
A77: 530506 | B77: Gravamen 4 x 1000 | C77: =-DATOS!C187 -> -58 | D77: =C77/$C$13 -> #REF! | F77: =-DATOS!F187 -> -86 | G77: =+F77/$F$13 -> #REF! | I77: =+C77-F77 -> 28 | J77: =IFERROR(I77/F77,0%) -> -0.3255814
A78: 530515 | B78: Comisiones | C78: =-DATOS!#REF! -> #REF! | D78: =C78/$C$13 -> #REF! | F78: =-DATOS!#REF! -> #REF! | G78: =+F78/$F$13 -> #REF! | I78: =+C78-F78 -> #REF! | J78: =IFERROR(I78/F78,0%) -> 0
A79: 530516 | B79: Comisiones fondo de garantias | C79: =-DATOS!#REF! -> #REF! | D79: =C79/$C$13 -> #REF! | F79: 0 | G79: =+F79/$F$13 -> #REF! | I79: =+C79-F79 -> #REF! | J79: =IFERROR(I79/F79,0%) -> 0
A80: 530517 | B80: Comision Factoring | C80: =-DATOS!C188 -> -5 | D80: =C80/$C$13 -> #REF! | F80: =-DATOS!#REF! -> #REF! | G80: =+F80/$F$13 -> #REF! | I80: =+C80-F80 -> #REF! | J80: =IFERROR(I80/F80,0%) -> 0
A81: 530520-21-22 | B81: Intereses | C81: =-DATOS!C192 -> -5501 | D81: =C81/$C$13 -> #REF! | F81: =-DATOS!F192 -> -456 | G81: =+F81/$F$13 -> #REF! | I81: =+C81-F81 -> -5045 | J81: =IFERROR(I81/F81,0%) -> 11.063596
B83: GANANCIA (PERDIDA), ANTES DE IMP. | C83: =+C69+C71+C75 -> #REF! | D83: =C83/$C$13 -> #REF! | F83: =+F69+F71+F75 -> #REF! | G83: =+F83/$F$13 -> #REF! | I83: =+C83-F83 -> #REF! | J83: =IFERROR(I83/F83,0%) -> 0
B85: Impuesto a las ganancias | C85: =+C86+C87 -> -13522 | D85: =C85/$C$13 -> #REF! | F85: =+F87+F86 -> #REF! | G85: =+F85/$F$13 -> #REF! | I85: =+C85-F85 -> #REF! | J85: =IFERROR(I85/F85,0%) -> 0
A86: 5402 | B86: Diferido | C86: =-DATOS!C193 -> -12703 | D86: =C86/$C$13 -> #REF! | F86: =-+DATOS!F202 -> -362 | G86: =+F86/$F$13 -> #REF! | I86: =+C86-F86 -> -12341 | J86: =IFERROR(I86/F86,0%) -> 34.09116
A87: 540505 | B87: Corriente | C87: =-DATOS!C194 -> -819 | D87: =C87/$C$13 -> #REF! | F87: =-F83*51.9% -> #REF! | G87: =+F87/$F$13 -> #REF! | I87: =+C87-F87 -> #REF! | J87: =IFERROR(I87/F87,0%) -> 0
B89: GANANCIA (PERDIDA), NETA | C89: =+C83+C85 -> #REF! | D89: =C89/$C$13 -> #REF! | F89: =+F83+F85 -> #REF! | G89: =+F89/$F$13 -> #REF! | I89: =+C89-F89 -> #REF! | J89: =IFERROR(I89/F89,0%) -> 0
B91: RESULTADO INTEGRAL TOTAL | C91: =+C89 -> #REF! | D91: =C91/$C$13 -> #REF! | F91: =+F89 -> #REF! | G91: =+F91/$F$13 -> #REF! | I91: =+C91-F91 -> #REF! | J91: =IFERROR(I91/F91,0%) -> 0
B93: DEPRECIACION | C93: =+DATOS!#REF! -> #REF! | D93: =C93/C13 -> #REF! | F93: =+DATOS!#REF! -> #REF! | G93: =F93/$F$13 -> #REF! | I93: =C93-F93 -> #REF! | J93: =IFERROR(I93/F93,0%) -> 0
B94: AMORTIZACION | C94: =+DATOS!#REF! -> #REF! | D94: =C94/C13 -> #REF! | F94: =+DATOS!#REF! -> #REF! | G94: =F94/$F$13 -> #REF! | I94: =C94-F94 -> #REF! | J94: =IFERROR(I94/F94,0%) -> 0
B95: PROV IND Y CCIO | C95: 0 | D95: =C95/C15 -> #DIV/0! | G95: =F95/$F$13 -> #REF! | I95: =C95-F95 -> 0 | J95: =IFERROR(I95/F95,0%) -> 0
B96: RESULTADO REAL DEL MES | C96: =C91+C93+C94+C95 -> #REF! | D96: =+C96/C13 -> #REF! | F96: =+F91+F93+F94 -> #REF! | G96: =+F96/F13 -> #REF! | I96: =C96-F96 -> #REF! | J96: =IFERROR(I96/F96,0%) -> 0
B98: CTRL | C98: =+DATOS!C80 -> -692.5 | F98: =+DATOS!E80 -> -5686.5
C99: =C91-C98 -> #REF! | F99: =+F91-F98 -> #REF!
B104: DEPRECIACIONES Y AMORTIZACIONES | C104: =+DATOS!#REF!+DATOS!#REF! -> #REF!
B105: PROVISION ICA | C105: =C95 -> 0
B106: PROVISION PRESTACIONES SOCIALES | C106: =+IF(DATOS!#REF!>0,DATOS!#REF!,0) -> #REF!
B107: ABONOS OBL FRAS | C107: =+DATOS!#REF! -> #REF!
C108: =C104+C105+C106+C107 -> #REF!

Sheet 1. OBSERVACIONES
A1: =+DATOS!H6 -> GRUPO DE LOLITA SAS
A2: =+DATOS!H7 -> NIT: 900.307.969-5
A3: =+DATOS!H8 -> A 30 DE JUNIO DE 2026 Y 2025
A4: CIFRAS EN MILES DE PESOS
E6: IVA BIMESTRE 1 | F6: 83590
C7: MES | D7: ACUMULADO | E7: IVA BIMESTRE 2 | F7: 81373
E8: IVA BIMESTRE 3 | F8: 61703
B9: RETENCION POR PAGAR | C9: =+DATOS!C52 -> 14503 | E9: IVA BIMESTRE 4 | F9: 0
E10: IVA BIMESTRE 5 | F10: 0
B11: IVA PERIODO | C11: =+SUMIF('6.BP2026'!A:A,2408,'6.BP2026'!H:H)-SUMIF('6.BP2026'!A:A,2408,'6.BP2026'!G:G)-SUMIF('6.BP2026'!A:A,240899,'6.BP2026'!H:H)+SUMIF('6.BP2026'!A:A,240899,'6.BP2026'!G:G) -> 30921 | D11: =-SUMIF('6.BP2026'!A:A,2408,'6.BP2026'!I:I)+F6+F7+F8+F9+F10 -> 226666
B12: PRESION DE IVA | C12: =+C11/('2.E.R.I. MES-ACUMULADO'!CG13) -> 0.064420361 | D12: =+D11/DATOS!D86 -> 0.073106049
A17: 1105 | B17: CAJA: | C17: =+DATOS!C6 -> 462620
B19: DETALLE CAJAS | C19: SALDO | D19: BASE | E19: DIFERENCIA | F19: OBSERVACION
B20: CAJA TRANSITORIA | C20: 456921 | D20: 0 | E20: =C20-D20 -> 456921 | F20: Caja de ajustes
B21: CAJA UNICENTRO | C21: 300 | D21: 300 | E21: =C21-D21 -> 0
B22: CAJAS MENORES | C22: 3900 | D22: 3900 | E22: =C22-D22 -> 0
B23: CAJA PUNTO CLAVE | C23: 300 | D23: 300 | E23: =C23-D23 -> 0
B24: CAJA LIBERTAD | C24: 300 | D24: 300 | E24: =C24-D24 -> 0
B25: CAJA PLAZA FABRICATO | C25: 0 | D25: 0 | E25: =C25-D25 -> 0
B26: CAJA MONTERREY | C26: 300 | D26: 300 | E26: =C26-D26 -> 0
B27: CAJA CLINICA PRADO | C27: 300 | D27: 300 | E27: =C27-D27 -> 0
B28: CAJA TORRE MEDICA | C28: 300 | D28: 300 | E28: =C28-D28 -> 0
B29: DIFERENCIA | C29: =SUM(C20:C28) -> 462621 | D29: =SUM(D20:D28) -> 5700 | E29: =SUM(E20:E28) -> 456921
C30: =+C17-C29 -> -1
A32: 1110 | B32: BANCOS | C32: =+DATOS!C7 -> 34966 | D32: OBSERVACION
B33: CTA B.OCCIDENTE 9426 | C33: 867 | D33: Conciliada con extracto
B34: HELM BANK - ITAU 1190 | C34: 36 | D34: Conciliada con extracto
B35: CTA B.BOGOTA 3199 | C35: 730 | D35: Conciliada con extracto
B36: HELMBANK - ITAU 2545 | C36: 94 | D36: Conciliada con extracto
B37: HELMBANK - ITAU 2624 | C37: 2502 | D37: Conciliada con extracto
B38: BANCO COLPATRIA 3358 | C38: 17 | D38: Conciliada con extracto
B39: CUENTA PUENTE 4451 BBIA | C39: 30721 | D39: Conciliada con extracto
C40: =SUM(C33:C39)-C32 -> 1
A42: 1120 | B42: BANCOS | C42: =+DATOS!C8 -> 37524 | D42: OBSERVACION
B43: CTA BANCOLOMBIA AHO 8271 | C43: 10 | D43: Conciliada con extracto.
B44: BANCO DAVIVIENDA 7872 | C44: 37515 | D44: Conciliada con extracto.
C45: =SUM(C43:C44)-C42 -> 1
A47: 1130 | B47: FIDUCUENTA | C47: =+DATOS!C9 -> 41670 | D47: OBSERVACION
B48: BANCO DE DAVIVIENDA CTA 3122 | C48: 420 | D48: Conciliada con extracto.
B49: BANCOLOMBIA | C49: 41250 | D49: Conciliada con extracto.
C50: =+C47-C48-C49 -> 0
A53: 1305 | B53: CLIENTES: | C53: =+DATOS!C11 -> 21421
B55: CLIENTE | C55: MODULO | D55: 1305 CONTAB | E55: 28 CONTAB | F55: DIFERENCIAS
B56: SODEXO SERVICIOS DE BENEFICIOS | C56: 345.686 | D56: 476 | E56: =-224-27 -> -251 | F56: =C56-(D56+E56) -> 120.686
B57: INSTITUTO DE LAS HERMANAS DE JESUS REDENTOR | C57: 200 | D57: 0 | E57: 0 | F57: =C57-(D57+E57) -> 200
B58: EMPRESAS PUBLICAS DE MEDELLIN | C58: -1138.369 | D58: 1950 | E58: 0 | F58: =C58-(D58+E58) -> -3088.369
B59: DE LOLITA RESTO CAFE S.A.S | C59: 1950.4 | D59: 1950 | E59: 0 | F59: =C59-(D59+E59) -> 0.4
B60: RAPPI S.A.S | C60: 827.655 | D60: 1067 | E60: -933 | F60: =C60-(D60+E60) -> 693.655
B61: SOY TU PEDIATRA INSTITUCION PRESTADORA DE SERVICIO | C61: 206.2 | D61: 206 | E61: -6 | F61: =C61-(D61+E61) -> 6.2
B62: NUTRIENDO ALMAS S.A.S | C62: 17570.109 | D62: 17570 | E62: 0 | F62: =C62-(D62+E62) -> 0.1089
B63: DIANA CAROLINA OSORIO PADILLA | C63: 150 | D63: 150 | F63: =C63-(D63+E63) -> 0
F64: =C64-(D64+E64) -> 0
B67: TOTAL | C67: =SUM(C56:C66) -> 20111.681 | D67: =SUM(D56:D66) -> 23369 | E67: =SUM(E64:E66) -> 0 | F67: =SUM(F64:F66) -> 0
D68: =+C53-D67 -> -1948
A70: 1325 | B70: CXC A SOCIOS Y ACCIONISTAS | C70: =+DATOS!C12 -> 0
C71: =+C72 -> 0
C72: 0
C73: =+C71-C70 -> 0
A75: 1330 | B75: ANTICIPOS A PROVEEDORES | C75: =+DATOS!C13 -> 327590 | D75: OBSERVACION
B76: ANDRES MONTOYA | C76: 3482
B77: PALLOMARO S.A | C77: 3819
B78: CREALA LLC | C78: 1796
B79: MARIO FERNANDO FILEVICH | C79: 740
B80: CIUDADELA COMERCIAL UNICENTRO | C80: 7502
B81: MARIO FERNANDO FILEVICH | C81: =28432+2691+5166 -> 36289 | D81: Anticipos Utilidades
B82: ANDREA VELASQUEZ | C82: 27460
B83: CATALINA MARIA MEJIA AGUDELO | C83: 12483
B84: JOSE RICARDO LOPERA | C84: 2922
B85: ANDRES FELIPE MONTOYA VELEZ | C85: 18357
B86: SERGIO BARTH | C86: 41261
B87: RAZEM S.A.S | C87: 3596
B88: JULIETA FILEVICH GIRALDO | C88: 43881
B89: MARTIN LOPERA VELASQUEZ | C89: 66728
B90: SAMUEL FILEVICH GIRALDO | C90: 42180
B91: CRISTOBAL LOPERA VELAZQUEZ | C91: 15094
C93: =+SUM(C76:C92)-C75 -> 0
A95: 1365 | B95: PRESTAMOS A EMPLEADOS | C95: =+DATOS!C15 -> 363 | D95: OBSERVACION
B96: CASTILLO YEPEZ YAMILETH COROMO | C96: 12 | D96: Deudores de caja -
B97: PAULA SERNA
B98: VERONICA MORENO | C98: 19
B99: NUBIA ELSY MONTOYA " | C99: 4
B100: MARIA EUGENIA VASQUEZ | C100: 122 | D100: Deudores de caja -falta registrar el prestamo
B101: SUAREZ BERMON SOLENNYS RUTH | C101: 165 | D101: Deudores de caja -falta registrar el prestamo
B102: ERIKA JULIETH BORJA ZAPATA | C102: 41
C103: =SUM(C96:C102)-C95 -> 0
A105: 1380 | B105: OTRAS CUENTAS POR COBRAR | C105: =+DATOS!C16 -> 87931 | D105: OBSERVACION
B106: GRUPO ATOCHA S.A.S | C106: 672 | D106: Cxc entre compañias
B107: CONVOCAMOS SERES DE AMOR S.A.S | C107: 30111 | D107: Cxc entre compañias
B108: OASIS URBANOS S.A.S. | C108: =13462+35000 -> 48462 | D108: Cxc entre compañias
B109: INSPIRAMOS EL MAÑANA S.A.S | C109: 7916 | D109: Cxc inspiramos el mañana
B110: CONVOCAMOS SERES DE AMOR S.A.S | C110: 0 | D110: Cxc nutriendo almas
B111: SODEXO SERVICIO DE BENEFICIOS | C111: 587
B112: IMPUESTO EN CUENTA PUNTE BANCOLOMBIA | C112: 183 | D112: Bonos sodexo
C113: =SUM(C106:C112)-C105 -> 0
A115: 14 | B115: INVENTARIOS | C115: =+DATOS!C17 -> 78249 | D115: OBSERVACION
B116: PLAZA DE LA LIBERTAD | C116: =+'2.E.R.I. MES-ACUMULADO'!CD18 -> 8089 | D116: Inventarios de acuerdo a información administrativa
B117: CLINICA DEL PRADO | C117: =+'2.E.R.I. MES-ACUMULADO'!CC18 -> 11243
B118: MAYORCA PISO 4 | C118: =+'2.E.R.I. MES-ACUMULADO'!CA18 -> 11879
B119: MEGAPLAZA | C119: =+'2.E.R.I. MES-ACUMULADO'!CB18 -> 11033
B120: MONTERREY | C120: =+'2.E.R.I. MES-ACUMULADO'!BX18 -> 7348
...

Sheet 2.E.R.I. MES-ACUMULADO
B1: =+DATOS!H6 -> GRUPO DE LOLITA SAS
B2: =+DATOS!H7 -> NIT: 900.307.969-5
B3: ESTADO DE RESULTADOS INTEGRAL ACUMULADO
B4: =+DATOS!H8 -> A 30 DE JUNIO DE 2026 Y 2025
B5: (Cifras Expresadas en Miles de Pesos Colombianos)
D8: MONTERREY (1004) | E8: TORRE MEDICA | F8: PUNTO CLAVE | G8: MAYORCA PISO 4 | H8: MEGAPLAZA | I8: CLINICA DEL PRADO | J8: LA LIBERTAD | K8: PLAZA FABRICATO | L8: UNICENTRO | M8: 2025-12 | N8: A.V | P8: MONTERREY (1004) | Q8: TORRE MEDICA | R8: PUNTO CLAVE | S8: MAYORCA PISO 4 | T8: MEGAPLAZA | U8: CLINICA DEL PRADO | V8: LA LIBERTAD | W8: PLAZA FABRICATO | X8: UNICENTRO | Y8: 2026-01 | Z8: A.V | AB8: MONTERREY (1004) | AC8: TORRE MEDICA | AD8: PUNTO CLAVE | AE8: MAYORCA PISO 4 | AF8: MEGAPLAZA | AG8: CLINICA DEL PRADO | AH8: LA LIBERTAD | AI8: PLAZA FABRICATO | AJ8: UNICENTRO | AK8: 2026-02 | AL8: A.V | AN8: MONTERREY (1004) | AO8: TORRE MEDICA | AP8: PUNTO CLAVE | AQ8: MAYORCA PISO 4 | AR8: MEGAPLAZA | AS8: CLINICA DEL PRADO | AT8: LA LIBERTAD | AU8: PLAZA FABRICATO | AV8: UNICENTRO | AW8: 2026-03 | AX8: A.V | AZ8: MONTERREY (1004) | BA8: TORRE MEDICA | BB8: PUNTO CLAVE | BC8: MAYORCA PISO 4 | BD8: MEGAPLAZA | BE8: CLINICA DEL PRADO | BF8: LA LIBERTAD | BG8: PLAZA FABRICATO | BH8: UNICENTRO | BI8: 2026-04 | BJ8: A.V | BL8: MONTERREY (1004) | BM8: TORRE MEDICA | BN8: PUNTO CLAVE | BO8: MAYORCA PISO 4 | BP8: MEGAPLAZA | BQ8: CLINICA DEL PRADO | BR8: LA LIBERTAD | BS8: PLAZA FABRICATO | BT8: UNICENTRO | BU8: 2026-05 | BV8: A.V | BX8: MONTERREY (1004) | BY8: TORRE MEDICA | BZ8: PUNTO CLAVE | CA8: MAYORCA PISO 4 | CB8: MEGAPLAZA | CC8: CLINICA DEL PRADO | CD8: LA LIBERTAD | CE8: PLAZA FABRICATO | CF8: UNICENTRO | CG8: 2026-06 | CH8: A.V | CJ8: VARIACION MES 2025 | CK8: A.H | CM8: ACUMULADO 2026 | CN8: A.V | CP8: =+DATOS!H11 -> 2025-06 | CQ8: A.V | CS8: ACUMULADO 2025 | CT8: A.V | CV8: VARIACION ACUMULADO 2024-2025 | CW8: A.H
A9: 4120 | B9: Fletes | D9: 0 | E9: 0 | F9: 0 | G9: 0 | H9: 0 | I9: 0 | J9: 0 | K9: 0 | L9: 0 | M9: =SUM(D9:L9) -> 0 | N9: =+M9/M$13 -> 0 | P9: 0 | Q9: 0 | R9: 0 | S9: 0 | T9: 0 | U9: 0 | V9: 0 | W9: 0 | X9: 0 | Y9: =SUM(P9:X9) -> 0 | Z9: =+Y9/Y$13 -> 0 | AB9: 0 | AC9: 0 | AD9: 0 | AE9: 0 | AF9: 0 | AG9: 0 | AH9: 0 | AI9: 0 | AJ9: 0 | AK9: =SUM(AB9:AJ9) -> 0 | AL9: =+AK9/AK$13 -> 0 | AN9: 0 | AO9: 0 | AP9: 0 | AQ9: 0 | AR9: 0 | AS9: 0 | AT9: 0 | AU9: 0 | AV9: 0 | AW9: =SUM(AN9:AV9) -> 0 | AX9: =+AW9/AW$13 -> 0 | AZ9: 0 | BA9: 0 | BB9: 0 | BC9: 0 | BD9: 2150 | BE9: 0 | BF9: 0 | BG9: 0 | BH9: 0 | BI9: =SUM(AZ9:BH9) -> 2150 | BJ9: =+BI9/BI$13 -> 0.0043351669 | BL9: 0 | BM9: 0 | BN9: 0 | BO9: 0 | BP9: 0 | BQ9: 0 | BR9: 0 | BS9: 0 | BT9: 0 | BU9: =SUM(BL9:BT9) -> 0 | BV9: =+BU9/BU$13 -> 0 | BX9: 0 | BY9: 150 | BZ9: 0 | CA9: 0 | CB9: 0 | CC9: 0 | CD9: 0 | CE9: 0 | CF9: 0 | CG9: =SUM(BX9:CF9) -> 150 | CH9: =+CG9/CG$13 -> 0.00031250781 | CJ9: =+CG9-BU9 -> 150 | CK9: =IFERROR(+CJ9/BU9,0%) -> 0 | CM9: =+DATOS!D88 -> 2300 | CN9: =+CM9/CM$13 -> 0.00075606525
A10: 4135 | B10: Comercio al por mayor y por menor | D10: 79613 | E10: 55945 | F10: 43382 | G10: 99947 | H10: 121937 | I10: 84160 | J10: 66193 | K10: 128 | L10: 54110 | M10: =SUM(D10:L10) -> 605415 | N10: =+M10/M$13 -> 1.1993902 | P10: 75219 | Q10: 50610 | R10: 36913 | S10: 78052 | T10: 106919 | U10: 77091 | V10: 57803 | W10: 0 | X10: 50111 | Y10: =SUM(P10:X10) -> 532718 | Z10: =+Y10/Y$13 -> 1.0122292 | AB10: 66066 | AC10: 56451 | AD10: 40250 | AE10: 61467 | AF10: 85050 | AG10: 88096 | AH10: 67386 | AI10: 0 | AJ10: 42596 | AK10: =SUM(AB10:AJ10) -> 507362 | AL10: =+AK10/AK$13 -> 0.99143519 | AN10: 73018 | AO10: 60645 | AP10: 41896 | AQ10: 66667 | AR10: 87219 | AS10: 89204 | AT10: 65645 | AU10: 0 | AV10: 47848 | AW10: =SUM(AN10:AV10) -> 532142 | AX10: =+AW10/AW$13 -> 1.0021054 | AZ10: 60593 | BA10: 58536 | BB10: 39617 | BC10: 62449 | BD10: 86837 | BE10: 83657 | BF10: 61022 | BG10: 0 | BH10: 42115 | BI10: =SUM(AZ10:BH10) -> 494826 | BJ10: =+BI10/BI$13 -> 0.99774571 | BL10: 57292 | BM10: 56023 | BN10: 36128 | BO10: 63856 | BP10: 95263 | BQ10: 82402 | BR10: 61526 | BS10: 0 | BT10: 45700 | BU10: =SUM(BL10:BT10) -> 498190 | BV10: =+BU10/BU$13 -> 1.0022451 | BX10: 60078 | BY10: 55981 | BZ10: 36240 | CA10: 65529 | CB10: 78684 | CC10: 81938 | CD10: 57110 | CE10: 0 | CF10: 45828 | CG10: =SUM(BX10:CF10) -> 481388 | CH10: =+CG10/CG$13 -> 1.0029167 | CJ10: =+CG10-BU10 -> -16802 | CK10: =IFERROR(+CJ10/BU10,0%) -> -0.033726088 | CM10: =SUM(DATOS!D89:D94)-CM11 -> 3046631.5 | CN10: =+CM10/CM$13 -> 1.001501 | CP10: =+DATOS!F89+DATOS!F90+DATOS!F91+DATOS!F92+DATOS!F93 -> 518352.5 | CQ10: =+CP10/CP$13 -> 1.0061258 | CS10: =+DATOS!G89+DATOS!G90+DATOS!G91+DATOS!G92+DATOS!G93 -> 2938925.5 | CT10: =+CS10/CS$13 -> 0.99999762 | CV10: =+CM10-CS10 -> 107706 | CW10: =+IFERROR(CV10/CS10,0) -> 0.036648088
B11: Ingreso Ajuste Henkost | D11: -12 | E11: -23 | F11: -31 | G11: -32 | H11: -15 | I11: -33 | J11: -20 | K11: 0 | L11: -26 | M11: =SUM(D11:L11) -> -192 | N11: =+M11/M$13 -> -0.00038037201 | P11: -514 | Q11: -335 | R11: -409 | S11: -697 | T11: -1830 | U11: -963 | V11: -514 | W11: 0 | X11: -267 | Y11: =SUM(P11:X11) -> -5529 | Z11: =+Y11/Y$13 -> -0.010505774 | AB11: 532 | AC11: 410 | AD11: 326 | AE11: 540 | AF11: 1683 | AG11: 963 | AH11: 465 | AI11: 0 | AJ11: 285 | AK11: =SUM(AB11:AJ11) -> 5204 | AL11: =+AK11/AK$13 -> 0.010169127 | AN11: 35 | AO11: 0 | AP11: -89 | AQ11: -136 | AR11: 18 | AS11: 0 | AT11: 24 | AU11: 0 | AV11: -98 | AW11: =SUM(AN11:AV11) -> -246 | AX11: =+AW11/AW$13 -> -0.0004632559 | AZ11: 171 | BA11: -95 | BB11: -73 | BC11: -263 | BD11: -9 | BE11: 0 | BF11: 26 | BG11: 0 | BH11: 78 | BI11: =SUM(AZ11:BH11) -> -165 | BJ11: =+BI11/BI$13 -> -0.00033269885 | BL11: 29 | BM11: 0 | BN11: 43 | BO11: 184 | BP11: 118 | BQ11: 0 | BR11: -182 | BS11: 0 | BT11: -10 | BU11: =SUM(BL11:BT11) -> 182 | BV11: =+BU11/BU$13 -> 0.00036614267 | BX11: -29 | BY11: 0 | BZ11: -43 | CA11: -141 | CB11: -133 | CC11: 0 | CD11: 50 | CE11: 0 | CF11: -16 | CG11: =SUM(BX11:CF11) -> -312 | CH11: =+CG11/CG$13 -> -0.00065001625 | CJ11: =+CG11-BU11 -> -494 | CK11: =IFERROR(+CJ11/BU11,0%) -> -2.7142857 | CM11: =+Y11+AK11+CG11+AW11+BI11+BU11 -> -866 | CN11: =+CM11/CM$13 -> -0.000284675 | CP11: =+DATOS!F94 -> -2453 | CQ11: =+CP11/CP$13 -> -0.0047612901 | CS11: =+DATOS!G94 -> 4446 | CT11: =+CS11/CS$13 -> 0.0015127942 | CV11: =+CM11-CS11 -> -5312 | CW11: =+IFERROR(CV11/CS11,0) -> -1.1947818
A12: 4175 | B12: Devoluciones en ventas | D12: 0 | E12: -87 | F12: -38 | G12: -41 | H12: -100085 | I12: -123 | J12: 0 | K12: 0 | L12: -80 | M12: =SUM(D12:L12) -> -100454 | N12: =+M12/M$13 -> -0.19900984 | P12: 0 | Q12: -35 | R12: -134 | S12: -51 | T12: -446 | U12: -54 | V12: -116 | W12: 0 | X12: -71 | Y12: =SUM(P12:X12) -> -907 | Z12: =+Y12/Y$13 -> -0.0017234106 | AB12: 0 | AC12: -114 | AD12: -19 | AE12: -236 | AF12: -273 | AG12: -130 | AH12: -49 | AI12: 0 | AJ12: 0 | AK12: =SUM(AB12:AJ12) -> -821 | AL12: =+AK12/AK$13 -> -0.0016043146 | AN12: 0 | AO12: -167 | AP12: -155 | AQ12: -260 | AR12: -77 | AS12: -148 | AT12: -13 | AU12: 0 | AV12: -52 | AW12: =SUM(AN12:AV12) -> -872 | AX12: =+AW12/AW$13 -> -0.0016421103 | AZ12: 0 | BA12: -95 | BB12: -220 | BC12: -321 | BD12: -52 | BE12: 0 | BF12: -135 | BG12: 0 | BH12: -44 | BI12: =SUM(AZ12:BH12) -> -867 | BJ12: =+BI12/BI$13 -> -0.0017481812 | BL12: -29 | BM12: -201 | BN12: -89 | BO12: -401 | BP12: -24 | BQ12: -90 | BR12: -361 | BS12: 0 | BT12: -103 | BU12: =SUM(BL12:BT12) -> -1298 | BV12: =+BU12/BU$13 -> -0.0026112812 | BX12: -218 | BY12: -116 | BZ12: -151 | CA12: -407 | CB12: -199 | CC12: -41 | CD12: -78 | CE12: 0 | CF12: -28 | CG12: =SUM(BX12:CF12) -> -1238 | CH12: =+CG12/CG$13 -> -0.0025792311 | CJ12: =+CG12-BU12 -> 60 | CK12: =IFERROR(+CJ12/BU12,0%) -> -0.046224961 | CM12: =-DATOS!D95 -> -6000 | CN12: =+CM12/CM$13 -> -0.0019723441 | CP12: =-DATOS!F95 -> -703 | CQ12: =+CP12/CP$13 -> -0.0013645279 | CS12: =-DATOS!G95 -> -4439 | CT12: =+CS12/CS$13 -> -0.0015104124 | CV12: =+CM12-CS12 -> -1561 | CW12: =+IFERROR(CV12/CS12,0) -> 0.35165578
B13: INGRESOS NETOS | D13: =SUM(D9:D12) -> 79601 | E13: =SUM(E9:E12) -> 55835 | F13: =SUM(F9:F12) -> 43313 | G13: =SUM(G9:G12) -> 99874 | H13: =SUM(H9:H12) -> 21837 | I13: =SUM(I9:I12) -> 84004 | J13: =SUM(J9:J12) -> 66173 | K13: =SUM(K9:K12) -> 128 | ... M13: =SUM(M9:M12) -> 504769 | N13: =+M13/M$13 -> 1 | P13: =SUM(P9:P12) -> 74705 | Q13: =SUM(Q9:Q12) -> 50240 | R13: =SUM(R9:R12) -> 36370 | S13: =SUM(S9:S12) -> 77304 | T13: =SUM(T9:T12) -> 104643 | U13: =SUM(U9:U12) -> 76074 | V13: =SUM(V9:V12) -> 57173 | W13: =SUM(W9:W12) -> 0 | ... Y13: =SUM(Y9:Y12) -> 526282 | Z13: =+Y13/Y$13 -> 1 | AB13: =SUM(AB9:AB12) -> 66598 | AC13: =SUM(AC9:AC12) -> 56747 | AD13: =SUM(AD9:AD12) -> 40557 | AE13: =SUM(AE9:AE12) -> 61771 | AF13: =SUM(AF9:AF12) -> 86460 | AG13: =SUM(AG9:AG12) -> 88929 | AH13: =SUM(AH9:AH12) -> 67802 | AI13: =SUM(AI9:AI12) -> 0 | ... AK13: =SUM(AK9:AK12) -> 511745 | AL13: =+AK13/AK$13 -> 1 | AN13: =SUM(AN9:AN12) -> 73053 | AO13: =SUM(AO9:AO12) -> 60478 | AP13: =SUM(AP9:AP12) -> 41652 | AQ13: =SUM(AQ9:AQ12) -> 66271 | AR13: =SUM(AR9:AR12) -> 87160 | AS13: =SUM(AS9:AS12) -> 89056 | AT13: =SUM(AT9:AT12) -> 65656 | AU13: =SUM(AU9:AU12) -> 0 | ... AW13: =SUM(AW9:AW12) -> 531024 | AX13: =+AW13/AW$13 -> 1 | AZ13: =SUM(AZ9:AZ12) -> 60764 | BA13: =SUM(BA9:BA12) -> 58346 | BB13: =SUM(BB9:BB12) -> 39324 | BC13: =SUM(BC9:BC12) -> 61865 | BD13: =SUM(BD9:BD12) -> 88926 | BE13: =SUM(BE9:BE12) -> 83657 | BF13: =SUM(BF9:BF12) -> 60913 | BG13: =SUM(BG9:BG12) -> 0 | ... BI13: =SUM(BI9:BI12) -> 495944 | BJ13: =+BI13/BI$13 -> 1 | BL13: =SUM(BL9:BL12) -> 57292 | BM13: =SUM(BM9:BM12) -> 55822 | BN13: =SUM(BN9:BN12) -> 36082 | BO13: =SUM(BO9:BO12) -> 63639 | BP13: =SUM(BP9:BP12) -> 95357 | BQ13: =SUM(BQ9:BQ12) -> 82312 | BR13: =SUM(BR9:BR12) -> 60983 | BS13: =SUM(BS9:BS12) -> 0 | ... BU13: =SUM(BU9:BU12) -> 497074 | BV13: =+BU13/BU$13 -> 1 | BX13: =SUM(BX9:BX12) -> 59831 | BY13: =SUM(BY9:BY12) -> 56015 | BZ13: =SUM(BZ9:BZ12) -> 36046 | CA13: =SUM(CA9:CA12) -> 64981 | CB13: =SUM(CB9:CB12) -> 78352 | CC13: =SUM(CC9:CC12) -> 81897 | CD13: =SUM(CD9:CD12) -> 57082 | CE13: =SUM(CE9:CE12) -> 0 | ... CG13: =SUM(CG9:CG12) -> 479988 | CH13: =+CG13/CG$13 -> 1 | CJ13: =+CG13-BU13 -> -17086 | CK13: =IFERROR(+CJ13/BU13,0%) -> -0.034373152 | CM13: =SUM(CM9:CM12) -> 3042065.5 | CN13: =+CM13/CM$13 -> 1 | CP13: =SUM(CP10:CP12) -> 515196.5 | CQ13: =+CP13/CP$13 -> 1 | CR13: =+CP13-DATOS!F87 -> 0 | CS13: =SUM(CS10:CS12) -> 2938932.5 | CT13: =+CS13/CS$13 -> 1 | CV13: =+CM13-CS13 -> 103133 | CW13: =+IFERROR(CV13/CS13,0) -> 0.035091993
CP14: =+CP15+DATOS!F212 -> 1 | CS14: =+CS15+DATOS!G212 -> 1
A15: 6 | B15: CMV | D15: =-(D16+D17-D18) -> -29927 | E15: =-(E16+E17-E18) -> -27561 | F15: =-(F16+F17-F18) -> -18660 | G15: =-(G16+G17-G18) -> -39572 | H15: =-(H16+H17-H18) -> -43047 | I15: =-(I16+I17-I18) -> -37823 | J15: =-(J16+J17-J18) -> -27747 | K15: =-(K16+K17-K18) -> 0 | ... M15: =-(M16+M17-M18) -> -248528 | N15: =+M15/M$13 -> -0.49235987 | P15: =-(P16+P17-P18) -> -26742 | Q15: =-(Q16+Q17-Q18) -> -22587 | R15: =-(R16+R17-R18) -> -14569 | S15: =-(S16+S17-S18) -> -27304 | T15: =-(T16+T17-T18) -> -36585 | U15: =-(U16+U17-U18) -> -32983 | V15: =-(V16+V17-V18) -> -25133 | W15: =-(W16+W17-W18) -> 0 | ... Y15: =-(Y16+Y17-Y18) -> -205215 | Z15: =+Y15/Y$13 -> -0.38993353 | AB15: =-(AB16+AB17-AB18) -> -26091 | AC15: =-(AC16+AC17-AC18) -> -28050 | AD15: =-(AD16+AD17-AD18) -> -16919 | AE15: =-(AE16+AE17-AE18) -> -25310 | AF15: =-(AF16+AF17-AF18) -> -32754 | AG15: =-(AG16+AG17-AG18) -> -42645 | AH15: =-(AH16+AH17-AH18) -> -31887 | AI15: =-(AI16+AI17-AI18) -> 0 | ... AK15: =-(AK16+AK17-AK18) -> -224232 | AL15: =+AK15/AK$13 -> -0.43817135 | AN15: =-(AN16+AN17-AN18) -> -29508 | AO15: =-(AO16+AO17-AO18) -> -28554 | AP15: =-(AP16+AP17-AP18) -> -19049 | AQ15: =-(AQ16+AQ17-AQ18) -> -25775 | AR15: =-(AR16+AR17-AR18) -> -32385 | AS15: =-(AS16+AS17-AS18) -> -41083 | AT15: =-(AT16+AT17-AT18) -> -28494 | AU15: =-(AU16+AU17-AU18) -> 0 | ... AW15: =-(AW16+AW17-AW18) -> -224593 | AX15: =+AW15/AW$13 -> -0.42294322 | AZ15: =-(AZ16+AZ17-AZ18) -> -25403 | BA15: =-(BA16+BA17-BA18) -> -28195 | BB15: =-(BB16+BB17-BB18) -> -17528 | BC15: =-(BC16+BC17-BC18) -> -24913 | BD15: =-(BD16+BD17-BD18) -> -32295 | BE15: =-(BE16+BE17-BE18) -> -38201 | BF15: =-(BF16+BF17-BF18) -> -27079 | BG15: =-(BG16+BG17-BG18) -> 0 | ... BI15: =-(BI16+BI17-BI18) -> -214448 | BJ15: =+BI15/BI$13 -> -0.43240366 | BL15: =-(BL16+BL17-BL18) -> -23715 | BM15: =-(BM16+BM17-BM18) -> -26391 | BN15: =-(BN16+BN17-BN18) -> -15247 | BO15: =-(BO16+BO17-BO18) -> -25222 | BP15: =-(BP16+BP17-BP18) -> -35192 | BQ15: =-(BQ16+BQ17-BQ18) -> -37970 | BR15: =-(BR16+BR17-BR18) -> -27474 | BS15: =-(BS16+BS17-BS18) -> 0 | ... BU15: =-(BU16+BU17-BU18) -> -210791 | BV15: =+BU15/BU$13 -> -0.42406362 | BX15: =-(BX16+BX17-BX18) -> -22228 | BY15: =-(BY16+BY17-BY18) -> -25858 | BZ15: =-(BZ16+BZ17-BZ18) -> -15501 | CA15: =-(CA16+CA17-CA18) -> -25223 | CB15: =-(CB16+CB17-CB18) -> -29512 | CC15: =-(CC16+CC17-CC18) -> -37240 | CD15: =-(CD16+CD17-CD18) -> -25151 | CE15: =-(CE16+CE17-CE18) -> 0 | ... CG15: =-(CG16+CG17-CG18) -> -199859 | CH15: =+CG15/CG$13 -> -0.41638333 | CJ15: =+CG15-BU15 -> 10932 | CK15: =IFERROR(+CJ15/BU15,0%) -> -0.051861797 | CM15: =-(CM16+CM17-CM18) -> -1279138 | CN15: =+CM15/CM$13 -> -0.42048339 | CP15: =-(CP16+CP17-CP18) -> -221816 | CQ15: =+CP15/CP$13 -> -0.4305464 | CR15: =+CP15+DATOS!F212 -> 1 | CS15: =-(CS16+CS17-CS18) -> -1241064 | CT15: =+CS15/CS$13 -> -0.42228394 | CV15: =+CM15-CS15 -> -38074 | CW15: =+IFERROR(CV15/CS15,0) -> 0.030678515
A16: 14 | B16: Inventario inicial | D16: 7928 | E16: 11481 | F16: 8062 | G16: 9639 | H16: 8472 | I16: 14525 | J16: 9215 | K16: 0 | L16: 8636 | M16: =SUM(D16:L16) -> 77958 | N16: =+M16/M$13 -> 0.15444292 | P16: 7673 | Q16: 7927 | R16: 8345 | S16: 10712 | T16: 11516 | U16: 13198 | V16: 9559 | W16: 0 | X16: 9102 | Y16: =SUM(P16:X16) -> 78032 | Z16: =+Y16/Y$13 -> 0.14827032 | AB16: 7951 | AC16: 11554 | AD16: 8986 | AE16: 13481 | AF16: 12941 | AG16: 16261 | AH16: 9926 | AI16: 0 | AJ16: 9777 | AK16: =SUM(AB16:AJ16) -> 90877 | AL16: =+AK16/AK$13 -> 0.17758259 | AN16: 8244 | AO16: 10331 | AP16: 8193 | AQ16: 11096 | AR16: 11019 | AS16: 14952 | AT16: 9277 | AU16: 0 | AV16: 9414 | AW16: =SUM(AN16:AV16) -> 82526 | AX16: =+AW16/AW$13 -> 0.15540917 | AZ16: 8882 | BA16: 10926 | BB16: 8362 | BC16: 10210 | BD16: 11617 | BE16: 12673 | BF16: 7939 | BG16: 0 | BH16: 9642 | BI16: =SUM(AZ16:BH16) -> 80251 | BJ16: =+BI16/BI$13 -> 0.16181464 | BL16: 10032 | BM16: 10668 | BN16: 7927 | BO16: 11078 | BP16: 14210 | BQ16: 12520 | BR16: 8749 | BS16: 0 | BT16: 8102 | BU16: =SUM(BL16:BT16) -> 83286 | BV16: =+BU16/BU$13 -> 0.16755252 | BX16: 7337 | BY16: 10880 | BZ16: 8082 | CA16: 10491 | CB16: 9193 | CC16: 12051 | CD16: 9458 | CE16: 0 | CF16: 7508 | CG16: =SUM(BX16:CF16) -> 75000 | CH16: =+CG16/CG$13 -> 0.15625391 | CJ16: =+CG16-BU16 -> -8286 | CK16: =IFERROR(+CJ16/BU16,0%) -> -0.099488509 | CM16: =+Y16 -> 78032 | CN16: =+CM16/CM$13 -> 0.025650993 | CP16: =+SUMIF('7.BP2025'!A:A,14,'7.BP2025'!F:F) -> 92469 | CQ16: =+CP16/CP$13 -> 0.17948297 | CS16: 70972 | CT16: =+CS16/CS$13 -> 0.024148904 | CV16: =+CM16-CS16 -> 7060 | CW16: =+IFERROR(CV16/CS16,0) -> 0.09947585
A17: 14 | B17: Compras | D17: 29672 | E17: 24007 | F17: 18943 | G17: 40645 | H17: 46091 | I17: 36496 | J17: 28091 | K17: 0 | L17: 24657 | M17: =SUM(D17:L17) -> 248602 | N17: =+M17/M$13 -> 0.49250647 | P17: 27020 | Q17: 26214 | R17: 15210 | S17: 30073 | T17: 38010 | U17: 36046 | V17: 25500 | W17: 0 | X17: 19987 | Y17: =SUM(P17:X17) -> 218060 | Z17: =+Y17/Y$13 -> 0.4143406 | AB17: 26384 | AC17: 26827 | AD17: 16126 | AE17: 22925 | AF17: 30832 | AG17: 41336 | AH17: 31238 | AI17: 0 | AJ17: 20213 | AK17: =SUM(AB17:AJ17) -> 215881 | AL17: =+AK17/AK$13 -> 0.42185268 | AN17: 30146 | AO17: 29149 | AP17: 19218 | AQ17: 24889 | AR17: 32983 | AS17: 38804 | AT17: 27156 | AU17: 0 | AV17: 19973 | AW17: =SUM(AN17:AV17) -> 222318 | AX17: =+AW17/AW$13 -> 0.41865904 | AZ17: 26553 | BA17: 27937 | BB17: 17093 | BC17: 25781 | BD17: 34888 | BE17: 38048 | BF17: 27889 | BG17: 0 | BH17: 19294 | BI17: =SUM(AZ17:BH17) -> 217483 | BJ17: =+BI17/BI$13 -> 0.4385233 | BL17: 21020 | BM17: 26603 | BN17: 15402 | BO17: 24635 | BP17: 30175 | BQ17: 37501 | BR17: 28183 | BS17: 0 | BT17: 18986 | BU17: =SUM(BL17:BT17) -> 202505 | BV17: =+BU17/BU$13 -> 0.40739407 | BX17: 22239 | BY17: 26260 | BZ17: 15794 | CA17: 26611 | CB17: 31352 | CC17: 36432 | CD17: 23782 | CE17: 0 | CF17: 20638 | CG17: =SUM(BX17:CF17) -> 203108 | CH17: =+CG17/CG$13 -> 0.42315225 | CJ17: =+CG17-BU17 -> 603 | CK17: =IFERROR(+CJ17/BU17,0%) -> 0.0029777043 | CM17: =+Y17+AK17+CG17+AW17+BI17+BU17 -> 1279355 | CN17: =+CM17/CM$13 -> 0.42055472 | CP17: =+SUMIF('7.BP2025'!A:A,1435,'7.BP2025'!G:G)-SUMIF('7.BP2025'!A:A,1435,'7.BP2025'!H:H)+SUMIF('7.BP2025'!A:A,143599,'7.BP2025'!H:H)/2 -> 211197 | CQ17: =+CP17/CP$13 -> 0.40993485 | CS17: =184996-6-301+199683+206470+204133+245770+211197 -> 1251942 | CT17: =+CS17/CS$13 -> 0.42598529 | CV17: =+CM17-CS17 -> 27413 | CW17: =+IFERROR(CV17/CS17,0) -> 0.021896382
A18: 14 | B18: Inventario final | D18: 7673 | E18: 7927 | F18: 8345 | G18: 10712 | H18: 11516 | I18: 13198 | J18: 9559 | K18: 0 | L18: 9102 | M18: =SUM(D18:L18) -> 78032 | N18: =+M18/M$13 -> 0.15458953 | P18: 7951 | Q18: 11554 | R18: 8986 | S18: 13481 | T18: 12941 | U18: 16261 | V18: 9926 | W18: 0 | X18: 9777 | Y18: =SUM(P18:X18) -> 90877 | Z18: =+Y18/Y$13 -> 0.17267739 | AB18: 8244 | AC18: 10331 | AD18: 8193 | AE18: 11096 | AF18: 11019 | AG18: 14952 | AH18: 9277 | AI18: 0 | AJ18: 9414 | AK18: =SUM(AB18:AJ18) -> 82526 | AL18: =+AK18/AK$13 -> 0.16126391 | AN18: 8882 | AO18: 10926 | AP18: 8362 | AQ18: 10210 | AR18: 11617 | AS18: 12673 | AT18: 7939 | AU18: 0 | AV18: 9642 | AW18: =SUM(AN18:AV18) -> 80251 | AX18: =+AW18/AW$13 -> 0.151125 | AZ18: 10032 | BA18: 10668 | BB18: 7927 | BC18: 11078 | BD18: 14210 | BE18: 12520 | BF18: 8749 | BG18: 0 | BH18: 8102 | BI18: =SUM(AZ18:BH18) -> 83286 | BJ18: =+BI18/BI$13 -> 0.16793428 | BL18: 7337 | BM18: 10880 | BN18: 8082 | BO18: 10491 | BP18: 9193 | BQ18: 12051 | BR18: 9458 | BS18: 0 | BT18: 7508 | BU18: =SUM(BL18:BT18) -> 75000 | BV18: =+BU18/BU$13 -> 0.15088297 | BX18: 7348 | BY18: 11282 | BZ18: 8375 | CA18: 11879 | CB18: 11033 | CC18: 11243 | CD18: 8089 | CE18: 0 | CF18: 9000 | CG18: =SUM(BX18:CF18) -> 78249 | CH18: =+CG18/CG$13 -> 0.16302283 | CJ18: =+CG18-BU18 -> 3249 | CK18: =IFERROR(+CJ18/BU18,0%) -> 0.04332 | CM18: =+CG18 -> 78249 | CN18: =+CM18/CM$13 -> 0.025722326 | CP18: =+SUMIF('7.BP2025'!A:A,14,'7.BP2025'!I:I) -> 81850 | CQ18: =+CP18/CP$13 -> 0.15887142 | CS18: =+CP18 -> 81850 | CT18: =+CS18/CS$13 -> 0.027850248 | CV18: =+CM18-CS18 -> -3601 | CW18: =+IFERROR(CV18/CS18,0) -> -0.043995113
B20: GANANCIA BRUTA | D20: =+D13+D15 -> 49674 | E20: =+E13+E15 -> 28274 | F20: =+F13+F15 -> 24653 | G20: =+G13+G15 -> 60302 | H20: =+H13+H15 -> -21210 | I20: =+I13+I15 -> 46181 | J20: =+J13+J15 -> 38426 | K20: =+K13+K15 -> 128 | ... M20: =+M13+M15 -> 256241 | N20: =+M20/M$13 -> 0.50764013 | P20: =+P13+P15 -> 47963 | Q20: =+Q13+Q15 -> 27653 | R20: =+R13+R15 -> 21801 | S20: =+S13+S15 -> 50000 | T20: =+T13+T15 -> 68058 | U20: =+U13+U15 -> 43091 | V20: =+V13+V15 -> 32040 | W20: =+W13+W15 -> 0 | ... Y20: =+Y13+Y15 -> 321067 | Z20: =+Y20/Y$13 -> 0.61006647 | AB20: =+AB13+AB15 -> 40507 | AC20: =+AC13+AC15 -> 28697 | AD20: =+AD13+AD15 -> 23638 | AE20: =+AE13+AE15 -> 36461 | AF20: =+AF13+AF15 -> 53706 | AG20: =+AG13+AG15 -> 46284 | AH20: =+AH13+AH15 -> 35915 | AI20: =+AI13+AI15 -> 0 | ... AK20: =+AK13+AK15 -> 287513 | AL20: =+AK20/AK$13 -> 0.56182865 | AN20: =+AN13+AN15 -> 43545 | AO20: =+AO13+AO15 -> 31924 | AP20: =+AP13+AP15 -> 22603 | AQ20: =+AQ13+AQ15 -> 40496 | AR20: =+AR13+AR15 -> 54775 | AS20: =+AS13+AS15 -> 47973 | AT20: =+AT13+AT15 -> 37162 | AU20: =+AU13+AU15 -> 0 | ... AW20: =+AW13+AW15 -> 306431 | AX20: =+AW20/AW$13 -> 0.57705678 | AZ20: =+AZ13+AZ15 -> 35361 | BA20: =+BA13+BA15 -> 30151 | BB20: =+BB13+BB15 -> 21796 | BC20: =+BC13+BC15 -> 36952 | BD20: =+BD13+BD15 -> 56631 | BE20: =+BE13+BE15 -> 45456 | BF20: =+BF13+BF15 -> 33834 | BG20: =+BG13+BG15 -> 0 | ... BI20: =+BI13+BI15 -> 281496 | BJ20: =+BI20/BI$13 -> 0.56759634 | BL20: =+BL13+BL15 -> 33577 | BM20: =+BM13+BM15 -> 29431 | BN20: =+BN13+BN15 -> 20835 | BO20: =+BO13+BO15 -> 38417 | BP20: =+BP13+BP15 -> 60165 | BQ20: =+BQ13+BQ15 -> 44342 | BR20: =+BR13+BR15 -> 33509 | BS20: =+BS13+BS15 -> 0 | ... BU20: =+BU13+BU15 -> 286283 | BV20: =+BU20/BU$13 -> 0.57593638 | BX20: =+BX13+BX15 -> 37603 | BY20: =+BY13+BY15 -> 30157 | BZ20: =+BZ13+BZ15 -> 20545 | CA20: =+CA13+CA15 -> 39758 | CB20: =+CB13+CB15 -> 48840 | CC20: =+CC13+CC15 -> 44657 | CD20: =+CD13+CD15 -> 31931 | CE20: =+CE13+CE15 -> 0 | ... CG20: =+CG13+CG15 -> 280129 | CH20: =+CG20/CG$13 -> 0.58361667 | CJ20: =+CG20-BU20 -> -6154 | CK20: =IFERROR(+CJ20/BU20,0%) -> -0.021496212 | CM20: =+CM13+CM15 -> 1762927.5 | CN20: =+CM20/CM$13 -> 0.57951661 | CP20: =+CP13+CP15 -> 293380.5 | CQ20: =+CP20/CP$13 -> 0.5694536 | CS20: =+CS13+CS15 -> 1697868.5 | CT20: =+CS20/CS$13 -> 0.57771606 | CV20: =+CM20-CS20 -> 65059 | CW20: =+IFERROR(CV20/CS20,0) -> 0.038318044
B22: Otros Ingresos | D22: =+SUM(D25:D31) -> 35 | E22: =+SUM(E25:E31) -> 44 | F22: =+SUM(F25:F31) -> 65 | G22: =+SUM(G25:G31) -> 237 | H22: =+SUM(H25:H31) -> 6526 | I22: =+SUM(I25:I31) -> 209 | J22: =+SUM(J25:J31) -> 63 | K22: =+SUM(K25:K31) -> 0 | ... M22: =+SUM(M25:M31) -> 7249 | N22: =+M22/M$13 -> 0.014361025 | P22: =+SUM(P23:P31) -> 41 | Q22: =+SUM(Q23:Q31) -> 118 | R22: =+SUM(R23:R31) -> 18 | S22: =+SUM(S23:S31) -> 50 | T22: =+SUM(T23:T31) -> 7422 | U22: =+SUM(U23:U31) -> 178 | V22: =+SUM(V23:V31) -> 81 | W22: =+SUM(W23:W31) -> 2406 | ... Y22: =+SUM(Y23:Y31) -> 10375 | Z22: =+Y22/Y$13 -> 0.019713766 | AB22: =+SUM(AB23:AB31) -> 15 | AC22: =+SUM(AC23:AC31) -> 125 | AD22: =+SUM(AD23:AD31) -> 37 | AE22: =+SUM(AE23:AE31) -> 69 | AF22: =+SUM(AF23:AF31) -> 5162 | AG22: =+SUM(AG23:AG31) -> 295 | AH22: =+SUM(AH23:AH31) -> 106 | AI22: =+SUM(AI23:AI31) -> 0 | ... AK22: =+SUM(AK23:AK31) -> 5859 | AL22: =+AK22/AK$13 -> 0.011449062 | AN22: =+SUM(AN23:AN31) -> 81 | AO22: =+SUM(AO23:AO31) -> 156 | AP22: =+SUM(AP23:AP31) -> 74 | AQ22: =+SUM(AQ23:AQ31) -> 37 | AR22: =+SUM(AR23:AR31) -> 1013 | AS22: =+SUM(AS23:AS31) -> 58 | AT22: =+SUM(AT23:AT31) -> 63 | AU22: =+SUM(AU23:AU31) -> 6220 | ... AW22: =+SUM(AW23:AW31) -> 7812 | AX22: =+AW22/AW$13 -> 0.014711199 | AZ22: =+SUM(AZ23:AZ31) -> 108 | BA22: =+SUM(BA23:BA31) -> 692 | BB22: =+SUM(BB23:BB31) -> 98 | BC22: =+SUM(BC23:BC31) -> 105 | BD22: =+SUM(BD23:BD31) -> 1005 | BE22: =+SUM(BE23:BE31) -> 118 | BF22: =+SUM(BF23:BF31) -> 91 | BG22: =+SUM(BG23:BG31) -> 7620 | ... BI22: =+SUM(BI23:BI31) -> 9958 | BJ22: =+BI22/BI$13 -> 0.02007888 | BL22: =+SUM(BL23:BL31) -> 405 | BM22: =+SUM(BM23:BM31) -> 38 | BN22: =+SUM(BN23:BN31) -> 32 | BO22: =+SUM(BO23:BO31) -> 167 | BP22: =+SUM(BP23:BP31) -> 1073 | BQ22: =+SUM(BQ23:BQ31) -> 62 | BR22: =+SUM(BR23:BR31) -> 698 | BS22: =+SUM(BS23:BS31) -> 9246 | ... BU22: =+SUM(BU23:BU31) -> 11733 | BV22: =+BU22/BU$13 -> 0.023604131 | BX22: =+SUM(BX23:BX31) -> 12 | BY22: =+SUM(BY23:BY31) -> 35 | BZ22: =+SUM(BZ23:BZ31) -> 97 | CA22: =+SUM(CA23:CA31) -> 167 | CB22: =+SUM(CB23:CB31) -> 966 | CC22: =+SUM(CC23:CC31) -> 107 | CD22: =+SUM(CD23:CD31) -> 161 | CE22: =+SUM(CE23:CE31) -> 9133 | ... CG22: =+SUM(CG23:CG31) -> 10756 | CH22: =+CG22/CG$13 -> 0.022408894 | CJ22: =+CG22-BU22 -> -977 | CK22: =IFERROR(+CJ22/BU22,0%) -> -0.083269411 | CM22: =+SUM(CM23:CM31) -> 56493 | CN22: =+CM22/CM$13 -> 0.018570606 | CP22: =+SUM(CP25:CP31) -> 1944 | CQ22: =+CP22/CP$13 -> 0.0037733176 | CS22: =+SUM(CS25:CS31) -> 9959 | CT22: =+CS22/CS$13 -> 0.0033886454 | CV22: =+CM22-CS22 -> 46534 | CW22: =+IFERROR(CV22/CS22,0) -> 4.6725575
A23: 4220 | B23: Ingresos por arrendamientos | P23: 0 | Q23: 0 | R23: 0 | S23: 0 | T23: 0 | U23: 0 | V23: 0 | W23: 2406 | X23: 0 | Y23: =SUM(P23:X23) -> 2406 | Z23: =+Y23/Y$13 -> 0.0045716935 | AB23: 0 | AC23: 0 | AD23: 0 | AE23: 0 | AF23: 0 | AG23: 0 | AH23: 0 | AI23: 0 | AJ23: 0 | AK23: =SUM(AB23:AJ23) -> 0 | AL23: =+AK23/AK$13 -> 0 | AN23: 0 | AO23: 0 | AP23: 0 | AQ23: 0 | AR23: 0 | AS23: 0 | AT23: 0 | AU23: 6220 | AV23: 0 | AW23: =SUM(AN23:AV23) -> 6220 | AX23: =+AW23/AW$13 -> 0.011713218 | AZ23: 0 | BA23: 0 | BB23: 0 | BC23: 0 | BD23: 0 | BE23: 0 | BF23: 0 | BG23: 7620 | BH23: 0 | BI23: =SUM(AZ23:BH23) -> 7620 | BJ23: =+BI23/BI$13 -> 0.015364638 | BL23: 0 | BM23: 0 | BN23: 0 | BO23: 0 | BP23: 0 | BQ23: 0 | BR23: 0 | BS23: 9246 | BT23: 0 | BU23: =SUM(BL23:BT23) -> 9246 | BV23: =+BU23/BU$13 -> 0.018600852 | BX23: 0 | BY23: 0 | BZ23: 0 | CA23: 0 | CB23: 0 | CC23: 0 | CD23: 0 | CE23: 9133 | CF23: 0 | CG23: =SUM(BX23:CF23) -> 9133 | CH23: =+CG23/CG$13 -> 0.019027559 | CJ23: =+CG23-BU23 -> -113 | CK23: =IFERROR(+CJ23/BU23,0%) -> -0.012221501 | CM23: =+Y23+AK23+CG23+AW23+BI23+BU23 -> 34625 | CN23: =+CM23/CM$13 -> 0.011382069
A24: 42358001 | B24: Servicios Fletes | P24: 0 | Q24: 0 | R24: 0 | S24: 0 | T24: 899 | U24: 0 | V24: 0 | W24: 0 | X24: 0 | Y24: =SUM(P24:X24) -> 899 | Z24: =+Y24/Y$13 -> 0.0017082097 | AB24: 0 | AC24: 0 | AD24: 0 | AE24: 0 | AF24: 899 | AG24: 0 | AH24: 0 | AI24: 0 | AJ24: 0 | AK24: =SUM(AB24:AJ24) -> 899 | AL24: =+AK24/AK$13 -> 0.0017567343 | AN24: 0 | AO24: 0 | AP24: 0 | AQ24: 0 | AR24: 0 | AS24: 0 | AT24: 0 | AU24: 0 | AV24: 0 | AW24: =SUM(AN24:AV24) -> 0 | AX24: =+AW24/AW$13 -> 0 | AZ24: 0 | BA24: 0 | BB24: 0 | BC24: 0 | BD24: 0 | BE24: 0 | BF24: 0 | BG24: 0 | BH24: 0 | BI24: =SUM(AZ24:BH24) -> 0 | BJ24: =+BI24/BI$13 -> 0 | BL24: 0 | BM24: 0 | BN24: 0 | BO24: 0 | BP24: 0 | BQ24: 0 | BR24: 0 | BS24: 0 | BT24: 0 | BU24: =SUM(BL24:BT24) -> 0 | BV24: =+BU24/BU$13 -> 0 | BX24: 0 | BY24: 0 | BZ24: 0 | CA24: 0 | CB24: 0 | CC24: 0 | CD24: 0 | CE24: 0 | CF24: 0 | CG24: =SUM(BX24:CF24) -> 0 | CH24: =+CG24/CG$13 -> 0 | CJ24: =+CG24-BU24 -> 0 | CK24: =IFERROR(+CJ24/BU24,0%) -> 0 | CM24: =+Y24+AK24+CG24+AW24+BI24+BU24 -> 1798 | CN24: =+CM24/CM$13 -> 0.00059104579
A25: 42359604 | B25: Servicios | D25: 0 | E25: 0 | F25: 0 | G25: 0 | H25: 6462 | I25: 0 | J25: 0 | K25: 0 | L25: 0 | M25: =SUM(D25:L25) -> 6462 | N25: =+M25/M$13 -> 0.012801896 | P25: 0 | Q25: 0 | R25: 0 | S25: 0 | T25: 6354 | U25: 0 | V25: 0 | W25: 0 | X25: 0 | Y25: =SUM(P25:X25) -> 6354 | Z25: =+Y25/Y$13 -> 0.012073375 | AB25: 0 | AC25: 0 | AD25: 0 | AE25: 0 | AF25: 4222 | AG25: 0 | AH25: 0 | AI25: 0 | AJ25: 0 | AK25: =SUM(AB25:AJ25) -> 4222 | AL25: =+AK25/AK$13 -> 0.0082502027 | AN25: 0 | AO25: 0 | AP25: 0 | AQ25: 0 | AR25: 899 | AS25: 0 | AT25: 0 | AU25: 0 | AV25: 0 | AW25: =SUM(AN25:AV25) -> 899 | AX25: =+AW25/AW$13 -> 0.0016929555 | AZ25: 0 | BA25: 0 | BB25: 0 | BC25: 0 | BD25: 899 | BE25: 0 | BF25: 0 | BG25: 0 | BH25: 104 | BI25: =SUM(AZ25:BH25) -> 1003 | BJ25: =+BI25/BI$13 -> 0.0020224058 | BL25: 0 | BM25: 0 | BN25: 0 | BO25: 0 | BP25: 990 | BQ25: 0 | BR25: 627 | BS25: 0 | BT25: 0 | BU25: =SUM(BL25:BT25) -> 1617 | BV25: =+BU25/BU$13 -> 0.0032530368 | BX25: 0 | BY25: 0 | BZ25: 0 | CA25: 0 | CB25: 899 | CC25: 0 | CD25: 0 | CE25: 0 | CF25: 0 | CG25: =SUM(BX25:CF25) -> 899 | CH25: =+CG25/CG$13 -> 0.0018729635 | CJ25: =+CG25-BU25 -> -718 | CK25: =IFERROR(+CJ25/BU25,0%) -> -0.44403216 | CM25: =+Y25+AK25+CG25+AW25+BI25+BU25 -> 14994 | CN25: =+CM25/CM$13 -> 0.004928888 | CP25: =+DATOS!F99 -> 1421 | CQ25: =+CP25/CP$13 -> 0.0027581709 | CS25: =+DATOS!G99 -> 4161 | CT25: =+CS25/CS$13 -> 0.0014158202 | CV25: =+CM25-CS25 -> 10833 | CW25: =+IFERROR(CV25/CS25,0) -> 2.6034607
A26: 42505001 | B26: Recuperacion de costos y gastos | D26: 0 | E26: 0 | F26: 0 | G26: 0 | H26: 0 | I26: 0 | J26: 0 | K26: 0 | L26: 0 | M26: =SUM(D26:L26) -> 0 | N26: =+M26/M$13 -> 0 | P26: 0 | Q26: 0 | R26: 0 | S26: 0 | T26: 0 | U26: 0 | V26: 0 | W26: 0 | X26: 0 | Y26: =SUM(P26:X26) -> 0 | Z26: =+Y26/Y$13 -> 0 | AB26: 0 | AC26: 0 | AD26: 0 | AE26: 0 | AF26: 0 | AG26: 0 | AH26: 0 | AI26: 0 | AJ26: 0 | AK26: =SUM(AB26:AJ26) -> 0 | AL26: =+AK26/AK$13 -> 0 | AN26: 0 | AO26: 0 | AP26: 0 | AQ26: 0 | AR26: 0 | AS26: 0 | AT26: 0 | AU26: 0 | AV26: 0 | AW26: =SUM(AN26:AV26) -> 0 | AX26: =+AW26/AW$13 -> 0 | AZ26: 0 | BA26: 0 | BB26: 0 | BC26: 0 | BD26: 0 | BE26: 0 | BF26: 0 | BG26: 0 | BH26: 0 | BI26: =SUM(AZ26:BH26) -> 0 | BJ26: =+BI26/BI$13 -> 0 | BL26: 0 | BM26: 0 | BN26: 0 | BO26: 0 | BP26: 0 | BQ26: 0 | BR26: 0 | BS26: 0 | BT26: 0 | BU26: =SUM(BL26:BT26) -> 0 | BV26: =+BU26/BU$13 -> 0 | BX26: 0 | BY26: 0 | BZ26: 0 | CA26: 0 | CB26: 0 | CC26: 0 | CD26: 0 | CE26: 0 | CF26: 0 | CG26: =SUM(BX26:CF26) -> 0 | CH26: =+CG26/CG$13 -> 0 | CJ26: =+CG26-BU26 -> 0 | CK26: =IFERROR(+CJ26/BU26,0%) -> 0 | CM26: =+Y26+AK26+CG26+AW26+BI26+BU26 -> 0 | CN26: =+CM26/CM$13 -> 0 | CP26: =+DATOS!F101 -> 4 | CQ26: =+CP26/CP$13 -> 7.7640279e-06 | CT26: =+CS26/CS$13 -> 0 | CV26: =+CM26-CS26 -> 0 | CW26: =+IFERROR(CV26/CS26,0) -> 0
A27: 42505003 | B27: Ded. Alimentancion empleados | D27: 0 | E27: 0 | F27: 0 | G27: 0 | H27: 1 | I27: 0 | J27: 3 | K27: 0 | L27: 0 | M27: =SUM(D27:L27) -> 4 | N27: =+M27/M$13 -> 7.9244169e-06 | P27: 0 | Q27: 0 | R27: 0 | S27: 0 | T27: 1 | U27: 0 | V27: 3 | W27: 0 | X27: 0 | Y27: =SUM(P27:X27) -> 4 | Z27: =+Y27/Y$13 -> 7.600488e-06 | AB27: 0 | AC27: 0 | AD27: 0 | AE27: 0 | AF27: 1 | AG27: 0 | AH27: 3 | AI27: 0 | AJ27: 0 | AK27: =SUM(AB27:AJ27) -> 4 | AL27: =+AK27/AK$13 -> 7.8163929e-06 | AN27: 0 | AO27: 0 | AP27: 0 | AQ27: 0 | AR27: 1 | AS27: 0 | AT27: 3 | AU27: 0 | AV27: 0 | AW27: =SUM(AN27:AV27) -> 4 | AX27: =+AW27/AW$13 -> 7.5326162e-06 | AZ27: 0 | BA27: 0 | BB27: 0 | BC27: 0 | BD27: 1 | BE27: 0 | BF27: 3 | BG27: 0 | BH27: 0 | BI27: =SUM(AZ27:BH27) -> 4 | BJ27: =+BI27/BI$13 -> 8.0654267e-06 | BL27: 0 | BM27: 0 | BN27: 0 | BO27: 0 | BP27: 1 | BQ27: 0 | BR27: 3 | BS27: 0 | BT27: 0 | BU27: =SUM(BL27:BT27) -> 4 | BV27: =+BU27/BU$13 -> 8.0470916e-06 | BX27: 0 | BY27: 0 | BZ27: 0 | CA27: 0 | CB27: 1 | CC27: 0 | CD27: 3 | CE27: 0 | CF27: 0 | CG27: =SUM(BX27:CF27) -> 4 | CH27: =+CG27/CG$13 -> 8.3335417e-06 | CJ27: =+CG27-BU27 -> 0 | CK27: =IFERROR(+CJ27/BU27,0%) -> 0 | CM27: =+Y27+AK27+CG27+AW27+BI27+BU27 -> 24 | CN27: =+CM27/CM$13 -> 7.8893765e-06 | CP27: 0 | CQ27: =+CP27/CP$13 -> 0 | CS27: =+DATOS!G101 -> 20 | CT27: =+CS27/CS$13 -> 6.805192e-06 | CV27: =+CM27-CS27 -> 4 | CW27: =+IFERROR(CV27/CS27,0) -> 0.2
A28: 42554001 | B28: Indemnizaciones (incapacidades) | D28: 0 | E28: 0 | F28: 0 | G28: 0 | H28: 0 | I28: 0 | J28: 0 | K28: 0 | L28: 0 | M28: =SUM(D28:L28) -> 0 | N28: =+M28/M$13 -> 0 | P28: 0 | Q28: 0 | R28: 0 | S28: 0 | T28: 0 | U28: 0 | V28: 0 | W28: 0 | X28: 0 | Y28: =SUM(P28:X28) -> 0 | Z28: =+Y28/Y$13 -> 0 | AB28: 0 | AC28: 0 | AD28: 0 | AE28: 0 | AF28: 0 | AG28: 0 | AH28: 0 | AI28: 0 | AJ28: 0 | AK28: =SUM(AB28:AJ28) -> 0 | AL28: =+AK28/AK$13 -> 0 | AN28: 0 | AO28: 47 | AP28: 0 | AQ28: 0 | AR28: 0 | AS28: 0 | AT28: 0 | AU28: 0 | AV28: 0 | AW28: =SUM(AN28:AV28) -> 47 | AX28: =+AW28/AW$13 -> 8.8508241e-05 | AZ28: 0 | BA28: 226 | BB28: 0 | BC28: 0 | BD28: 0 | BE28: 0 | BF28: 0 | BG28: 0 | BH28: 0 | BI28: =SUM(AZ28:BH28) -> 226 | BJ28: =+BI28/BI$13 -> 0.00045569661 | BL28: 332 | BM28: 0 | BN28: 0 | BO28: 0 | BP28: 0 | BQ28: 0 | BR28: 0 | BS28: 0 | BT28: 0 | BU28: =SUM(BL28:BT28) -> 332 | BV28: =+BU28/BU$13 -> 0.0006679086 | BX28: 0 | BY28: 0 | BZ28: 0 | CA28: 0 | CB28: 0 | CC28: 0 | CD28: 0 | CE28: 0 | CF28: 0 | CG28: =SUM(BX28:CF28) -> 0 | CH28: =+CG28/CG$13 -> 0 | CJ28: =+CG28-BU28 -> -332 | CK28: =IFERROR(+CJ28/BU28,0%) -> -1 | CM28: =+Y28+AK28+CG28+AW28+BI28+BU28 -> 605 | CN28: =+CM28/CM$13 -> 0.00019887803 | CP28: =+DATOS!F102 -> 0 | CQ28: =+CP28/CP$13 -> 0 | CS28: =+DATOS!G102 -> 1051 | CT28: =+CS28/CS$13 -> 0.00035761284 | CV28: =+CM28-CS28 -> -446 | CW28: =+IFERROR(CV28/CS28,0) -> -0.42435775
A29: 42950501 | B29: Aprovechamientos | D29: 0 | E29: 0 | F29: 22 | G29: 0 | H29: 0 | I29: 0 | J29: 0 | K29: 0 | L29: 0 | M29: =SUM(D29:L29) -> 22 | N29: =+M29/M$13 -> 4.3584293e-05 | P29: 0 | Q29: 0 | R29: 0 | S29: 0 | T29: 0 | U29: 0 | V29: 0 | W29: 0 | X29: 0 | Y29: =SUM(P29:X29) -> 0 | Z29: =+Y29/Y$13 -> 0 | AB29: 0 | AC29: 0 | AD29: 8 | AE29: 0 | AF29: 0 | AG29: 0 | AH29: 0 | AI29: 0 | AJ29: 0 | AK29: =SUM(AB29:AJ29) -> 8 | AL29: =+AK29/AK$13 -> 1.5632786e-05 | AN29: 0 | AO29: 0 | AP29: 0 | AQ29: 0 | AR29: 0 | AS29: 0 | AT29: 0 | AU29: 0 | AV29: 0 | AW29: =SUM(AN29:AV29) -> 0 | AX29: =+AW29/AW$13 -> 0 | AZ29: 0 | BA29: 400 | BB29: 30 | BC29: 0 | BD29: 0 | BE29: 0 | BF29: 0 | BG29: 0 | BH29: 0 | BI29: =SUM(AZ29:BH29) -> 430 | BJ29: =+BI29/BI$13 -> 0.00086703337 | BL29: 0 | BM29: 0 | BN29: 0 | BO29: 0 | BP29: 0 | BQ29: 0 | BR29: 0 | BS29: 0 | BT29: 0 | BU29: =SUM(BL29:BT29) -> 0 | BV29: =+BU29/BU$13 -> 0 | BX29: 0 | BY29: 0 | BZ29: 42 | CA29: 0 | CB29: 35 | CC29: 0 | CD29: 0 | CE29: 0 | CF29: 0 | CG29: =SUM(BX29:CF29) -> 77 | CH29: =+CG29/CG$13 -> 0.00016042068 | CJ29: =+CG29-BU29 -> 77 | CK29: =IFERROR(+CJ29/BU29,0%) -> 0 | CM29: =+Y29+AK29+CG29+AW29+BI29+BU29 -> 515 | CN29: =+CM29/CM$13 -> 0.00016929287 | CP29: 0 | CQ29: =+CP29/CP$13 -> 0 | CS29: 0 | CT29: =+CS29/CS$13 -> 0 | CV29: =+CM29-CS29 -> 515 | CW29: =+IFERROR(CV29/CS29,0) -> 0
A30: 42951601 | B30: Sobrantes de caja | D30: 35 | E30: 44 | F30: 43 | G30: 236 | H30: 63 | I30: 209 | J30: 60 | K30: 0 | L30: 70 | M30: =SUM(D30:L30) -> 760 | N30: =+M30/M$13 -> 0.0015056392 | P30: 41 | Q30: 118 | R30: 18 | S30: 50 | T30: 168 | U30: 178 | V30: 78 | W30: 0 | X30: 61 | Y30: =SUM(P30:X30) -> 712 | Z30: =+Y30/Y$13 -> 0.0013528869 | AB30: 15 | AC30: 125 | AD30: 29 | AE30: 69 | AF30: 40 | AG30: 295 | AH30: 102 | AI30: 0 | AJ30: 50 | AK30: =SUM(AB30:AJ30) -> 725 | AL30: =+AK30/AK$13 -> 0.0014167212 | AN30: 81 | AO30: 109 | AP30: 74 | AQ30: 37 | AR30: 113 | AS30: 58 | AT30: 59 | AU30: 0 | AV30: 110 | AW30: =SUM(AN30:AV30) -> 641 | AX30: =+AW30/AW$13 -> 0.0012071018 | AZ30: 108 | BA30: 66 | BB30: 68 | BC30: 105 | BD30: 105 | BE30: 118 | BF30: 88 | BG30: 0 | BH30: 17 | BI30: =SUM(AZ30:BH30) -> 675 | BJ30: =+BI30/BI$13 -> 0.0013610408 | BL30: 73 | BM30: 38 | BN30: 32 | BO30: 167 | BP30: 82 | BQ30: 62 | BR30: 68 | BS30: 0 | BT30: 12 | BU30: =SUM(BL30:BT30) -> 534 | BV30: =+BU30/BU$13 -> 0.0010742867 | BX30: 12 | BY30: 35 | BZ30: 55 | CA30: 167 | CB30: 31 | CC30: 107 | CD30: 158 | CE30: 0 | CF30: 78 | CG30: =SUM(BX30:CF30) -> 643 | CH30: =+CG30/CG$13 -> 0.0013396168 | CJ30: =+CG30-BU30 -> 109 | CK30: =IFERROR(+CJ30/BU30,0%) -> 0.20411985 | CM30: =+Y30+AK30+CG30+AW30+BI30+BU30 -> 3930 | CN30: =+CM30/CM$13 -> 0.0012918854 | CP30: 0 | CQ30: =+CP30/CP$13 -> 0 | CT30: =+CS30/CS$13 -> 0 | CV30: =+CM30-CS30 -> 3930 | CW30: =+IFERROR(CV30/CS30,0) -> 0
A31: 42958101 | B31: Ajuste Al Peso | D31: 0 | E31: 0 | F31: 0 | G31: 1 | H31: 0 | I31: 0 | J31: 0 | K31: 0 | L31: 0 | M31: =SUM(D31:L31) -> 1 | N31: =+M31/M$13 -> 1.9811042e-06 | P31: 0 | Q31: 0 | R31: 0 | S31: 0 | T31: 0 | U31: 0 | V31: 0 | W31: 0 | X31: 0 | Y31: =SUM(P31:X31) -> 0 | Z31: =+Y31/Y$13 -> 0 | AB31: 0 | AC31: 0 | AD31: 0 | AE31: 0 | AF31: 0 | AG31: 0 | AH31: 1 | AI31: 0 | AJ31: 0 | AK31: =SUM(AB31:AJ31) -> 1 | AL31: =+AK31/AK$13 -> 1.9540982e-06 | AN31: 0 | AO31: 0 | AP31: 0 | AQ31: 0 | AR31: 0 | AS31: 0 | AT31: 1 | AU31: 0 | AV31: 0 | AW31: =SUM(AN31:AV31) -> 1 | AX31: =+AW31/AW$13 -> 1.8831541e-06 | AZ31: 0 | BA31: 0 | BB31: 0 | BC31: 0 | BD31: 0 | BE31: 0 | BF31: 0 | BG31: 0 | BH31: 0 | BI31: =SUM(AZ31:BH31) -> 0 | BJ31: =+BI31/BI$13 -> 0 | BL31: 0 | BM31: 0 | BN31: 0 | BO31: 0 | BP31: 0 | BQ31: 0 | BR31: 0 | BS31: 0 | BT31: 0 | BU31: =SUM(BL31:BT31) -> 0 | BV31: =+BU31/BU$13 -> 0 | BX31: 0 | BY31: 0 | BZ31: 0 | CA31: 0 | CB31: 0 | CC31: 0 | CD31: 0 | CE31: 0 | CF31: 0 | CG31: =SUM(BX31:CF31) -> 0 | CH31: =+CG31/CG$13 -> 0 | CJ31: =+CG31-BU31 -> 0 | CK31: =IFERROR(+CJ31/BU31,0%) -> 0 | CM31: =+Y31+AK31+CG31+AW31+BI31+BU31 -> 2 | CN31: =+CM31/CM$13 -> 6.5744804e-07 | CP31: =+DATOS!F104 -> 519 | CQ31: =+CP31/CP$13 -> 0.0010073826 | CS31: =+DATOS!G104 -> 4727 | CT31: =+CS31/CS$13 -> 0.0016084071 | CV31: =+CM31-CS31 -> -4725 | CW31: =+IFERROR(CV31/CS31,0) -> -0.9995769
B32: Gastos de Ventas | D32: =+D33+D39+D63+D64+D65+D66+D91+D92+D93+D116+D118+D61+D62+D67+D86+D87+D88+D89+D90+D94 -> -36116 | E32: =+E33+E39+E63+E64+E65+E66+E91+E92+E93+E116+E118+E61+E62+E67+E86+E87+E88+E89+E90+E94 -> -19686 | F32: =+F33+F39+F63+F64+F65+F66+F91+F92+F93+F116+F118+F61+F62+F67+F86+F87+F88+F89+F90+F94 -> -19216 | G32: =+G33+G39+G63+G64+G65+G66+G91+G92+G93+G116+G118+G61+G62+G67+G86+G87+G88+G89+G90+G94 -> -39331 | H32: =+H33+H39+H63+H64+H65+H66+H91+H92+H93+H116+H118+H61+H62+H67+H86+H87+H88+H89+H90+H94 -> -57543 | I32: =+I33+I39+I63+I64+I65+I66+I91+I92+I93+I116+I61+I62+I67+I86+I87+I88+I89+I90+I94 -> -31289 | J32: =+J33+J39+J63+J64+J65+J66+J91+J92+J93+J116+J118+J61+J62+J67+J86+J87+J88+J89+J90+J94 -> -27914 | K32: =+K33+K39+K63+K64+K65+K66+K91+K92+K93+K116+K118+K61+K62+K67+K86+K87+K88+K89+K90+K94 -> -14917 | L32: =+L33+L39+L63+L64+L65+L66+L91+L92+L93+L116+L118+L61+L62+L67+L86+L87+L88+L89+L90+L94 -> -25117 | M32: =+M33+M39+M63+M64+M65+M66+M91+M92+M93+M116+M118+M61+M62+M67+M86+M87+M88+M89+M90+M94 -> -271129 | N32: =+M32/M$13 -> -0.53713481 | P32: =+P33+P39+P63+P64+P65+P66+P91+P92+P93+P116+P118+P61+P62+P67+P86+P87+P88+P89+P90+P94 -> -26998 | Q32: =+Q33+Q39+Q63+Q64+Q65+Q66+Q91+Q92+Q93+Q116+Q118+Q61+Q62+Q67+Q86+Q87+Q88+Q89+Q90+Q94 -> -31394 | R32: =+R33+R39+R63+R64+R65+R66+R91+R92+R93+R116+R118+R61+R62+R67+R86+R87+R88+R89+R90+R94 -> -15520 | S32: =+S33+S39+S63+S64+S65+S66+S91+S92+S93+S116+S118+S61+S62+S67+S86+S87+S88+S89+S90+S94 -> -40186 | T32: =+T33+T39+T63+T64+T65+T66+T91+T92+T93+T116+T118+T61+T62+T67+T86+T87+T88+T89+T90+T94 -> -68838 | U32: =+U33+U39+U63+U64+U65+U66+U91+U92+U93+U116+U61+U62+U67+U86+U87+U88+U89+U90+U94 -> -29221 | V32: =+V33+V39+V63+V64+V65+V66+V91+V92+V93+V116+V118+V61+V62+V67+V86+V87+V88+V89+V90+V94 -> -24378 | W32: =+W33+W39+W63+W64+W65+W66+W91+W92+W93+W116+W118+W61+W62+W67+W86+W87+W88+W89+W90+W94 -> -276 | X32: =+X33+X39+X63+X64+X65+X66+X91+X92+X93+X116+X118+X61+X62+X67+X86+X87+X88+X89+X90+X94 -> -22523 | Y32: =+Y33+Y39+Y63+Y64+Y65+Y66+Y91+Y92+Y93+Y116+Y118+Y61+Y62+Y67+Y86+Y87+Y88+Y89+Y90+Y94 -> -261469 | Z32: =+Y32/Y$13 -> -0.496823 | AB32: =+AB33+AB39+AB63+AB64+AB65+AB66+AB91+AB92+AB93+AB116+AB118+AB61+AB62+AB67+AB86+AB87+AB88+AB89+AB90+AB94 -> -26131 | AC32: =+AC33+AC39+AC63+AC64+AC65+AC66+AC91+AC92+AC93+AC116+AC118+AC61+AC62+AC67+AC86+AC87+AC88+AC89+AC90+AC94 -> -31244 | AD32: =+AD33+AD39+AD63+AD64+AD65+AD66+AD91+AD92+AD93+AD116+AD118+AD61+AD62+AD67+AD86+AD87+AD88+AD89+AD90+AD94 -> -17401 | AE32: =+AE33+AE39+AE63+AE64+AE65+AE66+AE91+AE92+AE93+AE116+AE118+AE61+AE62+AE67+AE86+AE87+AE88+AE89+AE90+AE94 -> -38211 | AF32: =+AF33+AF39+AF63+AF64+AF65+AF66+AF91+AF92+AF93+AF116+AF118+AF61+AF62+AF67+AF86+AF87+AF88+AF89+AF90+AF94 -> -79386 | AG32: =+AG33+AG39+AG63+AG64+AG65+AG66+AG91+AG92+AG93+AG116+AG61+AG62+AG67+AG86+AG87+AG88+AG89+AG90+AG94 -> -33391 | AH32: =+AH33+AH39+AH63+AH64+AH65+AH66+AH91+AH92+AH93+AH116+AH118+AH61+AH62+AH67+AH86+AH87+AH88+AH89+AH90+AH94 -> -25498 | AI32: =+AI33+AI39+AI63+AI64+AI65+AI66+AI91+AI92+AI93+AI116+AI118+AI61+AI62+AI67+AI86+AI87+AI88+AI89+AI90+AI94 -> -4496 | AJ32: =+AJ33+AJ39+AJ63+AJ64+AJ65+AJ66+AJ91+AJ92+AJ93+AJ116+AJ118+AJ61+AJ62+AJ67+AJ86+AJ87+AJ88+AJ89+AJ90+AJ94 -> -24761 | AK32: =+AK33+AK39+AK63+AK64+AK65+AK66+AK91+AK92+AK93+AK116+AK118+AK61+AK62+AK67+AK86+AK87+AK88+AK89+AK90+AK94 -> -283145 | AL32: =+AK32/AK$13 -> -0.55329314 | AN32: =+AN33+AN39+AN63+AN64+AN65+AN66+AN91+AN92+AN93+AN116+AN118+AN61+AN62+AN67+AN86+AN87+AN88+AN89+AN90+AN94 -> -28306 | AO32: =+AO33+AO39+AO63+AO64+AO65+AO66+AO91+AO92+AO93+AO116+AO118+AO61+AO62+AO67+AO86+AO87+AO88+AO89+AO90+AO94 -> -26582 | AP32: =+AP33+AP39+AP63+AP64+AP65+AP66+AP91+AP92+AP93+AP116+AP118+AP61+AP62+AP67+AP86+AP87+AP88+AP89+AP90+AP94 -> -16807 | AQ32: =+AQ33+AQ39+AQ63+AQ64+AQ65+AQ66+AQ91+AQ92+AQ93+AQ116+AQ118+AQ61+AQ62+AQ67+AQ86+AQ87+AQ88+AQ89+AQ90+AQ94 -> -36500 | AR32: =+AR33+AR39+AR63+AR64+AR65+AR66+AR91+AR92+AR93+AR116+AR118+AR61+AR62+AR67+AR86+AR87+AR88+AR89+AR90+AR94 -> -70013 | AS32: =+AS33+AS39+AS63+AS64+AS65+AS66+AS91+AS92+AS93+AS116+AS61+AS62+AS67+AS86+AS87+AS88+AS89+AS90+AS94 -> -30979 | AT32: =+AT33+AT39+AT63+AT64+AT65+AT66+AT91+AT92+AT93+AT116+AT118+AT61+AT62+AT67+AT86+AT87+AT88+AT89+AT90+AT94 -> -25492 | AU32: =+AU33+AU39+AU63+AU64+AU65+AU66+AU91+AU92+AU93+AU116+AU118+AU61+AU62+AU67+AU86+AU87+AU88+AU89+AU90+AU94 -> -4506 | AV32: =+AV33+AV39+AV63+AV64+AV65+AV66+AV91+AV92+AV93+AV116+AV118+AV61+AV62+AV67+AV86+AV87+AV88+AV89+AV90+AV94 -> -24199 | AW32: =+AW33+AW39+AW63+AW64+AW65+AW66+AW91+AW92+AW93+AW116+AW118+AW61+AW62+AW67+AW86+AW87+AW88+AW89+AW90+AW94 -> -264697 | AX32: =+AW32/AW$13 -> -0.49846523 | AZ32: =+AZ33+AZ39+AZ63+AZ64+AZ65+AZ66+AZ91+AZ92+AZ93+AZ116+AZ118+AZ61+AZ62+AZ67+AZ86+AZ87+AZ88+AZ89+AZ90+AZ94 -> -25794 | BA32: =+BA33+BA39+BA63+BA64+BA65+BA66+BA91+BA92+BA93+BA116+BA118+BA61+BA62+BA67+BA86+BA87+BA88+BA89+BA90+BA94 -> -25611 | BB32: =+BB33+BB39+BB63+BB64+BB65+BB66+BB91+BB92+BB93+BB116+BB118+BB61+BB62+BB67+BB86+BB87+BB88+BB89+BB90+BB94 -> -15899 | BC32: =+BC33+BC39+BC63+BC64+BC65+BC66+BC91+BC92+BC93+BC116+BC118+BC61+BC62+BC67+BC86+BC87+BC88+BC89+BC90+BC94 -> -39597 | BD32: =+BD33+BD39+BD63+BD64+BD65+BD66+BD91+BD92+BD93+BD116+BD118+BD61+BD62+BD67+BD86+BD87+BD88+BD89+BD90+BD94 -> -84271 | BE32: =+BE33+BE39+BE63+BE64+BE65+BE66+BE91+BE92+BE93+BE116+BE61+BE62+BE67+BE86+BE87+BE88+BE89+BE90+BE94 -> -33314 | BF32: =+BF33+BF39+BF63+BF64+BF65+BF66+BF91+BF92+BF93+BF116+BF118+BF61+BF62+BF67+BF86+BF87+BF88+BF89+BF90+BF94 -> -28272 | BG32: =+BG33+BG39+BG63+BG64+BG65+BG66+BG91+BG92+BG93+BG116+BG118+BG61+BG62+BG67+BG86+BG87+BG88+BG89+BG90+BG94 -> -4437 | BH32: =+BH33+BH39+BH63+BH64+BH65+BH66+BH91+BH92+BH93+BH116+BH118+BH61+BH62+BH67+BH86+BH87+BH88+BH89+BH90+BH94 -> -25159 | BI32: =+BI33+BI39+BI63+BI64+BI65+BI66+BI91+BI92+BI93+BI116+BI118+BI61+BI62+BI67+BI86+BI87+BI88+BI89+BI90+BI94 -> -282354 | BJ32: =+BI32/BI$13 -> -0.56932638 | BL32: =+BL33+BL39+BL63+BL64+BL65+BL66+BL91+BL92+BL93+BL116+BL118+BL61+BL62+BL67+BL86+BL87+BL88+BL89+BL90+BL94 -> -26084 | BM32: =+BM33+BM39+BM63+BM64+BM65+BM66+BM91+BM92+BM93+BM116+BM118+BM61+BM62+BM67+BM86+BM87+BM88+BM89+BM90+BM94 -> -27976 | BN32: =+BN33+BN39+BN63+BN64+BN65+BN66+BN91+BN92+BN93+BN116+BN118+BN61+BN62+BN67+BN86+BN87+BN88+BN89+BN90+BN94 -> -18120 | BO32: =+BO33+BO39+BO63+BO64+BO65+BO66+BO91+BO92+BO93+BO116+BO118+BO61+BO62+BO67+BO86+BO87+BO88+BO89+BO90+BO94 -> -38443 | BP32: =+BP33+BP39+BP63+BP64+BP65+BP66+BP91+BP92+BP93+BP116+BP118+BP61+BP62+BP67+BP86+BP87+BP88+BP89+BP90+BP94 -> -96955 | BQ32: =+BQ33+BQ39+BQ63+BQ64+BQ65+BQ66+BQ91+BQ92+BQ93+BQ116+BQ61+BQ62+BQ67+BQ86+BQ87+BQ88+BQ89+BQ90+BQ94 -> -31961 | BR32: =+BR33+BR39+BR63+BR64+BR65+BR66+BR91+BR92+BR93+BR116+BR118+BR61+BR62+BR67+BR86+BR87+BR88+BR89+BR90+BR94 -> -25460 | BS32: =+BS33+BS39+BS63+BS64+BS65+BS66+BS91+BS92+BS93+BS116+BS118+BS61+BS62+BS67+BS86+BS87+BS88+BS89+BS90+BS94 -> -26603 | BT32: =+BT33+BT39+BT63+BT64+BT65+BT66+BT91+BT92+BT93+BT116+BT118+BT61+BT62+BT67+BT86+BT87+BT88+BT89+BT90+BT94 -> -26280 | BU32: =+BU33+BU39+BU63+BU64+BU65+BU66+BU91+BU92+BU93+BU116+BU118+BU61+BU62+BU67+BU86+BU87+BU88+BU89+BU90+BU94 -> -317882 | BV32: =+BU32/BU$13 -> -0.63950639 | BX32: =+BX33+BX39+BX63+BX64+BX65+BX66+BX91+BX92+BX93+BX116+BX118+BX61+BX62+BX67+BX86+BX87+BX88+BX89+BX90+BX94 -> -29846 | BY32: =+BY33+BY39+BY63+BY64+BY65+BY66+BY91+BY92+BY93+BY116+BY118+BY61+BY62+BY67+BY86+BY87+BY88+BY89+BY90+BY94 -> -25257 | BZ32: =+BZ33+BZ39+BZ63+BZ64+BZ65+BZ66+BZ91+BZ92+BZ93+BZ116+BZ118+BZ61+BZ62+BZ67+BZ86+BZ87+BZ88+BZ89+BZ90+BZ94 -> -16484 | CA32: =+CA33+CA39+CA63+CA64+CA65+CA66+CA91+CA92+CA93+CA116+CA118+CA61+CA62+CA67+CA86+CA87+CA88+CA89+CA90+CA94 -> -46469 | CB32: =+CB33+CB39+CB63+CB64+CB65+CB66+CB91+CB92+CB93+CB116+CB118+CB61+CB62+CB67+CB86+CB87+CB88+CB89+CB90+CB94 -> -64655 | CC32: =+CC33+CC39+CC63+CC64+CC65+CC66+CC91+CC92+CC93+CC116+CC61+CC62+CC67+CC86+CC87+CC88+CC89+CC90+CC94 -> -34851 | CD32: =+CD33+CD39+CD63+CD64+CD65+CD66+CD91+CD92+CD93+CD116+CD118+CD61+CD62+CD67+CD86+CD87+CD88+CD89+CD90+CD94 -> -29351 | CE32: =+CE33+CE39+CE63+CE64+CE65+CE66+CE91+CE92+CE93+CE116+CE118+CE61+CE62+CE67+CE86+CE87+CE88+CE89+CE90+CE94 -> -5912 | CF32: =+CF33+CF39+CF63+CF64+CF65+CF66+CF91+CF92+CF93+CF116+CF118+CF61+CF62+CF67+CF86+CF87+CF88+CF89+CF90+CF94 -> -27010 | CG32: =+CG33+CG39+CG63+CG64+CG65+CG66+CG91+CG92+CG93+CG116+CG118+CG61+CG62+CG67+CG86+CG87+CG88+CG89+CG90+CG94 -> -279835 | CH32: =+CG32/CG$13 -> -0.58300416 | CJ32: =+CG32-BU32 -> 38047 | CK32: =IFERROR(+CJ32/BU32,0%) -> -0.11968907 | CM32: =+Y32+AK32+CG32+AW32+BI32+BU32 -> -1689382 | CN32: =+CM32/CM$13 -> -0.55534044 | CP32: =+CP33+CP39+CP63+CP64+CP65+CP66+CP91+CP92+CP93+CP116+CP118+CP61+CP62+CP67+CP86+CP87+CP88+CP89+CP90+CP94 -> -287674.5 | CQ32: =+CP32/CP$13 -> -0.55837821 | CR32: =+CP32+DATOS!F114 -> 0 | CS32: =+CS33+CS39+CS63+CS64+CS65+CS66+CS91+CS92+CS93+CS116+CS118+CS61+CS62+CS67+CS86+CS87+CS88+CS89+CS90+CS94 -> -1570193 | CT32: =+CS32/CS$13 -> -0.53427324 | CV32: =+CM32-CS32 -> -119189 | CW32: =+IFERROR(CV32/CS32,0) -> 0.075907229
A33: 5204 | B33: Aportes sobre la nomina | D33: =+SUM(D34:D38) -> -1410 | E33: =+SUM(E34:E38) -> -1396 | F33: =+SUM(F34:F38) -> -1142 | G33: =+SUM(G34:G38) -> -1542 | H33: =+SUM(H34:H38) -> -2379 | I33: =+SUM(I34:I38) -> -1319 | J33: =+SUM(J34:J38) -> -1151 | K33: =+SUM(K34:K38) -> 0 | ... M33: =+SUM(M34:M38) -> -11422 | N33: =+M33/M$13 -> -0.022628172 | P33: =+SUM(P34:P38) -> -1312 | Q33: =+SUM(Q34:Q38) -> -1855 | R33: =+SUM(R34:R38) -> -896 | S33: =+SUM(S34:S38) -> -1721 | T33: =+SUM(T34:T38) -> -2743 | U33: =+SUM(U34:U38) -> -1486 | V33: =+SUM(V34:V38) -> -1122 | W33: =+SUM(W34:W38) -> 0 | ... Y33: =+SUM(Y34:Y38) -> -11945 | Z33: =+Y33/Y$13 -> -0.022696957 | AB33: =+SUM(AB34:AB38) -> -1369 | AC33: =+SUM(AC34:AC38) -> -1517 | AD33: =+SUM(AD34:AD38) -> -814 | AE33: =+SUM(AE34:AE38) -> -1514 | AF33: =+SUM(AF34:AF38) -> -3554 | AG33: =+SUM(AG34:AG38) -> -1822 | AH33: =+SUM(AH34:AH38) -> -1126 | AI33: =+SUM(AI34:AI38) -> 0 | ... AK33: =+SUM(AK34:AK38) -> -13038 | AL33: =+AK33/AK$13 -> -0.025477533 | AN33: =+SUM(AN34:AN38) -> -1384 | AO33: =+SUM(AO34:AO38) -> -1134 | AP33: =+SUM(AP34:AP38) -> -801 | AQ33: =+SUM(AQ34:AQ38) -> -1264 | AR33: =+SUM(AR34:AR38) -> -3150 | AS33: =+SUM(AS34:AS38) -> -1460 | AT33: =+SUM(AT34:AT38) -> -1151 | AU33: =+SUM(AU34:AU38) -> 0 | ... AW33: =+SUM(AW34:AW38) -> -11427 | AX33: =+AW33/AW$13 -> -0.021518801 | AZ33: =+SUM(AZ34:AZ38) -> -1362 | BA33: =+SUM(BA34:BA38) -> -1144 | BB33: =+SUM(BB34:BB38) -> -859 | BC33: =+SUM(BC34:BC38) -> -1296 | BD33: =+SUM(BD34:BD38) -> -3425 | BE33: =+SUM(BE34:BE38) -> -1909 | BF33: =+SUM(BF34:BF38) -> -1217 | BG33: =+SUM(BG34:BG38) -> 0 | ... BI33: =+SUM(BI34:BI38) -> -12426 | BJ33: =+BI33/BI$13 -> -0.025055248 | BL33: =+SUM(BL34:BL38) -> -1017 | BM33: =+SUM(BM34:BM38) -> -1200 | BN33: =+SUM(BN34:BN38) -> -1116 | BO33: =+SUM(BO34:BO38) -> -968 | BP33: =+SUM(BP34:BP38) -> -2765 | BQ33: =+SUM(BQ34:BQ38) -> -1529 | BR33: =+SUM(BR34:BR38) -> -1142 | BS33: =+SUM(BS34:BS38) -> 0 | ... BU33: =+SUM(BU34:BU38) -> -11183 | BV33: =+BU33/BU$13 -> -0.022497656 | BX33: =+SUM(BX34:BX38) -> -1474 | BY33: =+SUM(BY34:BY38) -> -1164 | BZ33: =+SUM(BZ34:BZ38) -> -773 | CA33: =+SUM(CA34:CA38) -> -1658 | CB33: =+SUM(CB34:CB38) -> -3065 | CC33: =+SUM(CC34:CC38) -> -1519 | CD33: =+SUM(CD34:CD38) -> -1198 | CE33: =+SUM(CE34:CE38) -> 0 | ... CG33: =+SUM(CG34:CG38) -> -12042 | CH33: =+CG33/CG$13 -> -0.025088127 | CJ33: =+CG33-BU33 -> -859 | CK33: =IFERROR(+CJ33/BU33,0%) -> 0.07681302 | CM33: =+SUM(CM34:CM38) -> -72060 | CN33: =+CM33/CM$13 -> -0.023687853 | CP33: =+SUM(CP34:CP38) -> -11908.5 | CQ33: =+CP33/CP$13 -> -0.023114482 | CS33: =+SUM(CS34:CS38) -> -66608.5 | CT33: =+CS33/CS$13 -> -0.022664182 | CV33: =+CM33-CS33 -> -5451.5 | CW33: =+IFERROR(CV33/CS33,0) -> 0.081843909
A34: 520468 | B34: Aportes A.R.P | D34: -181 | E34: -176 | F34: -147 | G34: -203 | H34: -284 | I34: -158 | J34: -134 | K34: 0 | L34: -132 | M34: =SUM(D34:L34) -> -1415 | N34: =+M34/M$13 -> -0.0028032625 | P34: -167 | Q34: -218 | R34: -109 | S34: -195 | T34: -331 | U34: -164 | V34: -139 | W34: 0 | X34: -107 | Y34: =SUM(P34:X34) -> -1430 | Z34: =+Y34/Y$13 -> -0.0027171744 | AB34: -151 | AC34: -201 | AD34: -106 | AE34: -188 | AF34: -439 | AG34: -241 | AH34: -129 | AI34: 0 | AJ34: -149 | AK34: =SUM(AB34:AJ34) -> -1604 | AL34: =+AK34/AK$13 -> -0.0031343736 | AN34: -183 | AO34: -139 | AP34: -106 | AQ34: -166 | AR34: -410 | AS34: -182 | AT34: -145 | AU34: 0 | AV34: -143 | AW34: =SUM(AN34:AV34) -> -1474 | AX34: =+AW34/AW$13 -> -0.0027757691 | AZ34: -178 | BA34: -151 | BB34: -114 | BC34: -140 | BD34: -450 | BE34: -242 | BF34: -160 | BG34: 0 | BH34: -160 | BI34: =SUM(AZ34:BH34) -> -1595 | BJ34: =+BI34/BI$13 -> -0.0032160889 | BL34: -124 | BM34: -151 | BN34: -148 | BO34: -119 | BP34: -362 | BQ34: -192 | BR34: -151 | BS34: 0 | BT34: -191 | BU34: =SUM(BL34:BT34) -> -1438 | BV34: =+BU34/BU$13 -> -0.0028929294 | BX34: -195 | BY34: -133 | BZ34: -100 | CA34: -178 | CB34: -404 | CC34: -199 | CD34: -158 | CE34: 0 | CF34: -156 | CG34: =SUM(BX34:CF34) -> -1523 | CH34: =+CG34/CG$13 -> -0.003172996 | CJ34: =+CG34-BU34 -> -85 | CK34: =IFERROR(+CJ34/BU34,0%) -> 0.059109875 | CM34: =-DATOS!D115 -> -9067 | CN34: =+CM34/CM$13 -> -0.0029805407 | CP34: =-DATOS!F115 -> -1540 | CQ34: =+CP34/CP$13 -> -0.0029891507 | CS34: =-DATOS!G115 -> -8379.5 | CT34: =+CS34/CS$13 -> -0.0028512053 | CV34: =+CM34-CS34 -> -687.5 | CW34: =+IFERROR(CV34/CS34,0) -> 0.082045468
A35: 520469 | B35: Aportes A E.P.S | D35: 0 | E35: 0 | F35: 0 | G35: 0 | H35: 0 | I35: 0 | J35: 0 | K35: 0 | L35: 0 | M35: =SUM(D35:L35) -> 0 | N35: =+M35/M$13 -> 0 | P35: 0 | Q35: -5 | R35: 0 | S35: 0 | T35: 0 | U35: 3 | V35: 0 | W35: 0 | X35: 0 | Y35: =SUM(P35:X35) -> -2 | Z35: =+Y35/Y$13 -> -3.800244e-06 | AB35: 0 | AC35: 0 | AD35: 0 | AE35: 0 | AF35: -1 | AG35: 0 | AH35: 0 | AI35: 0 | AJ35: 0 | AK35: =SUM(AB35:AJ35) -> -1 | AL35: =+AK35/AK$13 -> -1.9540982e-06 | AN35: 0 | AO35: -4 | AP35: 0 | AQ35: 0 | AR35: 0 | AS35: 0 | AT35: -3 | AU35: 0 | AV35: 0 | AW35: =SUM(AN35:AV35) -> -7 | AX35: =+AW35/AW$13 -> -1.3182078e-05 | AZ35: 0 | BA35: 0 | BB35: 0 | BC35: 0 | BD35: 0 | BE35: 0 | BF35: 0 | BG35: 0 | BH35: 0 | BI35: =SUM(AZ35:BH35) -> 0 | BJ35: =+BI35/BI$13 -> 0 | BL35: 0 | BM35: 0 | BN35: 0 | BO35: 0 | BP35: 0 | BQ35: 0 | BR35: 0 | BS35: 0 | BT35: 0 | BU35: =SUM(BL35:BT35) -> 0 | BV35: =+BU35/BU$13 -> 0 | BX35: 0 | BY35: 0 | BZ35: 0 | CA35: 0 | CB35: -5 | CC35: 0 | CD35: 0 | CE35: 0 | CF35: 0 | CG35: =SUM(BX35:CF35) -> -5 | CH35: =+CG35/CG$13 -> -1.0416927e-05 | CJ35: =+CG35-BU35 -> -5 | CK35: =IFERROR(+CJ35/BU35,0%) -> 0 | CM35: =-DATOS!D116 -> -14.5 | CN35: =+CM35/CM$13 -> -4.7664983e-06 | CP35: =-DATOS!F116 -> 0 | CQ35: =+CP35/CP$13 -> 0 | CS35: =-DATOS!G116 -> -5 | CT35: =+CS35/CS$13 -> -1.701298e-06 | CV35: =+CM35-CS35 -> -9.5 | CW35: =+IFERROR(CV35/CS35,0) -> 1.9
A36: 520470 | B36: Aportes A Fondos De Pensiones | D36: -901 | E36: -886 | F36: -753 | G36: -1006 | H36: -1568 | I36: -876 | J36: -723 | K36: 0 | L36: -725 | M36: =SUM(D36:L36) -> -7438 | N36: =+M36/M$13 -> -0.014735453 | P36: -870 | Q36: -1225 | R36: -595 | S36: -1135 | T36: -1812 | U36: -1008 | V36: -736 | W36: 0 | X36: -527 | Y36: =SUM(P36:X36) -> -7908 | Z36: =+Y36/Y$13 -> -0.015026165 | AB36: -968 | AC36: -987 | AD36: -532 | AE36: -997 | AF36: -2353 | AG36: -1186 | AH36: -749 | AI36: 0 | AJ36: -886 | AK36: =SUM(AB36:AJ36) -> -8658 | AL36: =+AK36/AK$13 -> -0.016918582 | AN36: -901 | AO36: -724 | AP36: -521 | AQ36: -819 | AR36: -2055 | AS36: -960 | AT36: -740 | AU36: 0 | AV36: -705 | AW36: =SUM(AN36:AV36) -> -7425 | AX36: =+AW36/AW$13 -> -0.013982419 | AZ36: -877 | BA36: -745 | BB36: -559 | BC36: -846 | BD36: -2228 | BE36: -1251 | BF36: -793 | BG36: 0 | BH36: -792 | BI36: =SUM(AZ36:BH36) -> -8091 | BJ36: =+BI36/BI$13 -> -0.016314342 | BL36: -641 | BM36: -796 | BN36: -726 | BO36: -637 | BP36: -1784 | BQ36: -946 | BR36: -743 | BS36: 0 | BT36: -941 | BU36: =SUM(BL36:BT36) -> -7214 | BV36: =+BU36/BU$13 -> -0.01451293 | BX36: -959 | BY36: -813 | BZ36: -505 | CA36: -1148 | CB36: -1993 | CC36: -993 | CD36: -780 | CE36: 0 | CF36: -780 | CG36: =SUM(BX36:CF36) -> -7971 | CH36: =+CG36/CG$13 -> -0.016606665 | CJ36: =+CG36-BU36 -> -757 | CK36: =IFERROR(+CJ36/BU36,0%) -> 0.10493485 | CM36: =-DATOS!D117 -> -47263 | CN36: =+CM36/CM$13 -> -0.015536483 | CP36: =-DATOS!F117 -> -7772 | CQ36: =+CP36/CP$13 -> -0.015085506 | CS36: =-DATOS!G117 -> -43610.5 | CT36: =+CS36/CS$13 -> -0.014838891 | CV36: =+CM36-CS36 -> -3652.5 | CW36: =+IFERROR(CV36/CS36,0) -> 0.083752766
A37: 520472 | B37: Aportes Cajas De Compensacion | D37: -328 | E37: -334 | F37: -242 | G37: -333 | H37: -527 | I37: -285 | J37: -294 | K37: 0 | L37: -226 | M37: =SUM(D37:L37) -> -2569 | N37: =+M37/M$13 -> -0.0050894568 | P37: -275 | Q37: -407 | R37: -192 | S37: -391 | T37: -600 | U37: -317 | V37: -247 | W37: 0 | X37: -176 | Y37: =SUM(P37:X37) -> -2605 | Z37: =+Y37/Y$13 -> -0.0049498178 | AB37: -250 | AC37: -329 | AD37: -176 | AE37: -329 | AF37: -761 | AG37: -395 | AH37: -248 | AI37: 0 | AJ37: -287 | AK37: =SUM(AB37:AJ37) -> -2775 | AL37: =+AK37/AK$13 -> -0.0054226226 | AN37: -300 | AO37: -267 | AP37: -174 | AQ37: -279 | AR37: -685 | AS37: -318 | AT37: -263 | AU37: 0 | AV37: -235 | AW37: =SUM(AN37:AV37) -> -2521 | AX37: =+AW37/AW$13 -> -0.0047474314 | AZ37: -307 | BA37: -248 | BB37: -186 | BC37: -310 | BD37: -747 | BE37: -416 | BF37: -264 | BG37: 0 | BH37: -262 | BI37: =SUM(AZ37:BH37) -> -2740 | BJ37: =+BI37/BI$13 -> -0.0055248173 | BL37: -252 | BM37: -253 | BN37: -242 | BO37: -212 | BP37: -619 | BQ37: -391 | BR37: -248 | BS37: 0 | BT37: -314 | BU37: =SUM(BL37:BT37) -> -2531 | BV37: =+BU37/BU$13 -> -0.0050917972 | BX37: -320 | BY37: -218 | BZ37: -168 | CA37: -332 | CB37: -663 | CC37: -327 | CD37: -260 | CE37: 0 | CF37: -255 | CG37: =SUM(BX37:CF37) -> -2543 | CH37: =+CG37/CG$13 -> -0.0052980491 | CJ37: =+CG37-BU37 -> -12 | CK37: =IFERROR(+CJ37/BU37,0%) -> 0.004741209 | CM37: =-DATOS!D118 -> -15715.5 | CN37: =+CM37/CM$13 -> -0.0051660623 | CP37: =-DATOS!F118 -> -2596.5 | CQ37: =+CP37/CP$13 -> -0.0050398246 | CS37: =-DATOS!G118 -> -14613.5 | CT37: =+CS37/CS$13 -> -0.0049723837 | CV37: =+CM37-CS37 -> -1102 | CW37: =+IFERROR(CV37/CS37,0) -> 0.075409724
A38: 520478 | B38: SENA | D38: 0 | E38: 0 | F38: 0 | G38: 0 | H38: 0 | I38: 0 | J38: 0 | K38: 0 | L38: 0 | M38: =SUM(D38:L38) -> 0 | N38: =+M38/M$13 -> 0 | P38: 0 | Q38: 0 | R38: 0 | S38: 0 | T38: 0 | U38: 0 | V38: 0 | W38: 0 | X38: 0 | Y38: =SUM(P38:X38) -> 0 | Z38: =+Y38/Y$13 -> 0 | AB38: 0 | AC38: 0 | AD38: 0 | AE38: 0 | AF38: 0 | AG38: 0 | AH38: 0 | AI38: 0 | AJ38: 0 | AK38: =SUM(AB38:AJ38) -> 0 | AL38: =+AK38/AK$13 -> 0 | AN38: 0 | AO38: 0 | AP38: 0 | AQ38: 0 | AR38: 0 | AS38: 0 | AT38: 0 | AU38: 0 | AV38: 0 | AW38: =SUM(AN38:AV38) -> 0 | AX38: =+AW38/AW$13 -> 0 | AZ38: 0 | BA38: 0 | BB38: 0 | BC38: 0 | BD38: 0 | BE38: 0 | BF38: 0 | BG38: 0 | BH38: 0 | BI38: =SUM(AZ38:BH38) -> 0 | BJ38: =+BI38/BI$13 -> 0 | BL38: 0 | BM38: 0 | BN38: 0 | BO38: 0 | BP38: 0 | BQ38: 0 | BR38: 0 | BS38: 0 | BT38: 0 | BU38: =SUM(BL38:BT38) -> 0 | BV38: =+BU38/BU$13 -> 0 | BX38: 0 | BY38: 0 | BZ38: 0 | CA38: 0 | CB38: 0 | CC38: 0 | CD38: 0 | CE38: 0 | CF38: 0 | CG38: =SUM(BX38:CF38) -> 0 | CH38: =+CG38/CG$13 -> 0 | CJ38: =+CG38-BU38 -> 0 | CK38: =IFERROR(+CJ38/BU38,0%) -> 0 | CM38: 0 | CN38: =+CM38/CM$13 -> 0 | CP38: 0 | CQ38: =+CP38/CP$13 -> 0 | CS38: 0 | CT38: =+CS38/CS$13 -> 0 | CV38: =+CM38-CS38 -> 0 | CW38: =+IFERROR(CV38/CS38,0) -> 0
A39: 5205 | B39: Gasto de personal | D39: =+SUM(D40:D59) -> -9786 | E39: =+SUM(E40:E59) -> -11672 | F39: =+SUM(F40:F59) -> -8759 | G39: =+SUM(G40:G59) -> -14111 | H39: =+SUM(H40:H60) -> -23937 | I39: =+SUM(I40:I59) -> -11251 | J39: =+SUM(J40:J59) -> -10592 | K39: =+SUM(K40:K59) -> -298 | L39: =+SUM(L40:L59) -> -8976 | M39: =+SUM(M40:M60) -> -99382 | N39: =+M39/M$13 -> -0.1968861 | P39: =+SUM(P40:P59) -> -10673 | Q39: =+SUM(Q40:Q59) -> -10972 | R39: =+SUM(R40:R59) -> -5583 | S39: =+SUM(S40:S59) -> -15579 | T39: =+SUM(T40:T60) -> -20226 | U39: =+SUM(U40:U59) -> -10040 | V39: =+SUM(V40:V59) -> -8649 | W39: =+SUM(W40:W59) -> 0 | X39: =+SUM(X40:X59) -> -8249 | Y39: =+SUM(Y40:Y60) -> -92106 | Z39: =+Y39/Y$13 -> -0.17501264 | AB39: =+SUM(AB40:AB59) -> -9155 | AC39: =+SUM(AC40:AC59) -> -10959 | AD39: =+SUM(AD40:AD59) -> -5400 | AE39: =+SUM(AE40:AE59) -> -12833 | AF39: =+SUM(AF40:AF60) -> -23153 | AG39: =+SUM(AG40:AG59) -> -12439 | AH39: =+SUM(AH40:AH59) -> -7148 | AI39: =+SUM(AI40:AI59) -> 0 | AJ39: =+SUM(AJ40:AJ59) -> -9141 | AK39: =+SUM(AK40:AK60) -> -92854 | AL39: =+AK39/AK$13 -> -0.18144584 | AN39: =+SUM(AN40:AN59) -> -10338 | AO39: =+SUM(AO40:AO59) -> -8394 | AP39: =+SUM(AP40:AP59) -> -6023 | AQ39: =+SUM(AQ40:AQ59) -> -9556 | AR39: =+SUM(AR40:AR60) -> -23010 | AS39: =+SUM(AS40:AS59) -> -10200 | AT39: =+SUM(AT40:AT59) -> -8027 | AU39: =+SUM(AU40:AU59) -> 0 | AV39: =+SUM(AV40:AV59) -> -8434 | AW39: =+SUM(AW40:AW60) -> -85295 | AX39: =+AW39/AW$13 -> -0.16062363 | AZ39: =+SUM(AZ40:AZ59) -> -8394 | BA39: =+SUM(BA40:BA59) -> -8815 | BB39: =+SUM(BB40:BB59) -> -5674 | BC39: =+SUM(BC40:BC59) -> -10500 | BD39: =+SUM(BD40:BD60) -> -24938 | BE39: =+SUM(BE40:BE59) -> -12980 | BF39: =+SUM(BF40:BF59) -> -8744 | BG39: =+SUM(BG40:BG59) -> 0 | BH39: =+SUM(BH40:BH59) -> -9870 | BI39: =+SUM(BI40:BI60) -> -89915 | BJ39: =+BI39/BI$13 -> -0.18130071 | BL39: =+SUM(BL40:BL59) -> -6951 | BM39: =+SUM(BM40:BM59) -> -9279 | BN39: =+SUM(BN40:BN59) -> -7010 | BO39: =+SUM(BO40:BO59) -> -8341 | BP39: =+SUM(BP40:BP60) -> -20300 | BQ39: =+SUM(BQ40:BQ59) -> -11674 | BR39: =+SUM(BR40:BR59) -> -8857 | BS39: =+SUM(BS40:BS59) -> 0 | BT39: =+SUM(BT40:BT59) -> -11700 | BU39: =+SUM(BU40:BU60) -> -84112 | BV39: =+BU39/BU$13 -> -0.16921424 | BX39: =+SUM(BX40:BX59) -> -9641 | BY39: =+SUM(BY40:BY59) -> -6872 | BZ39: =+SUM(BZ40:BZ59) -> -5468 | CA39: =+SUM(CA40:CA59) -> -15488 | CB39: =+SUM(CB40:CB60) -> -22655 | CC39: =+SUM(CC40:CC59) -> -12007 | CD39: =+SUM(CD40:CD59) -> -8157 | CE39: =+SUM(CE40:CE59) -> 0 | CF39: =+SUM(CF40:CF59) -> -9281 | CG39: =+SUM(CG40:CG60) -> -89569 | CH39: =+CG39/CG$13 -> -0.18660675 | CJ39: =+CG39-BU39 -> -5457 | CK39: =IFERROR(+CJ39/BU39,0%) -> 0.064877782 | CM39: =+SUM(CM40:CM60) -> -533858.5 | CN39: =+CM39/CM$13 -> -0.17549211 | CP39: =+SUM(CP40:CP60) -> -90567 | CQ39: =+CP39/CP$13 -> -0.17579118 | CS39: =+SUM(CS40:CS60) -> -493063 | CT39: =+CS39/CS$13 -> -0.16776942 | CV39: =+CM39-CS39 -> -40795.5 | CW39: =+IFERROR(CV39/CS39,0) -> 0.08273892
A40: 52050601 | B40: Sueldos | D40: -5113 | E40: -6363 | F40: -4502 | G40: -6508 | H40: -9817 | I40: -6072 | J40: -4969 | K40: 0 | L40: -5066 | M40: =SUM(D40:L40) -> -48410 | N40: =+M40/M$13 -> -0.095905256 | P40: -5836 | Q40: -6682 | R40: -3043 | S40: -6925 | T40: -9542 | U40: -5631 | V40: -5356 | W40: 0 | X40: -4261 | Y40: =SUM(P40:X40) -> -47276 | Z40: =+Y40/Y$13 -> -0.089830167 | AB40: -5603 | AC40: -7440 | AD40: -3210 | AE40: -6468 | AF40: -11910 | AG40: -8694 | AH40: -4959 | AI40: 0 | AJ40: -5836 | AK40: =SUM(AB40:AJ40) -> -54120 | AL40: =+AK40/AK$13 -> -0.1057558 | AN40: -7004 | AO40: -5398 | AP40: -3385 | AQ40: -5603 | AR40: -14001 | AS40: -6826 | AT40: -5368 | AU40: 0 | AV40: -5545 | AW40: =SUM(AN40:AV40) -> -53130 | AX40: =+AW40/AW$13 -> -0.10005198 | AZ40: -5078 | BA40: -5690 | BB40: -3093 | BC40: -5274 | BD40: -12871 | BE40: -8461 | BF40: -5776 | BG40: 0 | BH40: -5720 | BI40: =SUM(AZ40:BH40) -> -51963 | BJ40: =+BI40/BI$13 -> -0.10477594 | BL40: -3428 | BM40: -5281 | BN40: -3969 | BO40: -3932 | BP40: -10202 | BQ40: -6768 | BR40: -5834 | BS40: 0 | BT40: -7253 | BU40: =SUM(BL40:BT40) -> -46667 | BV40: =+BU40/BU$13 -> -0.093883406 | BX40: -5255 | BY40: -4814 | BZ40: -3560 | CA40: -6965 | CB40: -11217 | CC40: -7527 | CD40: -5484 | CE40: 0 | CF40: -5216 | CG40: =SUM(BX40:CF40) -> -50038 | CH40: =+CG40/CG$13 -> -0.10424844 | CJ40: =+CG40-BU40 -> -3371 | CK40: =IFERROR(+CJ40/BU40,0%) -> 0.072235198 | CM40: =-DATOS!D119 -> -303194 | CN40: =+CM40/CM$13 -> -0.09966715 | CP40: =-DATOS!F119 -> -51262 | CQ40: =+CP40/CP$13 -> -0.0994999 | CS40: =-DATOS!G119 -> -281725 | CT40: =+CS40/CS$13 -> -0.095859636 | CV40: =+CM40-CS40 -> -21469 | CW40: =+IFERROR(CV40/CS40,0) -> 0.07620552
A41: 52051501 | B41: Horas Extras | D41: -658 | E41: -788 | F41: -1141 | G41: -2456 | H41: -3171 | I41: -729 | J41: -499 | K41: 0 | L41: -1412 | M41: =SUM(D41:L41) -> -10854 | N41: =+M41/M$13 -> -0.021502905 | P41: -1323 | Q41: -772 | R41: -580 | S41: -3955 | T41: -4720 | U41: -507 | V41: -242 | W41: 0 | X41: -1232 | Y41: =SUM(P41:X41) -> -13331 | Z41: =+Y41/Y$13 -> -0.025330526 | AB41: -594 | AC41: -787 | AD41: -726 | AE41: -3051 | AF41: -4349 | AG41: -252 | AH41: -238 | AI41: 0 | AJ41: -852 | AK41: =SUM(AB41:AJ41) -> -10849 | AL41: =+AK41/AK$13 -> -0.021200012 | AN41: -501 | AO41: -225 | AP41: -755 | AQ41: -1543 | AR41: -1664 | AS41: -40 | AT41: -196 | AU41: 0 | AV41: -724 | AW41: =SUM(AN41:AV41) -> -5648 | AX41: =+AW41/AW$13 -> -0.010636054 | AZ41: -877 | BA41: -516 | BB41: -777 | BC41: -2659 | BD41: -4403 | BE41: -88 | BF41: -682 | BG41: 0 | BH41: -1746 | BI41: =SUM(AZ41:BH41) -> -11748 | BJ41: =+BI41/BI$13 -> -0.023688158 | BL41: -861 | BM41: -740 | BN41: -865 | BO41: -2045 | BP41: -3807 | BQ41: -691 | BR41: -298 | BS41: 0 | BT41: -1412 | BU41: =SUM(BL41:BT41) -> -10719 | BV41: =+BU41/BU$13 -> -0.021564194 | BX41: -1305 | BY41: -580 | BZ41: -577 | CA41: -2617 | CB41: -3195 | CC41: -730 | CD41: -296 | CE41: 0 | CF41: -1449 | CG41: =SUM(BX41:CF41) -> -10749 | CH41: =+CG41/CG$13 -> -0.02239431 | CJ41: =+CG41-BU41 -> -30 | CK41: =IFERROR(+CJ41/BU41,0%) -> 0.0027987685 | CM41: =-DATOS!D120 -> -63045 | CN41: =+CM41/CM$13 -> -0.020724406 | CP41: =-DATOS!F120 -> -10669 | CQ41: =+CP41/CP$13 -> -0.020708603 | CS41: =-DATOS!G120 -> -53832 | CT41: =+CS41/CS$13 -> -0.018316855 | CV41: =+CM41-CS41 -> -9213 | CW41: =+IFERROR(CV41/CS41,0) -> 0.17114356
A42: 52052401 | B42: Incapacidades | D42: -95 | E42: 0 | F42: -47 | G42: -47 | H42: 0 | I42: -142 | J42: -190 | K42: 0 | L42: 0 | M42: =SUM(D42:L42) -> -521 | N42: =+M42/M$13 -> -0.0010321553 | P42: 0 | Q42: -292 | R42: -117 | S42: -467 | T42: -168 | U42: -117 | V42: 0 | W42: 0 | X42: 0 | Y42: =SUM(P42:X42) -> -1161 | Z42: =+Y42/Y$13 -> -0.0022060416 | AB42: 0 | AC42: 0 | AD42: 0 | AE42: -175 | AF42: 0 | AG42: 0 | AH42: 0 | AI42: 0 | AJ42: 0 | AK42: =SUM(AB42:AJ42) -> -175 | AL42: =+AK42/AK$13 -> -0.00034196719 | AN42: 0 | AO42: -295 | AP42: 0 | AQ42: 0 | AR42: 0 | AS42: 0 | AT42: 0 | AU42: 0 | AV42: 0 | AW42: =SUM(AN42:AV42) -> -295 | AX42: =+AW42/AW$13 -> -0.00055553045 | AZ42: 0 | BA42: 0 | BB42: 0 | BC42: 0 | BD42: -117 | BE42: 0 | BF42: 0 | BG42: 0 | BH42: -58 | BI42: =SUM(AZ42:BH42) -> -175 | BJ42: =+BI42/BI$13 -> -0.00035286242 | BL42: -233 | BM42: -292 | BN42: 0 | BO42: -409 | BP42: 0 | BQ42: 0 | BR42: 0 | BS42: 0 | BT42: 0 | BU42: =SUM(BL42:BT42) -> -934 | BV42: =+BU42/BU$13 -> -0.0018789959 | BX42: 0 | BY42: 0 | BZ42: 0 | CA42: -1046 | CB42: 0 | CC42: -117 | CD42: 0 | CE42: 0 | CF42: -117 | CG42: =SUM(BX42:CF42) -> -1280 | CH42: =+CG42/CG$13 -> -0.0026667333 | CJ42: =+CG42-BU42 -> -346 | CK42: =IFERROR(+CJ42/BU42,0%) -> 0.37044968 | CM42: =-DATOS!D121 -> -4018 | CN42: =+CM42/CM$13 -> -0.0013208131 | CP42: =-DATOS!F121 -> -348 | CQ42: =+CP42/CP$13 -> -0.00067547043 | CS42: =-DATOS!G121 -> -2969 | CT42: =+CS42/CS$13 -> -0.0010102308 | CV42: =+CM42-CS42 -> -1049 | CW42: =+IFERROR(CV42/CS42,0) -> 0.35331762
A43: 52052701 | B43: Auxilio De Transporte | D43: -680 | E43: -787 | F43: -500 | G43: -900 | H43: -1153 | I43: -760 | J43: -560 | K43: 0 | L43: -640 | M43: =SUM(D43:L43) -> -5980 | N43: =+M43/M$13 -> -0.011847003 | P43: -830 | Q43: -888 | R43: -349 | S43: -955 | T43: -1196 | U43: -756 | V43: -689 | W43: 0 | X43: -606 | Y43: =SUM(P43:X43) -> -6269 | Z43: =+Y43/Y$13 -> -0.011911865 | AB43: -797 | AC43: -996 | AD43: -448 | AE43: -905 | AF43: -1129 | AG43: -1146 | AH43: -614 | AI43: 0 | AJ43: -830 | AK43: =SUM(AB43:AJ43) -> -6865 | AL43: =+AK43/AK$13 -> -0.013414884 | AN43: -996 | AO43: -706 | AP43: -482 | AQ43: -797 | AR43: -1453 | AS43: -880 | AT43: -672 | AU43: 0 | AV43: -789 | AW43: =SUM(AN43:AV43) -> -6775 | AX43: =+AW43/AW$13 -> -0.012758369 | AZ43: -722 | BA43: -747 | BB43: -440 | BC43: -747 | BD43: -1378 | BE43: -1104 | BF43: -722 | BG43: 0 | BH43: -814 | BI43: =SUM(AZ43:BH43) -> -6674 | BJ43: =+BI43/BI$13 -> -0.013457165 | BL43: -482 | BM43: -673 | BN43: -565 | BO43: -556 | BP43: -1005 | BQ43: -872 | BR43: -739 | BS43: 0 | BT43: -980 | BU43: =SUM(BL43:BT43) -> -5872 | BV43: =+BU43/BU$13 -> -0.01181313 | BX43: -681 | BY43: -623 | BZ43: -498 | CA43: -913 | CB43: -1138 | CC43: -980 | CD43: -689 | CE43: 0 | CF43: -747 | CG43: =SUM(BX43:CF43) -> -6269 | CH43: =+CG43/CG$13 -> -0.013060743 | CJ43: =+CG43-BU43 -> -397 | CK43: =IFERROR(+CJ43/BU43,0%) -> 0.067608992 | CM43: =-DATOS!D122 -> -38726 | CN43: =+CM43/CM$13 -> -0.012730166 | CP43: =-DATOS!F122 -> -5980 | CQ43: =+CP43/CP$13 -> -0.011607222 | CS43: =-DATOS!G122 -> -33073 | CT43: =+CS43/CS$13 -> -0.011253406 | CV43: =+CM43-CS43 -> -5653 | CW43: =+IFERROR(CV43/CS43,0) -> 0.17092492
A44: 52053001 | B44: Cesantias | D44: -1180 | E44: -1169 | F44: -977 | G44: -1264 | H44: -1130 | I44: -1143 | J44: -1021 | K44: 0 | L44: -991 | M44: =SUM(D44:L44) -> -8875 | N44: =+M44/M$13 -> -0.0175823 | P44: -760 | Q44: -754 | R44: -222 | S44: -978 | T44: -1364 | U44: -793 | V44: -573 | W44: 0 | X44: -632 | Y44: =SUM(P44:X44) -> -6076 | Z44: =+Y44/Y$13 -> -0.011545141 | AB44: -623 | AC44: -769 | AD44: -408 | AE44: -719 | AF44: -1669 | AG44: -924 | AH44: -568 | AI44: 0 | AJ44: -662 | AK44: =SUM(AB44:AJ44) -> -6342 | AL44: =+AK44/AK$13 -> -0.012392891 | AN44: -708 | AO44: -552 | AP44: -403 | AQ44: -633 | AR44: -1548 | AS44: -714 | AT44: -550 | AU44: 0 | AV44: -552 | AW44: =SUM(AN44:AV44) -> -5660 | AX44: =+AW44/AW$13 -> -0.010658652 | AZ44: -684 | BA44: -579 | BB44: -429 | BC44: -627 | BD44: -1656 | BE44: -960 | BF44: -612 | BG44: 0 | BH44: -611 | BI44: =SUM(AZ44:BH44) -> -6158 | BJ44: =+BI44/BI$13 -> -0.012416724 | BL44: -492 | BM44: -609 | BN44: -353 | BO44: -290 | BP44: -1315 | BQ44: -801 | BR44: -540 | BS44: 0 | BT44: -523 | BU44: =SUM(BL44:BT44) -> -4923 | BV44: =+BU44/BU$13 -> -0.009903958 | BX44: -728 | BY44: -505 | BZ44: -389 | CA44: -570 | CB44: -1439 | CC44: -771 | CD44: -604 | CE44: 0 | CF44: -588 | CG44: =SUM(BX44:CF44) -> -5594 | CH44: =+CG44/CG$13 -> -0.011654458 | CJ44: =+CG44-BU44 -> -671 | CK44: =IFERROR(+CJ44/BU44,0%) -> 0.136299 | CM44: =-DATOS!D123 -> -34754 | CN44: =+CM44/CM$13 -> -0.011424475 | CP44: =-DATOS!F123 -> -6351 | CQ44: =+CP44/CP$13 -> -0.012327335 | CS44: =-DATOS!G123 -> -32795 | CT44: =+CS44/CS$13 -> -0.011158814 | CV44: =+CM44-CS44 -> -1959 | CW44: =+IFERROR(CV44/CS44,0) -> 0.059734716
A45: 52053301 | B45: Intereses Sobre Cesantias | D45: -120 | E45: -138 | F45: -137 | G45: -112 | H45: -106 | I45: -150 | J45: -125 | K45: 0 | L45: -111 | M45: =SUM(D45:L45) -> -999 | N45: =+M45/M$13 -> -0.0019791231 | P45: -7 | Q45: -8 | R45: -2 | S45: -9 | T45: -12 | U45: -8 | V45: -6 | W45: 0 | X45: -6 | Y45: =SUM(P45:X45) -> -58 | Z45: =+Y45/Y$13 -> -0.00011020708 | AB45: -16 | AC45: -23 | AD45: -12 | AE45: -19 | AF45: -42 | AG45: -25 | AH45: -17 | AI45: 0 | AJ45: -18 | AK45: =SUM(AB45:AJ45) -> -172 | AL45: =+AK45/AK$13 -> -0.0003361049 | AN45: -33 | AO45: -28 | AP45: -20 | AQ45: -32 | AR45: -71 | AS45: -38 | AT45: -26 | AU45: 0 | AV45: -23 | AW45: =SUM(AN45:AV45) -> -271 | AX45: =+AW45/AW$13 -> -0.00051033475 | AZ45: -43 | BA45: -40 | BB45: -30 | BC45: -35 | BD45: -104 | BE45: -66 | BF45: -40 | BG45: 0 | BH45: -36 | BI45: =SUM(AZ45:BH45) -> -394 | BJ45: =+BI45/BI$13 -> -0.00079444453 | BL45: -32 | BM45: -53 | BN45: -29 | BO45: -29 | BP45: -109 | BQ45: -57 | BR45: -49 | BS45: 0 | BT45: -38 | BU45: =SUM(BL45:BT45) -> -396 | BV45: =+BU45/BU$13 -> -0.00079666207 | BX45: -60 | BY45: -59 | BZ45: -27 | CA45: -50 | CB45: -130 | CC45: -67 | CD45: -64 | CE45: 0 | CF45: -58 | CG45: =SUM(BX45:CF45) -> -515 | CH45: =+CG45/CG$13 -> -0.0010729435 | CJ45: =+CG45-BU45 -> -119 | CK45: =IFERROR(+CJ45/BU45,0%) -> 0.30050505 | CM45: =-DATOS!D124 -> -1809 | CN45: =+CM45/CM$13 -> -0.00059466175 | CP45: =-DATOS!F124 -> -599 | CQ45: =+CP45/CP$13 -> -0.0011626632 | CS45: =-DATOS!G124 -> -1893 | CT45: =+CS45/CS$13 -> -0.00064411142 | CV45: =+CM45-CS45 -> 84 | CW45: =+IFERROR(CV45/CS45,0) -> -0.04437401
A46: 52053601 | B46: Prima De Servicios | D46: -749 | E46: -743 | F46: -638 | G46: -758 | H46: -1194 | I46: -737 | J46: -628 | K46: 0 | L46: -593 | M46: =SUM(D46:L46) -> -6040 | N46: =+M46/M$13 -> -0.01196587 | P46: -605 | Q46: -714 | R46: -196 | S46: -899 | T46: -1241 | U46: -729 | V46: -555 | W46: 0 | X46: -574 | Y46: =SUM(P46:X46) -> -5513 | Z46: =+Y46/Y$13 -> -0.010475373 | AB46: -617 | AC46: -746 | AD46: -362 | AE46: -708 | AF46: -1677 | AG46: -913 | AH46: -564 | AI46: 0 | AJ46: -649 | AK46: =SUM(AB46:AJ46) -> -6236 | AL46: =+AK46/AK$13 -> -0.012185757 | AN46: -712 | AO46: -553 | AP46: -398 | AQ46: -637 | AR46: -1585 | AS46: -715 | AT46: -537 | AU46: 0 | AV46: -551 | AW46: =SUM(AN46:AV46) -> -5688 | AX46: =+AW46/AW$13 -> -0.01071138 | AZ46: -675 | BA46: -575 | BB46: -421 | BC46: -627 | BD46: -1644 | BE46: -951 | BF46: -594 | BG46: 0 | BH46: -602 | BI46: =SUM(AZ46:BH46) -> -6089 | BJ46: =+BI46/BI$13 -> -0.012277596 | BL46: -490 | BM46: -601 | BN46: -553 | BO46: -477 | BP46: -1297 | BQ46: -765 | BR46: -572 | BS46: 0 | BT46: -726 | BU46: =SUM(BL46:BT46) -> -5481 | BV46: =+BU46/BU$13 -> -0.011026527 | BX46: -1084 | BY46: -58 | BZ46: -161 | CA46: -2402 | CB46: -2853 | CC46: -1176 | CD46: -664 | CE46: 0 | CF46: -760 | CG46: =SUM(BX46:CF46) -> -9158 | CH46: =+CG46/CG$13 -> -0.019079644 | CJ46: =+CG46-BU46 -> -3677 | CK46: =IFERROR(+CJ46/BU46,0%) -> 0.67086298 | CM46: =-DATOS!D125 -> -38162 | CN46: =+CM46/CM$13 -> -0.012544766 | CP46: =-DATOS!F125 -> -5639 | CQ46: =+CP46/CP$13 -> -0.010945338 | CS46: =-DATOS!G125 -> -32101 | CT46: =+CS46/CS$13 -> -0.010922673 | CV46: =+CM46-CS46 -> -6061 | CW46: =+IFERROR(CV46/CS46,0) -> 0.18881032
A47: 52053901 | B47: Vacaciones | D47: -447 | E47: -1223 | F47: -204 | G47: -558 | H47: -3664 | I47: -762 | J47: -712 | K47: 0 | L47: -152 | M47: =SUM(D47:L47) -> -7722 | N47: =+M47/M$13 -> -0.015298087 | P47: -716 | Q47: -668 | R47: -777 | S47: -952 | T47: -1250 | U47: -945 | V47: -803 | W47: 0 | X47: -911 | Y47: =SUM(P47:X47) -> -7022 | Z47: =+Y47/Y$13 -> -0.013342657 | AB47: -293 | AC47: -184 | AD47: -229 | AE47: -336 | AF47: -844 | AG47: -322 | AH47: -79 | AI47: 0 | AJ47: -286 | AK47: =SUM(AB47:AJ47) -> -2573 | AL47: =+AK47/AK$13 -> -0.0050278948 | AN47: -307 | AO47: -245 | AP47: -237 | AQ47: -303 | AR47: -790 | AS47: -403 | AT47: -337 | AU47: 0 | AV47: -245 | AW47: =SUM(AN47:AV47) -> -2867 | AX47: =+AW47/AW$13 -> -0.0053990027 | AZ47: -305 | BA47: -250 | BB47: -239 | BC47: -425 | BD47: -812 | BE47: -633 | BF47: -307 | BG47: 0 | BH47: -275 | BI47: =SUM(AZ47:BH47) -> -3246 | BJ47: =+BI47/BI$13 -> -0.0065450938 | BL47: -45 | BM47: -24 | BN47: 8 | BO47: 253 | BP47: 736 | BQ47: -65 | BR47: -299 | BS47: 0 | BT47: -166 | BU47: =SUM(BL47:BT47) -> 398 | BV47: =+BU47/BU$13 -> 0.00080068561 | BX47: -246 | BY47: -238 | BZ47: -146 | CA47: -566 | CB47: -576 | CC47: -316 | CD47: -246 | CE47: 0 | CF47: -213 | CG47: =SUM(BX47:CF47) -> -2547 | CH47: =+CG47/CG$13 -> -0.0053063827 | CJ47: =+CG47-BU47 -> -2945 | CK47: =IFERROR(+CJ47/BU47,0%) -> -7.3994975 | CM47: =-DATOS!D126 -> -17854 | CN47: =+CM47/CM$13 -> -0.0058690387 | CP47: =-DATOS!F126 -> -3884 | CQ47: =+CP47/CP$13 -> -0.0075388711 | CS47: =-DATOS!G126 -> -18951 | CT47: =+CS47/CS$13 -> -0.0064482597 | CV47: =+CM47-CS47 -> 1097 | CW47: =+IFERROR(CV47/CS47,0) -> -0.057886127
A48: 52054502 | B48: Auxilios | D48: 0 | E48: 0 | F48: 0 | G48: 0 | H48: 0 | I48: 0 | J48: 0 | K48: 0 | L48: 0 | M48: =SUM(D48:L48) -> 0 | N48: =+M48/M$13 -> 0 | P48: 0 | Q48: 0 | R48: 0 | S48: 0 | T48: 0 | U48: 0 | V48: 0 | W48: 0 | X48: 0 | Y48: =SUM(P48:X48) -> 0 | Z48: =+Y48/Y$13 -> 0 | AB48: 0 | AC48: 0 | AD48: 0 | AE48: 0 | AF48: 0 | AG48: 0 | AH48: 0 | AI48: 0 | AJ48: 0 | AK48: =SUM(AB48:AJ48) -> 0 | AL48: =+AK48/AK$13 -> 0 | AN48: 0 | AO48: 0 | AP48: 0 | AQ48: 0 | AR48: 0 | AS48: 0 | AT48: 0 | AU48: 0 | AV48: 0 | AW48: =SUM(AN48:AV48) -> 0 | AX48: =+AW48/AW$13 -> 0 | AZ48: 0 | BA48: 0 | BB48: 0 | BC48: 0 | BD48: 0 | BE48: 0 | BF48: 0 | BG48: 0 | BH48: 0 | BI48: =SUM(AZ48:BH48) -> 0 | BJ48: =+BI48/BI$13 -> 0 | BL48: 0 | BM48: 0 | BN48: 0 | BO48: 0 | BP48: 0 | BQ48: 0 | BR48: 0 | BS48: 0 | BT48: 0 | BU48: =SUM(BL48:BT48) -> 0 | BV48: =+BU48/BU$13 -> 0 | BX48: 0 | BY48: 0 | BZ48: 0 | CA48: 0 | CB48: 0 | CC48: 0 | CD48: 0 | CE48: 0 | CF48: 0 | CG48: =SUM(BX48:CF48) -> 0 | CH48: =+CG48/CG$13 -> 0 | CJ48: =+CG48-BU48 -> 0 | CK48: =IFERROR(+CJ48/BU48,0%) -> 0 | CM48: =-DATOS!D127 -> 0 | CN48: =+CM48/CM$13 -> 0 | CP48: =-DATOS!F127 -> -400 | CQ48: =+CP48/CP$13 -> -0.00077640279 | CS48: =-DATOS!G127 -> -3117 | CT48: =+CS48/CS$13 -> -0.0010605892 | CV48: =+CM48-CS48 -> 3117 | CW48: =+IFERROR(CV48/CS48,0) -> -1
A49: 52054801 | B49: Bonificación Salarial | D49: 0 | E49: 0 | F49: -300 | G49: 0 | H49: 0 | I49: 0 | J49: 0 | K49: 0 | L49: 0 | M49: =SUM(D49:L49) -> -300 | N49: =+M49/M$13 -> -0.00059433127 | P49: 0 | Q49: 0 | R49: 0 | S49: 0 | T49: 0 | U49: 0 | V49: 0 | W49: 0 | X49: 0 | Y49: =SUM(P49:X49) -> 0 | Z49: =+Y49/Y$13 -> 0 | AB49: 0 | AC49: 0 | AD49: 0 | AE49: 0 | AF49: 0 | AG49: 0 | AH49: 0 | AI49: 0 | AJ49: 0 | AK49: =SUM(AB49:AJ49) -> 0 | AL49: =+AK49/AK$13 -> 0 | AN49: 0 | AO49: 0 | AP49: 0 | AQ49: 0 | AR49: 0 | AS49: 0 | AT49: 0 | AU49: 0 | AV49: 0 | AW49: =SUM(AN49:AV49) -> 0 | AX49: =+AW49/AW$13 -> 0 | AZ49: 0 | BA49: -390 | BB49: -240 | BC49: 0 | BD49: 0 | BE49: -504 | BF49: 0 | BG49: 0 | BH49: 0 | BI49: =SUM(AZ49:BH49) -> -1134 | BJ49: =+BI49/BI$13 -> -0.0022865485 | BL49: 0 | BM49: -382 | BN49: -240 | BO49: -174 | BP49: -510 | BQ49: -510 | BR49: 0 | BS49: 0 | BT49: 0 | BU49: =SUM(BL49:BT49) -> -1816 | BV49: =+BU49/BU$13 -> -0.0036533796 | BX49: 0 | BY49: 0 | BZ49: 0 | CA49: 0 | CB49: 0 | CC49: 0 | CD49: 0 | CE49: 0 | CF49: 0 | CG49: =SUM(BX49:CF49) -> 0 | CH49: =+CG49/CG$13 -> 0 | CJ49: =+CG49-BU49 -> 1816 | CK49: =IFERROR(+CJ49/BU49,0%) -> -1 | CM49: =-DATOS!D128 -> -2950 | CN49: =+CM49/CM$13 -> -0.00096973586 | CP49: =-DATOS!F128 -> -1250 | CQ49: =+CP49/CP$13 -> -0.0024262587 | CS49: =-DATOS!G128 -> -5750 | CT49: =+CS49/CS$13 -> -0.0019564927 | CV49: =+CM49-CS49 -> 2800 | CW49: =+IFERROR(CV49/CS49,0) -> -0.48695652
A50: 52054802 | B50: Bonificaciones no salariales | D50: -10 | E50: 0 | F50: 0 | G50: -216 | H50: -200 | I50: 0 | J50: 0 | K50: 0 | L50: 0 | M50: =SUM(D50:L50) -> -426 | N50: =+M50/M$13 -> -0.0008439504 | P50: -390 | Q50: -180 | R50: -270 | S50: -330 | T50: -510 | U50: -510 | V50: -390 | W50: 0 | X50: 0 | Y50: =SUM(P50:X50) -> -2580 | Z50: =+Y50/Y$13 -> -0.0049023147 | AB50: -407 | AC50: 0 | AD50: 0 | AE50: -240 | AF50: -390 | AG50: 0 | AH50: 0 | AI50: 0 | AJ50: 0 | AK50: =SUM(AB50:AJ50) -> -1037 | AL50: =+AK50/AK$13 -> -0.0020263999 | AN50: -69 | AO50: -381 | AP50: -240 | AQ50: 0 | AR50: -342 | AS50: -570 | AT50: -330 | AU50: 0 | AV50: 0 | AW50: =SUM(AN50:AV50) -> -1932 | AX50: =+AW50/AW$13 -> -0.0036382536 | AZ50: 0 | BA50: 0 | BB50: 0 | BC50: 0 | BD50: 0 | BE50: 0 | BF50: 0 | BG50: 0 | BH50: 0 | BI50: =SUM(AZ50:BH50) -> 0 | BJ50: =+BI50/BI$13 -> 0 | BL50: -108 | BM50: 0 | BN50: 0 | BO50: 0 | BP50: 0 | BQ50: 0 | BR50: 0 | BS50: 0 | BT50: 0 | BU50: =SUM(BL50:BT50) -> -108 | BV50: =+BU50/BU$13 -> -0.00021727147 | BX50: -52 | BY50: 0 | BZ50: 0 | CA50: 0 | CB50: 0 | CC50: 0 | CD50: 0 | CE50: 0 | CF50: 0 | CG50: =SUM(BX50:CF50) -> -52 | CH50: =+CG50/CG$13 -> -0.00010833604 | CJ50: =+CG50-BU50 -> 56 | CK50: =IFERROR(+CJ50/BU50,0%) -> -0.51851852 | CM50: =-DATOS!D129 -> -5709.5 | CN50: =+CM50/CM$13 -> -0.0018768498 | CP50: =-DATOS!F129 -> -1825.5 | CQ50: =+CP50/CP$13 -> -0.0035433082 | CS50: =-DATOS!G129 -> -11857 | CT50: =+CS50/CS$13 -> -0.0040344581 | CV50: =+CM50-CS50 -> 6147.5 | CW50: =+IFERROR(CV50/CS50,0) -> -0.5184701
A51: 52055101 | B51: Dotacion Y Suministros Al Trab | D51: -631 | E51: -447 | F51: -298 | G51: -1192 | H51: -1152 | I51: -745 | J51: -447 | K51: -298 | L51: 0 | M51: =SUM(D51:L51) -> -5210 | N51: =+M51/M$13 -> -0.010321553 | P51: 0 | Q51: 0 | R51: 0 | S51: -6 | T51: -6 | U51: -33 | V51: 0 | W51: 0 | X51: -6 | Y51: =SUM(P51:X51) -> -51 | Z51: =+Y51/Y$13 -> -9.6906221e-05 | AB51: -102 | AC51: 0 | AD51: 0 | AE51: -109 | AF51: -102 | AG51: -51 | AH51: 0 | AI51: 0 | AJ51: 0 | AK51: =SUM(AB51:AJ51) -> -364 | AL51: =+AK51/AK$13 -> -0.00071129176 | AN51: 0 | AO51: 0 | AP51: 0 | AQ51: 0 | AR51: -80 | AS51: 0 | AT51: 0 | AU51: 0 | AV51: 0 | AW51: =SUM(AN51:AV51) -> -80 | AX51: =+AW51/AW$13 -> -0.00015065232 | AZ51: 0 | BA51: 0 | BB51: 0 | BC51: 0 | BD51: -177 | BE51: 0 | BF51: 0 | BG51: 0 | BH51: 0 | BI51: =SUM(AZ51:BH51) -> -177 | BJ51: =+BI51/BI$13 -> -0.00035689513 | BL51: -682 | BM51: -514 | BN51: -346 | BO51: -682 | BP51: -941 | BQ51: -850 | BR51: -514 | BS51: 0 | BT51: -504 | BU51: =SUM(BL51:BT51) -> -5033 | BV51: =+BU51/BU$13 -> -0.010125253 | BX51: -225 | BY51: 5 | BZ51: -110 | CA51: -243 | CB51: -236 | CC51: -225 | CD51: -110 | CE51: 0 | CF51: -133 | CG51: =SUM(BX51:CF51) -> -1277 | CH51: =+CG51/CG$13 -> -0.0026604832 | CJ51: =+CG51-BU51 -> 3756 | CK51: =IFERROR(+CJ51/BU51,0%) -> -0.74627459 | CM51: =-DATOS!D130 -> -6981 | CN51: =+CM51/CM$13 -> -0.0022948224 | CP51: =-DATOS!F130 -> 0 | CQ51: =+CP51/CP$13 -> 0 | CS51: =-DATOS!G130 -> -10100 | CT51: =+CS51/CS$13 -> -0.003436622 | CV51: =+CM51-CS51 -> 3119 | CW51: =+IFERROR(CV51/CS51,0) -> -0.30881188
A52: 520560 | B52: Indemnizaciones | D52: 0 | E52: 0 | F52: 0 | G52: 0 | H52: 0 | I52: 0 | J52: -1424 | K52: 0 | L52: 0 | M52: =SUM(D52:L52) -> -1424 | N52: =+M52/M$13 -> -0.0028210924 | P52: 0 | Q52: 0 | R52: 0 | S52: 0 | T52: 0 | U52: 0 | V52: 0 | W52: 0 | X52: 0 | Y52: =SUM(P52:X52) -> 0 | Z52: =+Y52/Y$13 -> 0 | AB52: 0 | AC52: 0 | AD52: 0 | AE52: 0 | AF52: 0 | AG52: 0 | AH52: 0 | AI52: 0 | AJ52: 0 | AK52: =SUM(AB52:AJ52) -> 0 | AL52: =+AK52/AK$13 -> 0 | AN52: 0 | AO52: 0 | AP52: 0 | AQ52: 0 | AR52: 0 | AS52: 0 | AT52: 0 | AU52: 0 | AV52: 0 | AW52: =SUM(AN52:AV52) -> 0 | AX52: =+AW52/AW$13 -> 0 | AZ52: 0 | BA52: 0 | BB52: 0 | BC52: 0 | BD52: 0 | BE52: 0 | BF52: 0 | BG52: 0 | BH52: 0 | BI52: =SUM(AZ52:BH52) -> 0 | BJ52: =+BI52/BI$13 -> 0 | BL52: 0 | BM52: 0 | BN52: 0 | BO52: 0 | BP52: 0 | BQ52: 0 | BR52: 0 | BS52: 0 | BT52: 0 | BU52: =SUM(BL52:BT52) -> 0 | BV52: =+BU52/BU$13 -> 0 | BX52: 0 | BY52: 0 | BZ52: 0 | CA52: 0 | CB52: 0 | CC52: 0 | CD52: 0 | CE52: 0 | CF52: 0 | CG52: =SUM(BX52:CF52) -> 0 | CH52: =+CG52/CG$13 -> 0 | CJ52: =+CG52-BU52 -> 0 | CK52: =IFERROR(+CJ52/BU52,0%) -> 0 | CM52: =-DATOS!D131 -> 0 | CP52: =-+DATOS!F131 -> 0 | CS52: =+-DATOS!G131 -> 0
A53: 52056301 | B53: Capacitacion Al Personal | D53: 0 | E53: 0 | F53: 0 | G53: 0 | H53: -11 | I53: 0 | J53: 0 | K53: 0 | L53: 0 | M53: =SUM(D53:L53) -> -11 | N53: =+M53/M$13 -> -2.1792147e-05 | P53: 0 | Q53: 0 | R53: -12 | S53: 0 | T53: 0 | U53: 0 | V53: -12 | W53: 0 | X53: -12 | Y53: =SUM(P53:X53) -> -36 | Z53: =+Y53/Y$13 -> -6.8404392e-05 | AB53: 0 | AC53: 0 | AD53: 0 | AE53: 0 | AF53: 0 | AG53: 0 | AH53: 0 | AI53: 0 | AJ53: 0 | AK53: =SUM(AB53:AJ53) -> 0 | AL53: =+AK53/AK$13 -> 0 | AN53: 0 | AO53: 0 | AP53: 0 | AQ53: 0 | AR53: 0 | AS53: 0 | AT53: 0 | AU53: 0 | AV53: 0 | AW53: =SUM(AN53:AV53) -> 0 | AX53: =+AW53/AW$13 -> 0 | AZ53: 0 | BA53: 0 | BB53: 0 | BC53: 0 | BD53: 0 | BE53: 0 | BF53: 0 | BG53: 0 | BH53: 0 | BI53: =SUM(AZ53:BH53) -> 0 | BJ53: =+BI53/BI$13 -> 0 | BL53: 0 | BM53: -12 | BN53: 0 | BO53: 0 | BP53: 0 | BQ53: 0 | BR53: -12 | BS53: 0 | BT53: 0 | BU53: =SUM(BL53:BT53) -> -24 | BV53: =+BU53/BU$13 -> -4.8282549e-05 | BX53: 0 | BY53: 0 | BZ53: 0 | CA53: 0 | CB53: 0 | CC53: 0 | CD53: 0 | CE53: 0 | CF53: 0 | CG53: =SUM(BX53:CF53) -> 0 | CH53: =+CG53/CG$13 -> 0 | CJ53: =+CG53-BU53 -> 24 | CK53: =IFERROR(+CJ53/BU53,0%) -> -1 | CM53: =-DATOS!D132 -> -60 | CN53: =+CM53/CM$13 -> -1.9723441e-05 | CP53: =-DATOS!F132 -> 0 | CQ53: =+CP53/CP$13 -> 0 | CS53: =-DATOS!G132 -> -55 | CT53: =+CS53/CS$13 -> -1.8714278e-05 | CV53: =+CM53-CS53 -> -5 | CW53: =+IFERROR(CV53/CS53,0) -> 0.090909091
A54: 52056601 | B54: Gastos Recreativos | D54: 0 | E54: 0 | F54: 0 | G54: 0 | H54: 0 | I54: 0 | J54: 0 | K54: 0 | L54: 0 | M54: =SUM(D54:L54) -> 0 | N54: =+M54/M$13 -> 0 | P54: 0 | Q54: 0 | R54: 0 | S54: 0 | T54: 0 | U54: 0 | V54: 0 | W54: 0 | X54: 0 | Y54: =SUM(P54:X54) -> 0 | Z54: =+Y54/Y$13 -> 0 | AB54: 0 | AC54: 0 | AD54: 0 | AE54: 0 | AF54: 0 | AG54: 0 | AH54: 0 | AI54: 0 | AJ54: 0 | AK54: =SUM(AB54:AJ54) -> 0 | AL54: =+AK54/AK$13 -> 0 | AN54: 0 | AO54: 0 | AP54: 0 | AQ54: 0 | AR54: 0 | AS54: 0 | AT54: 0 | AU54: 0 | AV54: 0 | AW54: =SUM(AN54:AV54) -> 0 | AX54: =+AW54/AW$13 -> 0 | AZ54: 0 | BA54: 0 | BB54: 0 | BC54: 0 | BD54: 0 | BE54: 0 | BF54: 0 | BG54: 0 | BH54: 0 | BI54: =SUM(AZ54:BH54) -> 0 | BJ54: =+BI54/BI$13 -> 0 | BL54: 0 | BM54: 0 | BN54: 0 | BO54: 0 | BP54: 0 | BQ54: 0 | BR54: 0 | BS54: 0 | BT54: 0 | BU54: =SUM(BL54:BT54) -> 0 | BV54: =+BU54/BU$13 -> 0 | BX54: 0 | BY54: 0 | BZ54: 0 | CA54: 0 | CB54: 0 | CC54: 0 | CD54: 0 | CE54: 0 | CF54: 0 | CG54: =SUM(BX54:CF54) -> 0 | CH54: =+CG54/CG$13 -> 0 | CJ54: =+CG54-BU54 -> 0 | CK54: =IFERROR(+CJ54/BU54,0%) -> 0 | CM54: =-DATOS!D133 -> 0 | CN54: =+CM54/CM$13 -> 0 | CP54: 0 | CQ54: =+CP54/CP$13 -> 0 | CS54: 0 | CT54: =+CS54/CS$13 -> 0 | CV54: =+CM54-CS54 -> 0 | CW54: =+IFERROR(CV54/CS54,0) -> 0
A55: 520584 | B55: Gastos Medicos Y Drogas | D55: 0 | E55: 0 | F55: 0 | G55: 0 | H55: 0 | I55: 0 | J55: 0 | K55: 0 | L55: 0 | M55: =SUM(D55:L55) -> 0 | N55: =+M55/M$13 -> 0 | P55: 0 | Q55: 0 | R55: 0 | S55: 0 | T55: 0 | U55: 0 | V55: 0 | W55: 0 | X55: 0 | Y55: =SUM(P55:X55) -> 0 | Z55: =+Y55/Y$13 -> 0 | AB55: 0 | AC55: 0 | AD55: 0 | AE55: 0 | AF55: 0 | AG55: 0 | AH55: 0 | AI55: 0 | AJ55: 0 | AK55: =SUM(AB55:AJ55) -> 0 | AL55: =+AK55/AK$13 -> 0 | AN55: 0 | AO55: 0 | AP55: 0 | AQ55: 0 | AR55: 0 | AS55: 0 | AT55: 0 | AU55: 0 | AV55: 0 | AW55: =SUM(AN55:AV55) -> 0 | AX55: =+AW55/AW$13 -> 0 | AZ55: 0 | BA55: 0 | BB55: 0 | BC55: 0 | BD55: 0 | BE55: 0 | BF55: 0 | BG55: 0 | BH55: 0 | BI55: =SUM(AZ55:BH55) -> 0 | BJ55: =+BI55/BI$13 -> 0 | BL55: 0 | BM55: 0 | BN55: 0 | BO55: 0 | BP55: 0 | BQ55: 0 | BR55: 0 | BS55: 0 | BT55: 0 | BU55: =SUM(BL55:BT55) -> 0 | BV55: =+BU55/BU$13 -> 0 | BX55: 0 | BY55: 0 | BZ55: 0 | CA55: 0 | CB55: 0 | CC55: 0 | CD55: 0 | CE55: 0 | CF55: 0 | CG55: =SUM(BX55:CF55) -> 0 | CH55: =+CG55/CG$13 -> 0 | CJ55: =+CG55-BU55 -> 0 | CK55: =IFERROR(+CJ55/BU55,0%) -> 0 | CM55: 0 | CN55: =+CM55/CM$13 -> 0 | CP55: =-DATOS!F134 -> -338 | CQ55: =+CP55/CP$13 -> -0.00065606036 | CS55: =-DATOS!G134 -> -2371 | CT55: =+CS55/CS$13 -> -0.00080675551 | CV55: =+CM55-CS55 -> 2371 | CW55: =+IFERROR(CV55/CS55,0) -> -1
A56: 52058401 | B56: Gastos Medicos Y Drogas | D56: -92 | E56: 0 | F56: 0 | G56: -92 | H56: -184 | I56: 0 | J56: 0 | K56: 0 | L56: 0 | M56: =SUM(D56:L56) -> -368 | N56: =+M56/M$13 -> -0.00072904636 | P56: -197 | Q56: 0 | R56: 0 | S56: -98 | T56: -197 | U56: 0 | V56: -6 | W56: 0 | X56: 0 | Y56: =SUM(P56:X56) -> -498 | Z56: =+Y56/Y$13 -> -0.00094626075 | AB56: -98 | AC56: 0 | AD56: 0 | AE56: -98 | AF56: -149 | AG56: -98 | AH56: -98 | AI56: 0 | AJ56: 0 | AK56: =SUM(AB56:AJ56) -> -541 | AL56: =+AK56/AK$13 -> -0.0010571671 | AN56: 0 | AO56: 0 | AP56: -98 | AQ56: 0 | AR56: 0 | AS56: 0 | AT56: 0 | AU56: 0 | AV56: 0 | AW56: =SUM(AN56:AV56) -> -98 | AX56: =+AW56/AW$13 -> -0.0001845491 | AZ56: 0 | BA56: -17 | BB56: 0 | BC56: -98 | BD56: 0 | BE56: -197 | BF56: 0 | BG56: 0 | BH56: 0 | BI56: =SUM(AZ56:BH56) -> -312 | BJ56: =+BI56/BI$13 -> -0.00062910329 | BL56: -98 | BM56: -98 | BN56: -98 | BO56: 0 | BP56: -99 | BQ56: -295 | BR56: 0 | BS56: 0 | BT56: -98 | BU56: =SUM(BL56:BT56) -> -786 | BV56: =+BU56/BU$13 -> -0.0015812535 | BX56: -5 | BY56: 0 | BZ56: 0 | CA56: -116 | CB56: -237 | CC56: -98 | CD56: 0 | CE56: 0 | CF56: 0 | CG56: =SUM(BX56:CF56) -> -456 | CH56: =+CG56/CG$13 -> -0.00095002375 | CJ56: =+CG56-BU56 -> 330 | CK56: =IFERROR(+CJ56/BU56,0%) -> -0.41984733 | CM56: =-DATOS!D134 -> -2696 | CN56: =+CM56/CM$13 -> -0.00088623996 | CP56: 0 | CQ56: =+CP56/CP$13 -> 0 | CS56: 0 | CT56: =+CS56/CS$13 -> 0 | CV56: =+CM56-CS56 -> -2696 | CW56: =+IFERROR(CV56/CS56,0) -> 0
A57: 52059501 | B57: Otros Gastos De Personal | D57: -11 | E57: -14 | F57: -15 | G57: -8 | H57: -20 | I57: -11 | J57: -17 | K57: 0 | L57: -11 | M57: =SUM(D57:L57) -> -107 | N57: =+M57/M$13 -> -0.00021197815 | P57: -9 | Q57: -14 | R57: -15 | S57: -5 | T57: -20 | U57: -11 | V57: -17 | W57: 0 | X57: -9 | Y57: =SUM(P57:X57) -> -100 | Z57: =+Y57/Y$13 -> -0.0001900122 | AB57: -5 | AC57: -14 | AD57: -5 | AE57: -5 | AF57: -17 | AG57: -14 | AH57: -11 | AI57: 0 | AJ57: -8 | AK57: =SUM(AB57:AJ57) -> -79 | AL57: =+AK57/AK$13 -> -0.00015437376 | AN57: -8 | AO57: -11 | AP57: -5 | AQ57: -8 | AR57: -17 | AS57: -14 | AT57: -11 | AU57: 0 | AV57: -5 | AW57: =SUM(AN57:AV57) -> -79 | AX57: =+AW57/AW$13 -> -0.00014876917 | AZ57: -10 | BA57: -11 | BB57: -5 | BC57: -8 | BD57: -25 | BE57: -16 | BF57: -11 | BG57: 0 | BH57: -8 | BI57: =SUM(AZ57:BH57) -> -94 | BJ57: =+BI57/BI$13 -> -0.00018953753 | BL57: 0 | BM57: 0 | BN57: 0 | BO57: 0 | BP57: 0 | BQ57: 0 | BR57: 0 | BS57: 0 | BT57: 0 | BU57: =SUM(BL57:BT57) -> 0 | BV57: =+BU57/BU$13 -> 0 | BX57: 0 | BY57: 0 | BZ57: 0 | CA57: 0 | CB57: 0 | CC57: 0 | CD57: 0 | CE57: 0 | CF57: 0 | CG57: =SUM(BX57:CF57) -> 0 | CH57: =+CG57/CG$13 -> 0 | CJ57: =+CG57-BU57 -> 0 | CK57: =IFERROR(+CJ57/BU57,0%) -> 0 | CM57: =-DATOS!D135 -> -354 | CN57: =+CM57/CM$13 -> -0.0001163683 | CP57: =-DATOS!F135 -> -99.5 | CQ57: =+CP57/CP$13 -> -0.00019313019 | CS57: =-DATOS!G135 -> -552 | CT57: =+CS57/CS$13 -> -0.0001878233 | CV57: =+CM57-CS57 -> 198 | CW57: =+IFERROR(CV57/CS57,0) -> -0.35869565
A58: 52059501 | B58: Otros Gastos De Personal | D58: 0 | E58: 0 | F58: 0 | G58: 0 | H58: 0 | I58: 0 | J58: 0 | K58: 0 | L58: 0 | M58: =SUM(D58:L58) -> 0 | N58: =+M58/M$13 -> 0 | P58: 0 | Q58: 0 | R58: 0 | S58: 0 | T58: 0 | U58: 0 | V58: 0 | W58: 0 | X58: 0 | Y58: =SUM(P58:X58) -> 0 | Z58: =+Y58/Y$13 -> 0 | AB58: 0 | AC58: 0 | AD58: 0 | AE58: 0 | AF58: 0 | AG58: 0 | AH58: 0 | AI58: 0 | AJ58: 0 | AK58: =SUM(AB58:AJ58) -> 0 | AL58: =+AK58/AK$13 -> 0 | AN58: 0 | AO58: 0 | AP58: 0 | AQ58: 0 | AR58: 0 | AS58: 0 | AT58: 0 | AU58: 0 | AV58: 0 | AW58: =SUM(AN58:AV58) -> 0 | AX58: =+AW58/AW$13 -> 0 | AZ58: 0 | BA58: 0 | BB58: 0 | BC58: 0 | BD58: 0 | BE58: 0 | BF58: 0 | BG58: 0 | BH58: 0 | BI58: =SUM(AZ58:BH58) -> 0 | BJ58: =+BI58/BI$13 -> 0 | BL58: 0 | BM58: 0 | BN58: 0 | BO58: 0 | BP58: 0 | BQ58: 0 | BR58: 0 | BS58: 0 | BT58: 0 | BU58: =SUM(BL58:BT58) -> 0 | BV58: =+BU58/BU$13 -> 0 | BX58: 0 | BY58: 0 | BZ58: 0 | CA58: 0 | CB58: 0 | CC58: 0 | CD58: 0 | CE58: 0 | CF58: 0 | CG58: =SUM(BX58:CF58) -> 0 | CH58: =+CG58/CG$13 -> 0 | CJ58: =+CG58-BU58 -> 0 | CK58: =IFERROR(+CJ58/BU58,0%) -> 0 | CM58: 0 | CN58: =+CM58/CM$13 -> 0 | CP58: 0 | CQ58: =+CP58/CP$13 -> 0 | CS58: 0 | CT58: =+CS58/CS$13 -> 0 | CV58: =+CM58-CS58 -> 0 | CW58: =+IFERROR(CV58/CS58,0) -> 0
A59: 52059505 | B59: Apoyo Economino Practicante | D59: 0 | E59: 0 | F59: 0 | G59: 0 | H59: 0 | I59: 0 | J59: 0 | K59: 0 | L59: 0 | M59: =SUM(D59:L59) -> 0 | N59: =+M59/M$13 -> 0 | P59: 0 | Q59: 0 | R59: 0 | S59: 0 | T59: 0 | U59: 0 | V59: 0 | W59: 0 | X59: 0 | Y59: =SUM(P59:X59) -> 0 | Z59: =+Y59/Y$13 -> 0 | AB59: 0 | AC59: 0 | AD59: 0 | AE59: 0 | AF59: -875 | AG59: 0 | AH59: 0 | AI59: 0 | AJ59: 0 | AK59: =SUM(AB59:AJ59) -> -875 | AL59: =+AK59/AK$13 -> -0.001709836 | AN59: 0 | AO59: 0 | AP59: 0 | AQ59: 0 | AR59: -1459 | AS59: 0 | AT59: 0 | AU59: 0 | AV59: 0 | AW59: =SUM(AN59:AV59) -> -1459 | AX59: =+AW59/AW$13 -> -0.0027475218 | AZ59: 0 | BA59: 0 | BB59: 0 | BC59: 0 | BD59: -1751 | BE59: 0 | BF59: 0 | BG59: 0 | BH59: 0 | BI59: =SUM(AZ59:BH59) -> -1751 | BJ59: =+BI59/BI$13 -> -0.0035306406 | BL59: 0 | BM59: 0 | BN59: 0 | BO59: 0 | BP59: -1751 | BQ59: 0 | BR59: 0 | BS59: 0 | BT59: 0 | BU59: =SUM(BL59:BT59) -> -1751 | BV59: =+BU59/BU$13 -> -0.0035226143 | BX59: 0 | BY59: 0 | BZ59: 0 | CA59: 0 | CB59: -1634 | CC59: 0 | CD59: 0 | CE59: 0 | CF59: 0 | CG59: =SUM(BX59:CF59) -> -1634 | CH59: =+CG59/CG$13 -> -0.0034042518 | CJ59: =+CG59-BU59 -> 117 | CK59: =IFERROR(+CJ59/BU59,0%) -> -0.066818961 | CM59: 0 | CN59: =+CM59/CM$13 -> 0 | CP59: 0 | CQ59: =+CP59/CP$13 -> 0 | CS59: 0 | CT59: =+CS59/CS$13 -> 0 | CV59: =+CM59-CS59 -> 0 | CW59: =+IFERROR(CV59/CS59,0) -> 0
A60: 52059506 | B60: Monetizacion SENA | D60: 0 | E60: 0 | F60: 0 | G60: 0 | H60: -2135 | I60: 0 | J60: 0 | K60: 0 | L60: 0 | M60: =SUM(D60:L60) -> -2135 | N60: =+M60/M$13 -> -0.0042296575 | P60: 0 | Q60: -2135 | R60: 0 | S60: 0 | T60: 0 | U60: 0 | V60: 0 | W60: 0 | X60: 0 | Y60: =SUM(P60:X60) -> -2135 | Z60: =+Y60/Y$13 -> -0.0040567604 | AB60: -2626 | AC60: 0 | AD60: 0 | AE60: 0 | AF60: 0 | AG60: 0 | AH60: 0 | AI60: 0 | AJ60: 0 | AK60: =SUM(AB60:AJ60) -> -2626 | AL60: =+AK60/AK$13 -> -0.005131462 | AN60: -1313 | AO60: 0 | AP60: 0 | AQ60: 0 | AR60: 0 | AS60: 0 | AT60: 0 | AU60: 0 | AV60: 0 | AW60: =SUM(AN60:AV60) -> -1313 | AX60: =+AW60/AW$13 -> -0.0024725813 | AZ60: 0 | BA60: 0 | BB60: 0 | BC60: 0 | BD60: 0 | BE60: 0 | BF60: 0 | BG60: 0 | BH60: 0 | BI60: =SUM(AZ60:BH60) -> 0 | BJ60: =+BI60/BI$13 -> 0 | BL60: 0 | BM60: 0 | BN60: 0 | BO60: 0 | BP60: 0 | BQ60: 0 | BR60: 0 | BS60: 0 | BT60: 0 | BU60: =SUM(BL60:BT60) -> 0 | BV60: =+BU60/BU$13 -> 0 | BX60: 0 | BY60: 0 | BZ60: 0 | CA60: 0 | CB60: 0 | CC60: 0 | CD60: 0 | CE60: 0 | CF60: 0 | CG60: =SUM(BX60:CF60) -> 0 | CH60: =+CG60/CG$13 -> 0 | CJ60: =+CG60-BU60 -> 0 | CK60: =IFERROR(+CJ60/BU60,0%) -> 0 | CM60: =-DATOS!D136 -> -13546 | CN60: =+CM60/CM$13 -> -0.0044528956 | CP60: =-DATOS!F136 -> -1922 | CQ60: =+CP60/CP$13 -> -0.0037306154 | CS60: =-DATOS!G136 -> -1922 | CT60: =+CS60/CS$13 -> -0.00065397895
A61: 5210 | B61: Honorarios | D61: -800 | E61: -800 | F61: -800 | G61: -800 | H61: -10080 | I61: -960 | J61: -800 | K61: -800 | L61: -885 | M61: =SUM(D61:L61) -> -16725 | N61: =+M61/M$13 -> -0.033133968 | P61: -800 | Q61: -800 | R61: -800 | S61: -800 | T61: -9280 | U61: -800 | V61: -800 | W61: 0 | X61: -800 | Y61: =SUM(P61:X61) -> -14880 | Z61: =+Y61/Y$13 -> -0.028273815 | AB61: -982 | AC61: -982 | AD61: -982 | AE61: -982 | AF61: -10262 | AG61: -982 | AH61: -982 | AI61: 0 | AJ61: -982 | AK61: =SUM(AB61:AJ61) -> -17136 | AL61: =+AK61/AK$13 -> -0.033485427 | AN61: -982 | AO61: -982 | AP61: -982 | AQ61: -982 | AR61: -10262 | AS61: -982 | AT61: -982 | AU61: 0 | AV61: -982 | AW61: =SUM(AN61:AV61) -> -17136 | AX61: =+AW61/AW$13 -> -0.032269728 | AZ61: -982 | BA61: -982 | BB61: -982 | BC61: -982 | BD61: -13862 | BE61: -982 | BF61: -982 | BG61: 0 | BH61: -982 | BI61: =SUM(AZ61:BH61) -> -20736 | BJ61: =+BI61/BI$13 -> -0.041811172 | BL61: -1300 | BM61: -1261 | BN61: -1222 | BO61: -1300 | BP61: -10697 | BQ61: -1339 | BR61: -1261 | BS61: 0 | BT61: -1261 | BU61: =SUM(BL61:BT61) -> -19641 | BV61: =+BU61/BU$13 -> -0.039513231 | BX61: -2152 | BY61: -2074 | BZ61: -2074 | CA61: -2113 | CB61: -11431 | CC61: -2191 | CD61: -2074 | CE61: -800 | CF61: -2113 | CG61: =SUM(BX61:CF61) -> -27022 | CH61: =+CG61/CG$13 -> -0.056297241 | CJ61: =+CG61-BU61 -> -7381 | CK61: =IFERROR(+CJ61/BU61,0%) -> 0.37579553 | CM61: =-DATOS!D138-DATOS!D140-DATOS!D141 -> -119492 | CN61: =+CM61/CM$13 -> -0.039279891 | CP61: =-DATOS!F141-DATOS!F139-DATOS!F138-DATOS!F137 -> -25797 | CQ61: =+CP61/CP$13 -> -0.050072157 | CS61: =-DATOS!G139-DATOS!G140-DATOS!G141 -> -14080.5 | CT61: =+CS61/CS$13 -> -0.0047910253 | CV61: =+CM61-CS61 -> -105411.5 | CW61: =+IFERROR(CV61/CS61,0) -> 7.4863464
A62: 52109502 | B62: Juliana Girald Sst//Servicomple | D62: -339 | E62: -376 | F62: -302 | G62: -413 | H62: -598 | I62: -450 | J62: -376 | K62: -79 | L62: -260 | M62: =SUM(D62:L62) -> -3193 | N62: =+M62/M$13 -> -0.0063256658 | P62: -81 | Q62: -81 | R62: -81 | S62: -81 | T62: -81 | U62: -81 | V62: -81 | W62: 0 | X62: -81 | Y62: =SUM(P62:X62) -> -648 | Z62: =+Y62/Y$13 -> -0.001231279 | AB62: -348 | AC62: -309 | AD62: -270 | AE62: -348 | AF62: -465 | AG62: -309 | AH62: -270 | AI62: 0 | AJ62: -270 | AK62: =SUM(AB62:AJ62) -> -2589 | AL62: =+AK62/AK$13 -> -0.0050591603 | AN62: -299 | AO62: -260 | AP62: -182 | AQ62: -260 | AR62: -377 | AS62: -299 | AT62: -221 | AU62: 0 | AV62: -260 | AW62: =SUM(AN62:AV62) -> -2158 | AX62: =+AW62/AW$13 -> -0.0040638465 | AZ62: -260 | BA62: -221 | BB62: -182 | BC62: -260 | BD62: -377 | BE62: -299 | BF62: -260 | BG62: 0 | BH62: -221 | BI62: =SUM(AZ62:BH62) -> -2080 | BJ62: =+BI62/BI$13 -> -0.0041940219 | BL62: -92 | BM62: -92 | BN62: -92 | BO62: -92 | BP62: -92 | BQ62: -92 | BR62: -92 | BS62: 0 | BT62: -92 | BU62: =SUM(BL62:BT62) -> -736 | BV62: =+BU62/BU$13 -> -0.0014806649 | BX62: -92 | BY62: -92 | BZ62: -92 | CA62: -92 | CB62: -92 | CC62: -92 | CD62: -92 | CE62: 0 | CF62: -92 | CG62: =SUM(BX62:CF62) -> -736 | CH62: =+CG62/CG$13 -> -0.0015333717 | CJ62: =+CG62-BU62 -> 0 | CK62: =IFERROR(+CJ62/BU62,0%) -> 0 | CM62: =-DATOS!D139 -> 0 | CN62: =+CM62/CM$13 -> 0 | CP62: =-DATOS!F140 -> -2227.5 | CQ62: =+CP62/CP$13 -> -0.004323593 | CS62: =-DATOS!G138 -> -106949 | CT62: =+CS62/CS$13 -> -0.036390424 | CV62: =+CM62-CS62 -> 106949 | CW62: =+IFERROR(CV62/CS62,0) -> -1
A63: 5215 | B63: Impuestos | D63: -872 | E63: -707 | F63: -505 | G63: -1389 | H63: -1408 | I63: -959 | J63: -791 | K63: -196 | L63: -541 | M63: =SUM(D63:L63) -> -7368 | N63: =+M63/M$13 -> -0.014596776 | P63: -828 | Q63: -665 | R63: -441 | S63: -1225 | T63: -1384 | U63: -887 | V63: -718 | W63: 0 | X63: -499 | Y63: =SUM(P63:X63) -> -6647 | Z63: =+Y63/Y$13 -> -0.012630111 | AB63: -742 | AC63: -692 | AD63: -472 | AE63: -1215 | AF63: -1234 | AG63: -997 | AH63: -801 | AI63: -86 | AJ63: -429 | AK63: =SUM(AB63:AJ63) -> -6668 | AL63: =+AK63/AK$13 -> -0.013029927 | AN63: -802 | AO63: -737 | AP63: -483 | AQ63: -1214 | AR63: -1698 | AS63: -989 | AT63: -783 | AU63: -112 | AV63: -851 | AW63: =SUM(AN63:AV63) -> -7669 | AX63: =+AW63/AW$13 -> -0.014441908 | AZ63: -680 | BA63: -712 | BB63: -455 | BC63: -1228 | BD63: -1250 | BE63: -934 | BF63: -725 | BG63: -1933 | BH63: -423 | BI63: =SUM(AZ63:BH63) -> -8340 | BJ63: =+BI63/BI$13 -> -0.016816415 | BL63: -653 | BM63: -689 | BN63: -426 | BO63: -1213 | BP63: -1232 | BQ63: -936 | BR63: -745 | BS63: 0 | BT63: -456 | BU63: =SUM(BL63:BT63) -> -6350 | BV63: =+BU63/BU$13 -> -0.012774758 | BX63: -625 | BY63: -801 | BZ63: -515 | CA63: -1543 | CB63: 3750 | CC63: -1078 | CD63: -804 | CE63: -1933 | CF63: -3194 | CG63: =SUM(BX63:CF63) -> -6743 | CH63: =+CG63/CG$13 -> -0.014048268 | CJ63: =+CG63-BU63 -> -393 | CK63: =IFERROR(+CJ63/BU63,0%) -> 0.061889764 | CM63: =-DATOS!D142-DATOS!D143-DATOS!D144-DATOS!D145 -> -42415 | CN63: =+CM63/CM$13 -> -0.013942829 | CP63: =-DATOS!F142-DATOS!F143-DATOS!F144 -> -7525 | CQ63: =+CP63/CP$13 -> -0.014606077 | CS63: =-DATOS!G142-DATOS!G143-DATOS!G144-DATOS!G145 -> -51563 | CT63: =+CS63/CS$13 -> -0.017544806 | CV63: =+CM63-CS63 -> 9148 | CW63: =+IFERROR(CV63/CS63,0) -> -0.17741404
A64: 5220 | B64: Arrendamientos | D64: -18883 | E64: -5 | F64: -3587 | G64: -13177 | H64: -5791 | I64: -10987 | J64: -8601 | K64: -5589 | L64: -7502 | M64: =SUM(D64:L64) -> -74122 | N64: =+M64/M$13 -> -0.14684341 | P64: -10447 | Q64: -9040 | R64: -3842 | S64: -13177 | T64: -21335 | U64: -10987 | V64: -8601 | W64: 0 | X64: -7502 | Y64: =SUM(P64:X64) -> -84931 | Z64: =+Y64/Y$13 -> -0.16137926 | AB64: -10447 | AC64: -9040 | AD64: -3842 | AE64: -13177 | AF64: -22121 | AG64: -10987 | AH64: -8601 | AI64: 0 | AJ64: -7502 | AK64: =SUM(AB64:AJ64) -> -85717 | AL64: =+AK64/AK$13 -> -0.16749944 | AN64: -10447 | AO64: -9040 | AP64: -3842 | AQ64: -13177 | AR64: -14323 | AS64: -10987 | AT64: -8601 | AU64: -1672 | AV64: -7502 | AW64: =SUM(AN64:AV64) -> -79591 | AX64: =+AW64/AW$13 -> -0.14988211 | AZ64: -10522 | BA64: -9040 | BB64: -4286 | BC64: -13177 | BD64: -20268 | BE64: -10987 | BF64: -8601 | BG64: -1636 | BH64: -7502 | BI64: =SUM(AZ64:BH64) -> -86019 | BJ64: =+BI64/BI$13 -> -0.17344499 | BL64: -10522 | BM64: -9040 | BN64: -3842 | BO64: -13177 | BP64: -21273 | BQ64: -10987 | BR64: -8601 | BS64: -3316 | BT64: -7502 | BU64: =SUM(BL64:BT64) -> -88260 | BV64: =+BU64/BU$13 -> -0.17755908 | BX64: -10881 | BY64: -9040 | BZ64: -3842 | CA64: -15119 | CB64: -18655 | CC64: -10987 | CD64: -9383 | CE64: 0 | CF64: -7502 | CG64: =SUM(BX64:CF64) -> -85409 | CH64: =+CG64/CG$13 -> -0.17793987 | CJ64: =+CG64-BU64 -> 2851 | CK64: =IFERROR(+CJ64/BU64,0%) -> -0.032302289 | CM64: =-DATOS!D146 -> -509925 | CN64: =+CM64/CM$13 -> -0.1676246 | CP64: =-DATOS!F146 -> -65084 | CQ64: =+CP64/CP$13 -> -0.1263285 | CS64: =-DATOS!G146 -> -394049 | CT64: =+CS64/CS$13 -> -0.13407896 | CV64: =+CM64-CS64 -> -115876 | CW64: =+IFERROR(CV64/CS64,0) -> 0.29406495
A65: 5225 | B65: Contribuciones y afiliaciones | D65: -545 | E65: 0 | F65: -422 | G65: -1973 | H65: -2012 | I65: -507 | J65: 0 | K65: 0 | L65: 0 | M65: =SUM(D65:L65) -> -5459 | N65: =+M65/M$13 -> -0.010814848 | P65: 0 | Q65: -573 | R65: -444 | S65: -2073 | T65: -4136 | U65: -533 | V65: 0 | W65: -276 | X65: 0 | Y65: =SUM(P65:X65) -> -8035 | Z65: =+Y65/Y$13 -> -0.01526748 | AB65: 0 | AC65: -573 | AD65: -444 | AE65: -2073 | AF65: -2114 | AG65: -533 | AH65: 0 | AI65: -2020 | AJ65: 0 | AK65: =SUM(AB65:AJ65) -> -7757 | AL65: =+AK65/AK$13 -> -0.01515794 | AN65: 0 | AO65: -684 | AP65: -510 | AQ65: -2073 | AR65: -2112 | AS65: -515 | AT65: 0 | AU65: -2722 | AV65: 0 | AW65: =SUM(AN65:AV65) -> -8616 | AX65: =+AW65/AW$13 -> -0.016225255 | AZ65: 0 | BA65: -684 | BB65: -28 | BC65: -2527 | BD65: -4520 | BE65: -527 | BF65: 0 | BG65: -868 | BH65: 0 | BI65: =SUM(AZ65:BH65) -> -9154 | BJ65: =+BI65/BI$13 -> -0.018457729 | BL65: 0 | BM65: -684 | BN65: -460 | BO65: -2187 | BP65: -2188 | BQ65: -527 | BR65: 0 | BS65: -3179 | BT65: 0 | BU65: =SUM(BL65:BT65) -> -9225 | BV65: =+BU65/BU$13 -> -0.018558605 | BX65: 0 | BY65: -640 | BZ65: -466 | CA65: -2187 | CB65: -2182 | CC65: -527 | CD65: 0 | CE65: -3179 | CF65: 0 | CG65: =SUM(BX65:CF65) -> -9181 | CH65: =+CG65/CG$13 -> -0.019127562 | CJ65: =+CG65-BU65 -> 44 | CK65: =IFERROR(+CJ65/BU65,0%) -> -0.0047696477 | CM65: =-DATOS!D147 -> -51970 | CN65: =+CM65/CM$13 -> -0.017083787 | CP65: =-DATOS!F147 -> -12012 | CQ65: =+CP65/CP$13 -> -0.023315376 | CS65: =-DATOS!G147 -> -73967 | CT65: =+CS65/CS$13 -> -0.025167982 | CV65: =+CM65-CS65 -> 21997 | CW65: =+IFERROR(CV65/CS65,0) -> -0.29738938
A66: 5230 | B66: Seguros | D66: 0 | E66: 0 | F66: 0 | G66: 0 | H66: 0 | I66: 0 | J66: 0 | K66: 0 | L66: 0 | M66: =SUM(D66:L66) -> 0 | N66: =+M66/M$13 -> 0 | P66: 0 | Q66: 0 | R66: 0 | S66: 0 | T66: 0 | U66: 0 | V66: 0 | W66: 0 | X66: 0 | Y66: =SUM(P66:X66) -> 0 | Z66: =+Y66/Y$13 -> 0 | AB66: -53 | AC66: -56 | AD66: -42 | AE66: -65 | AF66: -348 | AG66: -58 | AH66: -55 | AI66: 0 | AJ66: -76 | AK66: =SUM(AB66:AJ66) -> -753 | AL66: =+AK66/AK$13 -> -0.001471436 | AN66: 0 | AO66: 0 | AP66: 0 | AQ66: 0 | AR66: 0 | AS66: 0 | AT66: 0 | AU66: 0 | AV66: 0 | AW66: =SUM(AN66:AV66) -> 0 | AX66: =+AW66/AW$13 -> 0 | AZ66: -287 | BA66: 0 | BB66: 0 | BC66: 0 | BD66: 0 | BE66: 0 | BF66: 0 | BG66: 0 | BH66: -1137 | BI66: =SUM(AZ66:BH66) -> -1424 | BJ66: =+BI66/BI$13 -> -0.0028712919 | BL66: 0 | BM66: 0 | BN66: 0 | BO66: 0 | BP66: 0 | BQ66: 0 | BR66: 0 | BS66: 0 | BT66: 0 | BU66: =SUM(BL66:BT66) -> 0 | BV66: =+BU66/BU$13 -> 0 | BX66: 0 | BY66: 0 | BZ66: 0 | CA66: 0 | CB66: 0 | CC66: 0 | CD66: 0 | CE66: 0 | CF66: 0 | CG66: =SUM(BX66:CF66) -> 0 | CH66: =+CG66/CG$13 -> 0 | CJ66: =+CG66-BU66 -> 0 | CK66: =IFERROR(+CJ66/BU66,0%) -> 0 | CM66: =-DATOS!D148 -> -2176 | CN66: =+CM66/CM$13 -> -0.00071530347 | CP66: =-DATOS!F148 -> 0 | CQ66: =+CP66/CP$13 -> 0 | CS66: =-DATOS!G148 -> -10730 | CT66: =+CS66/CS$13 -> -0.0036509855 | CV66: =+CM66-CS66 -> 8554 | CW66: =+IFERROR(CV66/CS66,0) -> -0.7972041
A67: 5235 | B67: Servicios | D67: =+SUM(D68:D85) -> -2110 | E67: =+SUM(E68:E85) -> -4265 | F67: =+SUM(F68:F85) -> -3236 | G67: =+SUM(G68:G85) -> -5189 | H67: =+SUM(H68:H85) -> -9231 | I67: =+SUM(I68:I85) -> -3927 | J67: =+SUM(J68:J85) -> -4717 | K67: =+SUM(K68:K85) -> -3196 | ... M67: =+SUM(M68:M85) -> -40645 | N67: =+M67/M$13 -> -0.080521981 | P67: =+SUM(P68:P85) -> -2512 | Q67: =+SUM(Q68:Q85) -> -4420 | R67: =+SUM(R68:R85) -> -2758 | S67: =+SUM(S68:S85) -> -4561 | T67: =+SUM(T68:T85) -> -8657 | U67: =+SUM(U68:U85) -> -3643 | V67: =+SUM(V68:V85) -> -3897 | W67: =+SUM(W68:W85) -> 0 | ... Y67: =+SUM(Y68:Y85) -> -34484 | Z67: =+Y67/Y$13 -> -0.065523807 | AB67: =+SUM(AB68:AB85) -> -1909 | AC67: =+SUM(AC68:AC85) -> -3575 | AD67: =+SUM(AD68:AD85) -> -4531 | AE67: =+SUM(AE68:AE85) -> -4715 | AF67: =+SUM(AF68:AF85) -> -13212 | AG67: =+SUM(AG68:AG85) -> -3642 | AH67: =+SUM(AH68:AH85) -> -3951 | AI67: =+SUM(AI68:AI85) -> -2390 | ... AK67: =+SUM(AK68:AK85) -> -41401 | AL67: =+AK67/AK$13 -> -0.080901621 | AN67: =+SUM(AN68:AN85) -> -2166 | AO67: =+SUM(AO68:AO85) -> -3839 | AP67: =+SUM(AP68:AP85) -> -3266 | AQ67: =+SUM(AQ68:AQ85) -> -6073 | AR67: =+SUM(AR68:AR85) -> -12567 | AS67: =+SUM(AS68:AS85) -> -4098 | AT67: =+SUM(AT68:AT85) -> -4414 | AU67: =+SUM(AU68:AU85) -> 0 | ... AW67: =+SUM(AW68:AW85) -> -40750 | AX67: =+AW67/AW$13 -> -0.076738528 | AZ67: =+SUM(AZ68:AZ85) -> -1919 | BA67: =+SUM(BA68:BA85) -> -3650 | BB67: =+SUM(BB68:BB85) -> -2858 | BC67: =+SUM(BC68:BC85) -> -8500 | BD67: =+SUM(BD68:BD85) -> -14495 | BE67: =+SUM(BE68:BE85) -> -3776 | BF67: =+SUM(BF68:BF85) -> -4812 | BG67: =+SUM(BG68:BG85) -> 0 | ... BI67: =+SUM(BI68:BI85) -> -43453 | BJ67: =+BI67/BI$13 -> -0.087616747 | BL67: =+SUM(BL68:BL85) -> -2755 | BM67: =+SUM(BM68:BM85) -> -4444 | BN67: =+SUM(BN68:BN85) -> -3059 | BO67: =+SUM(BO68:BO85) -> -8960 | BP67: =+SUM(BP68:BP85) -> -34831 | BQ67: =+SUM(BQ68:BQ85) -> -3855 | BR67: =+SUM(BR68:BR85) -> -4099 | BS67: =+SUM(BS68:BS85) -> -20108 | ... BU67: =+SUM(BU68:BU85) -> -85587 | BV67: =+BU67/BU$13 -> -0.17218161 | BX67: =+SUM(BX68:BX85) -> -2731 | BY67: =+SUM(BY68:BY85) -> -3939 | BZ67: =+SUM(BZ68:BZ85) -> -2834 | CA67: =+SUM(CA68:CA85) -> -7144 | CB67: =+SUM(CB68:CB85) -> -8928 | CC67: =+SUM(CC68:CC85) -> -3787 | CD67: =+SUM(CD68:CD85) -> -4104 | CE67: =+SUM(CE68:CE85) -> 0 | ... CG67: =+SUM(CG68:CG85) -> -36671 | CH67: =+CG67/CG$13 -> -0.076399827 | CJ67: =+CG67-BU67 -> 48916 | CK67: =IFERROR(+CJ67/BU67,0%) -> -0.5715354 | CM67: =+SUM(CM68:CM85) -> -282241.5 | CN67: =+CM67/CM$13 -> -0.09277956 | CP67: =+SUM(CP68:CP85) -> -63050.5 | CQ67: =+CP67/CP$13 -> -0.12238146 | CS67: =+SUM(CS68:CS85) -> -285521 | CT67: =+CS67/CS$13 -> -0.097151262 | CV67: =+CM67-CS67 -> 3279.5 | CW67: =+IFERROR(CV67/CS67,0) -> -0.01148602
A68: 52350501 | B68: Aseo Y Vigilancia | D68: -54 | E68: -81 | F68: -62 | G68: -72 | H68: -418 | I68: -51 | J68: -81 | K68: -86 | L68: 0 | M68: =SUM(D68:L68) -> -905 | N68: =+M68/M$13 -> -0.0017928993 | P68: -59 | Q68: -81 | R68: -66 | S68: -72 | T68: -400 | U68: -50 | V68: -81 | W68: 0 | X68: 0 | Y68: =SUM(P68:X68) -> -809 | Z68: =+Y68/Y$13 -> -0.0015371987 | AB68: -42 | AC68: -81 | AD68: -63 | AE68: -72 | AF68: -400 | AG68: -51 | AH68: -81 | AI68: -173 | AJ68: 0 | AK68: =SUM(AB68:AJ68) -> -963 | AL68: =+AK68/AK$13 -> -0.0018817966 | AN68: -60 | AO68: -89 | AP68: -70 | AQ68: -83 | AR68: -434 | AS68: -56 | AT68: -89 | AU68: 0 | AV68: 0 | AW68: =SUM(AN68:AV68) -> -881 | AX68: =+AW68/AW$13 -> -0.0016590587 | AZ68: -71 | BA68: -90 | BB68: -74 | BC68: -83 | BD68: -434 | BE68: -57 | BF68: -90 | BG68: 0 | BH68: 0 | BI68: =SUM(AZ68:BH68) -> -899 | BJ68: =+BI68/BI$13 -> -0.0018127047 | BL68: -63 | BM68: -90 | BN68: -72 | BO68: -84 | BP68: -345 | BQ68: -57 | BR68: -91 | BS68: 0 | BT68: 0 | BU68: =SUM(BL68:BT68) -> -802 | BV68: =+BU68/BU$13 -> -0.0016134419 | BX68: -65 | BY68: -92 | BZ68: -71 | CA68: -89 | CB68: -439 | CC68: -58 | CD68: -92 | CE68: 0 | CF68: 0 | CG68: =SUM(BX68:CF68) -> -906 | CH68: =+CG68/CG$13 -> -0.0018875472 | CJ68: =+CG68-BU68 -> -104 | CK68: =IFERROR(+CJ68/BU68,0%) -> 0.12967581 | CM68: =-DATOS!D150 -> -5256.5 | CN68: =+CM68/CM$13 -> -0.0017279378 | CP68: =-DATOS!F150 -> -571.5 | CQ68: =+CP68/CP$13 -> -0.0011092855 | CS68: =-DATOS!G150 -> -4638 | CT68: =+CS68/CS$13 -> -0.001578124 | CV68: =+CM68-CS68 -> -618.5 | CW68: =+IFERROR(CV68/CS68,0) -> 0.13335489
A69: 52351001 | B69: Temporales | D69: 0 | E69: 0 | F69: 0 | G69: 0 | H69: 30 | I69: 0 | J69: 0 | K69: 0 | L69: 0 | M69: =SUM(D69:L69) -> 30 | N69: =+M69/M$13 -> 5.9433127e-05 | P69: 0 | Q69: 0 | R69: 0 | S69: 0 | T69: 0 | U69: 0 | V69: 0 | W69: 0 | X69: 0 | Y69: =SUM(P69:X69) -> 0 | Z69: =+Y69/Y$13 -> 0 | AB69: 0 | AC69: 0 | AD69: 0 | AE69: 0 | AF69: 0 | AG69: 0 | AH69: 0 | AI69: 0 | AJ69: 0 | AK69: =SUM(AB69:AJ69) -> 0 | AL69: =+AK69/AK$13 -> 0 | AN69: 0 | AO69: 0 | AP69: 0 | AQ69: 0 | AR69: 0 | AS69: 0 | AT69: 0 | AU69: 0 | AV69: 0 | AW69: =SUM(AN69:AV69) -> 0 | AX69: =+AW69/AW$13 -> 0 | AZ69: 0 | BA69: 0 | BB69: 0 | BC69: 0 | BD69: 0 | BE69: 0 | BF69: 0 | BG69: 0 | BH69: 0 | BI69: =SUM(AZ69:BH69) -> 0 | BJ69: =+BI69/BI$13 -> 0 | BL69: 0 | BM69: 0 | BN69: 0 | BO69: 0 | BP69: 0 | BQ69: 0 | BR69: 0 | BS69: 0 | BT69: 0 | BU69: =SUM(BL69:BT69) -> 0 | BV69: =+BU69/BU$13 -> 0 | BX69: 0 | BY69: 0 | BZ69: 0 | CA69: 0 | CB69: 0 | CC69: 0 | CD69: 0 | CE69: 0 | CF69: 0 | CG69: =SUM(BX69:CF69) -> 0 | CH69: =+CG69/CG$13 -> 0 | CJ69: =+CG69-BU69 -> 0 | CK69: =IFERROR(+CJ69/BU69,0%) -> 0 | CM69: =-DATOS!D151 -> 0 | CN69: =+CM69/CM$13 -> 0 | CP69: =-DATOS!F151 -> -10892 | CQ69: =+CP69/CP$13 -> -0.021141448 | CS69: =-DATOS!G151 -> -26366 | CT69: =+CS69/CS$13 -> -0.0089712846 | CV69: =+CM69-CS69 -> 26366 | CW69: =+IFERROR(CV69/CS69,0) -> -1
A70: 52351002 | B70: Administracion Nomina | D70: 0 | E70: 0 | F70: 0 | G70: 0 | H70: 0 | I70: 0 | J70: 0 | K70: 0 | L70: 0 | M70: =SUM(D70:L70) -> 0 | N70: =+M70/M$13 -> 0 | P70: 0 | Q70: 0 | R70: 0 | S70: 0 | T70: 0 | U70: 0 | V70: 0 | W70: 0 | X70: 0 | Y70: =SUM(P70:X70) -> 0 | Z70: =+Y70/Y$13 -> 0 | AB70: 0 | AC70: 0 | AD70: 0 | AE70: 0 | AF70: 0 | AG70: 0 | AH70: 0 | AI70: 0 | AJ70: 0 | AK70: =SUM(AB70:AJ70) -> 0 | AL70: =+AK70/AK$13 -> 0 | AN70: 0 | AO70: 0 | AP70: 0 | AQ70: 0 | AR70: 0 | AS70: 0 | AT70: 0 | AU70: 0 | AV70: 0 | AW70: =SUM(AN70:AV70) -> 0 | AX70: =+AW70/AW$13 -> 0 | AZ70: 0 | BA70: 0 | BB70: 0 | BC70: 0 | BD70: 0 | BE70: 0 | BF70: 0 | BG70: 0 | BH70: 0 | BI70: =SUM(AZ70:BH70) -> 0 | BJ70: =+BI70/BI$13 -> 0 | BL70: 0 | BM70: 0 | BN70: 0 | BO70: 0 | BP70: 0 | BQ70: 0 | BR70: 0 | BS70: 0 | BT70: 0 | BU70: =SUM(BL70:BT70) -> 0 | BV70: =+BU70/BU$13 -> 0 | BX70: 0 | BY70: 0 | BZ70: 0 | CA70: 0 | CB70: 0 | CC70: 0 | CD70: 0 | CE70: 0 | CF70: 0 | CG70: =SUM(BX70:CF70) -> 0 | CH70: =+CG70/CG$13 -> 0 | CJ70: =+CG70-BU70 -> 0 | CK70: =IFERROR(+CJ70/BU70,0%) -> 0 | CM70: =-DATOS!D152 -> 0 | CN70: =+CM70/CM$13 -> 0 | CP70: =-DATOS!F152 -> -871 | CQ70: =+CP70/CP$13 -> -0.0016906171 | CS70: =-DATOS!G152 -> -1903 | CT70: =+CS70/CS$13 -> -0.00064751402 | CV70: =+CM70-CS70 -> 1903 | CW70: =+IFERROR(CV70/CS70,0) -> -1
A71: 52351502 | B71: Examenes Microbiologicos | D71: 0 | E71: 0 | F71: 0 | G71: 0 | H71: 0 | I71: 0 | J71: 0 | K71: 0 | L71: 0 | M71: =SUM(D71:L71) -> 0 | N71: =+M71/M$13 -> 0 | P71: 0 | Q71: 0 | R71: 0 | S71: 0 | T71: 0 | U71: 0 | V71: 0 | W71: 0 | X71: 0 | Y71: =SUM(P71:X71) -> 0 | Z71: =+Y71/Y$13 -> 0 | AB71: 0 | AC71: 0 | AD71: 0 | AE71: 0 | AF71: 0 | AG71: -60 | AH71: 0 | AI71: 0 | AJ71: 0 | AK71: =SUM(AB71:AJ71) -> -60 | AL71: =+AK71/AK$13 -> -0.00011724589 | AN71: 0 | AO71: 0 | AP71: 0 | AQ71: 0 | AR71: 0 | AS71: 0 | AT71: 0 | AU71: 0 | AV71: 0 | AW71: =SUM(AN71:AV71) -> 0 | AX71: =+AW71/AW$13 -> 0 | AZ71: 0 | BA71: 0 | BB71: 0 | BC71: 0 | BD71: 0 | BE71: 0 | BF71: 0 | BG71: 0 | BH71: 0 | BI71: =SUM(AZ71:BH71) -> 0 | BJ71: =+BI71/BI$13 -> 0 | BL71: 0 | BM71: 0 | BN71: 0 | BO71: 0 | BP71: 0 | BQ71: 0 | BR71: 0 | BS71: 0 | BT71: 0 | BU71: =SUM(BL71:BT71) -> 0 | BV71: =+BU71/BU$13 -> 0 | BX71: 0 | BY71: 0 | BZ71: 0 | CA71: 0 | CB71: 0 | CC71: 0 | CD71: 0 | CE71: 0 | CF71: 0 | CG71: =SUM(BX71:CF71) -> 0 | CH71: =+CG71/CG$13 -> 0 | CJ71: =+CG71-BU71 -> 0 | CK71: =IFERROR(+CJ71/BU71,0%) -> 0 | CM71: =-DATOS!D153 -> -60 | CP71: =-+DATOS!F153 -> 0 | CQ71: =+CP71/CP$13 -> 0 | CS71: =+-DATOS!G153 -> 0
A72: 52352001 | B72: Procesamiento Electronico De D | D72: -336 | E72: -336 | F72: -436 | G72: -436 | H72: -436 | I72: -336 | J72: -336 | K72: -336 | L72: -436 | M72: =SUM(D72:L72) -> -3424 | N72: =+M72/M$13 -> -0.0067833009 | P72: -395 | Q72: -395 | R72: -495 | S72: -495 | T72: -495 | U72: -395 | V72: -395 | W72: 0 | X72: -495 | Y72: =SUM(P72:X72) -> -3560 | Z72: =+Y72/Y$13 -> -0.0067644343 | AB72: -396 | AC72: -396 | AD72: -496 | AE72: -496 | AF72: -496 | AG72: -396 | AH72: -396 | AI72: 0 | AJ72: -496 | AK72: =SUM(AB72:AJ72) -> -3568 | AL72: =+AK72/AK$13 -> -0.0069722225 | AN72: -396 | AO72: -396 | AP72: -496 | AQ72: -496 | AR72: -496 | AS72: -396 | AT72: -396 | AU72: 0 | AV72: -496 | AW72: =SUM(AN72:AV72) -> -3568 | AX72: =+AW72/AW$13 -> -0.0067190937 | AZ72: -396 | BA72: -396 | BB72: -396 | BC72: -396 | BD72: -921 | BE72: -396 | BF72: -396 | BG72: 0 | BH72: -396 | BI72: =SUM(AZ72:BH72) -> -3693 | BJ72: =+BI72/BI$13 -> -0.0074464052 | BL72: -395 | BM72: -395 | BN72: -395 | BO72: -395 | BP72: -395 | BQ72: -395 | BR72: -395 | BS72: 0 | BT72: -395 | BU72: =SUM(BL72:BT72) -> -3160 | BV72: =+BU72/BU$13 -> -0.0063572023 | BX72: -396 | BY72: -396 | BZ72: -396 | CA72: -396 | CB72: -396 | CC72: -396 | CD72: -396 | CE72: 0 | CF72: -396 | CG72: =SUM(BX72:CF72) -> -3168 | CH72: =+CG72/CG$13 -> -0.006600165 | CJ72: =+CG72-BU72 -> -8 | CK72: =IFERROR(+CJ72/BU72,0%) -> 0.0025316456 | CM72: =-DATOS!D154 -> -20719.5 | CN72: =+CM72/CM$13 -> -0.0068109973 | CP72: =-DATOS!F154 -> -4254.5 | CQ72: =+CP72/CP$13 -> -0.0082580142 | CS72: =-DATOS!G154 -> -21514 | CT72: =+CS72/CS$13 -> -0.0073203451 | CV72: =+CM72-CS72 -> 794.5 | CW72: =+IFERROR(CV72/CS72,0) -> -0.036929441
A73: 52352501 | B73: Acueducto Y Alcantarillado | D73: -168 | E73: -155 | F73: -115 | G73: -268 | H73: -418 | I73: -194 | J73: -194 | K73: -92 | L73: -118 | M73: =SUM(D73:L73) -> -1722 | N73: =+M73/M$13 -> -0.0034114615 | P73: -168 | Q73: -155 | R73: -115 | S73: -255 | T73: -303 | U73: -168 | V73: -207 | W73: 0 | X73: -79 | Y73: =SUM(P73:X73) -> -1450 | Z73: =+Y73/Y$13 -> -0.0027551769 | AB73: -168 | AC73: -155 | AD73: -128 | AE73: -322 | AF73: -316 | AG73: -115 | AH73: -155 | AI73: -76 | AJ73: -105 | AK73: =SUM(AB73:AJ73) -> -1540 | AL73: =+AK73/AK$13 -> -0.0030093113 | AN73: -155 | AO73: -220 | AP73: -155 | AQ73: -255 | AR73: -302 | AS73: -168 | AT73: -207 | AU73: 0 | AV73: -79 | AW73: =SUM(AN73:AV73) -> -1541 | AX73: =+AW73/AW$13 -> -0.0029019404 | AZ73: -168 | BA73: -233 | BB73: -155 | BC73: -255 | BD73: -289 | BE73: -168 | BF73: -181 | BG73: 0 | BH73: -105 | BI73: =SUM(AZ73:BH73) -> -1554 | BJ73: =+BI73/BI$13 -> -0.0031334183 | BL73: -160 | BM73: -214 | BN73: -146 | BO73: -291 | BP73: -193 | BQ73: -146 | BR73: -173 | BS73: 0 | BT73: -79 | BU73: =SUM(BL73:BT73) -> -1402 | BV73: =+BU73/BU$13 -> -0.0028205056 | BX73: -173 | BY73: -200 | BZ73: -146 | CA73: -305 | CB73: -326 | CC73: -173 | CD73: -173 | CE73: 0 | CF73: -105 | CG73: =SUM(BX73:CF73) -> -1601 | CH73: =+CG73/CG$13 -> -0.0033355001 | CJ73: =+CG73-BU73 -> -199 | CK73: =IFERROR(+CJ73/BU73,0%) -> 0.14194009 | CM73: =-DATOS!D155 -> -9085 | CN73: =+CM73/CM$13 -> -0.0029864577 | CP73: =-DATOS!F155 -> -1329 | CQ73: =+CP73/CP$13 -> -0.0025795983 | CS73: =-DATOS!G155 -> -7962 | CT73: =+CS73/CS$13 -> -0.0027091469 | CV73: =+CM73-CS73 -> -1123 | CW73: =+IFERROR(CV73/CS73,0) -> 0.14104496
A74: 52353001 | B74: Energia Electrica | D74: -28 | E74: -2008 | F74: -1131 | G74: -2204 | H74: -5639 | I74: -1867 | J74: -2090 | K74: -1646 | L74: -2228 | M74: =SUM(D74:L74) -> -18841 | N74: =+M74/M$13 -> -0.037325985 | P74: -28 | Q74: -1657 | R74: -1103 | S74: -2117 | T74: -4052 | U74: -1795 | V74: -2104 | W74: 0 | X74: -1764 | Y74: =SUM(P74:X74) -> -14620 | Z74: =+Y74/Y$13 -> -0.027779783 | AB74: -28 | AC74: -1638 | AD74: -977 | AE74: -2275 | AF74: -4338 | AG74: -1725 | AH74: -1866 | AI74: -2141 | AJ74: -1270 | AK74: =SUM(AB74:AJ74) -> -16258 | AL74: =+AK74/AK$13 -> -0.031769729 | AN74: -30 | AO74: -1609 | AP74: -1013 | AQ74: -2006 | AR74: -3783 | AS74: -1933 | AT74: -2030 | AU74: 0 | AV74: -1506 | AW74: =SUM(AN74:AV74) -> -13910 | AX74: =+AW74/AW$13 -> -0.026194673 | AZ74: -30 | BA74: -1608 | BB74: -987 | BC74: -1858 | BD74: -3855 | BE74: -1834 | BF74: -1887 | BG74: 0 | BH74: -1335 | BI74: =SUM(AZ74:BH74) -> -13394 | BJ74: =+BI74/BI$13 -> -0.027007081 | BL74: -30 | BM74: -1897 | BN74: -975 | BO74: -2068 | BP74: -2562 | BQ74: -1756 | BR74: -1934 | BS74: 0 | BT74: -1200 | BU74: =SUM(BL74:BT74) -> -12422 | BV74: =+BU74/BU$13 -> -0.024990243 | BX74: -30 | BY74: -1741 | BZ74: -975 | CA74: -2219 | CB74: -4103 | CC74: -1884 | CD74: -1997 | CE74: 0 | CF74: -1146 | CG74: =SUM(BX74:CF74) -> -14095 | CH74: =+CG74/CG$13 -> -0.029365317 | CJ74: =+CG74-BU74 -> -1673 | CK74: =IFERROR(+CJ74/BU74,0%) -> 0.13468041 | CM74: =-DATOS!D156 -> -84697 | CN74: =+CM74/CM$13 -> -0.027841938 | CP74: =-DATOS!F156 -> -14028 | CQ74: =+CP74/CP$13 -> -0.027228446 | CS74: =-DATOS!G156 -> -88695.5 | CT74: =+CS74/CS$13 -> -0.030179495 | CV74: =+CM74-CS74 -> 3998.5 | CW74: =+IFERROR(CV74/CS74,0) -> -0.045081205
A75: 52353501 | B75: Telefono | D75: 0 | E75: 0 | F75: 0 | G75: 0 | H75: 0 | I75: 0 | J75: 0 | K75: 0 | L75: 0 | M75: =SUM(D75:L75) -> 0 | N75: =+M75/M$13 -> 0 | P75: 0 | Q75: 0 | R75: 0 | S75: 0 | T75: 0 | U75: 0 | V75: 0 | W75: 0 | X75: 0 | Y75: =SUM(P75:X75) -> 0 | Z75: =+Y75/Y$13 -> 0 | AB75: 0 | AC75: 0 | AD75: 0 | AE75: 0 | AF75: 0 | AG75: 0 | AH75: 0 | AI75: 0 | AJ75: 0 | AK75: =SUM(AB75:AJ75) -> 0 | AL75: =+AK75/AK$13 -> 0 | AN75: 0 | AO75: 0 | AP75: 0 | AQ75: 0 | AR75: 0 | AS75: 0 | AT75: 0 | AU75: 0 | AV75: 0 | AW75: =SUM(AN75:AV75) -> 0 | AX75: =+AW75/AW$13 -> 0 | AZ75: 0 | BA75: 0 | BB75: 0 | BC75: -148 | BD75: -148 | BE75: 0 | BF75: -820 | BG75: 0 | BH75: 0 | BI75: =SUM(AZ75:BH75) -> -1116 | BJ75: =+BI75/BI$13 -> -0.0022502541 | BL75: 0 | BM75: 0 | BN75: 0 | BO75: 0 | BP75: 0 | BQ75: 0 | BR75: 0 | BS75: 0 | BT75: 0 | BU75: =SUM(BL75:BT75) -> 0 | BV75: =+BU75/BU$13 -> 0 | BX75: 0 | BY75: 0 | BZ75: 0 | CA75: 0 | CB75: 0 | CC75: 0 | CD75: 0 | CE75: 0 | CF75: 0 | CG75: =SUM(BX75:CF75) -> 0 | CH75: =+CG75/CG$13 -> 0 | CJ75: =+CG75-BU75 -> 0 | CK75: =IFERROR(+CJ75/BU75,0%) -> 0 | CM75: =-DATOS!D157 -> -1116 | CN75: =+CM75/CM$13 -> -0.00036685601 | CP75: =-DATOS!F157 -> 0 | CQ75: =+CP75/CP$13 -> 0 | CS75: =-DATOS!G157 -> -1 | CT75: =+CS75/CS$13 -> -3.402596e-07 | CV75: =+CM75-CS75 -> -1115 | CW75: =+IFERROR(CV75/CS75,0) -> 1115
A76: 52355001 | B76: Fletes | D76: -827 | E76: -895 | F76: -907 | G76: -1066 | H76: -1451 | I76: -832 | J76: -980 | K76: 0 | L76: -973 | M76: =SUM(D76:L76) -> -7931 | N76: =+M76/M$13 -> -0.015712138 | P76: -729 | Q76: -810 | R76: -729 | S76: -786 | T76: -825 | U76: -985 | V76: -753 | W76: 0 | X76: -829 | Y76: =SUM(P76:X76) -> -6446 | Z76: =+Y76/Y$13 -> -0.012248186 | AB76: -1129 | AC76: -1137 | AD76: -1113 | AE76: -1184 | AF76: -1482 | AG76: -1149 | AH76: -1164 | AI76: 0 | AJ76: -1173 | AK76: =SUM(AB76:AJ76) -> -9531 | AL76: =+AK76/AK$13 -> -0.01862451 | AN76: -1402 | AO76: -1402 | AP76: -1409 | AQ76: -1461 | AR76: -1750 | AS76: -1422 | AT76: -1412 | AU76: 0 | AV76: -1392 | AW76: =SUM(AN76:AV76) -> -11650 | AX76: =+AW76/AW$13 -> -0.021938745 | AZ76: -667 | BA76: -737 | BB76: -667 | BC76: -716 | BD76: -1029 | BE76: -697 | BF76: -707 | BG76: 0 | BH76: -667 | BI76: =SUM(AZ76:BH76) -> -5887 | BJ76: =+BI76/BI$13 -> -0.011870292 | BL76: -1303 | BM76: -689 | BN76: -667 | BO76: -732 | BP76: -1035 | BQ76: -697 | BR76: -702 | BS76: 0 | BT76: -667 | BU76: =SUM(BL76:BT76) -> -6492 | BV76: =+BU76/BU$13 -> -0.01306043 | BX76: -677 | BY76: -931 | BZ76: -667 | CA76: -732 | CB76: -1045 | CC76: -697 | CD76: -867 | CE76: 0 | CF76: -667 | CG76: =SUM(BX76:CF76) -> -6283 | CH76: =+CG76/CG$13 -> -0.013089911 | CJ76: =+CG76-BU76 -> 209 | CK76: =IFERROR(+CJ76/BU76,0%) -> -0.032193469 | CM76: =-DATOS!D158 -> -46292.5 | CN76: =+CM76/CM$13 -> -0.015217457 | CP76: =-DATOS!F158 -> -3352.5 | CQ76: =+CP76/CP$13 -> -0.0065072259 | CS76: =-DATOS!G158 -> -21748 | CT76: =+CS76/CS$13 -> -0.0073999658 | CV76: =+CM76-CS76 -> -24544.5 | CW76: =+IFERROR(CV76/CS76,0) -> 1.1285865
A77: 52356001 | B77: Publicidad, Propaganda Y Pr | D77: -17 | E77: 0 | F77: -17 | G77: -35 | H77: -35 | I77: -79 | J77: -17 | K77: 0 | L77: -164 | M77: =SUM(D77:L77) -> -364 | N77: =+M77/M$13 -> -0.00072112194 | P77: -950 | Q77: -89 | R77: -127 | S77: -234 | T77: -127 | U77: -127 | V77: -127 | W77: 0 | X77: -440 | Y77: =SUM(P77:X77) -> -2221 | Z77: =+Y77/Y$13 -> -0.0042201709 | AB77: -23 | AC77: -23 | AD77: -44 | AE77: -23 | AF77: -95 | AG77: -23 | AH77: -23 | AI77: 0 | AJ77: -124 | AK77: =SUM(AB77:AJ77) -> -378 | AL77: =+AK77/AK$13 -> -0.00073864913 | AN77: 0 | AO77: 0 | AP77: 0 | AQ77: 0 | AR77: 0 | AS77: 0 | AT77: 0 | AU77: 0 | AV77: 0 | AW77: =SUM(AN77:AV77) -> 0 | AX77: =+AW77/AW$13 -> 0 | AZ77: 0 | BA77: 0 | BB77: 0 | BC77: 0 | BD77: 0 | BE77: -45 | BF77: 0 | BG77: 0 | BH77: 0 | BI77: =SUM(AZ77:BH77) -> -45 | BJ77: =+BI77/BI$13 -> -9.0736051e-05 | BL77: -225 | BM77: -225 | BN77: -225 | BO77: -225 | BP77: -225 | BQ77: -225 | BR77: -225 | BS77: 0 | BT77: -225 | BU77: =SUM(BL77:BT77) -> -1800 | BV77: =+BU77/BU$13 -> -0.0036211912 | BX77: 0 | BY77: 0 | BZ77: 0 | CA77: -763 | CB77: 0 | CC77: 0 | CD77: 0 | CE77: 0 | CF77: 0 | CG77: =SUM(BX77:CF77) -> -763 | CH77: =+CG77/CG$13 -> -0.0015896231 | CJ77: =+CG77-BU77 -> 1037 | CK77: =IFERROR(+CJ77/BU77,0%) -> -0.57611111 | CM77: =-DATOS!D159 -> -5203 | CN77: =+CM77/CM$13 -> -0.0017103511 | CP77: =-DATOS!F159 -> -7649 | CQ77: =+CP77/CP$13 -> -0.014846762 | CS77: =-DATOS!G159 -> -13036 | CT77: =+CS77/CS$13 -> -0.0044356242 | CV77: =+CM77-CS77 -> 7833 | CW77: =+IFERROR(CV77/CS77,0) -> -0.6008745
A78: 52356501 | B78: Une Epm Telecomunicaciones S.A | D78: 0 | E78: 0 | F78: 0 | G78: 0 | H78: -100 | I78: 0 | J78: 0 | K78: 0 | L78: 0 | M78: =SUM(D78:L78) -> -100 | N78: =+M78/M$13 -> -0.00019811042 | P78: 0 | Q78: 0 | R78: 0 | S78: 0 | T78: -110 | U78: 0 | V78: 0 | W78: 0 | X78: 0 | Y78: =SUM(P78:X78) -> -110 | Z78: =+Y78/Y$13 -> -0.00020901342 | AB78: 0 | AC78: 0 | AD78: 0 | AE78: 0 | AF78: -110 | AG78: 0 | AH78: 0 | AI78: 0 | AJ78: 0 | AK78: =SUM(AB78:AJ78) -> -110 | AL78: =+AK78/AK$13 -> -0.00021495081 | AN78: 0 | AO78: 0 | AP78: 0 | AQ78: 0 | AR78: -110 | AS78: 0 | AT78: 0 | AU78: 0 | AV78: 0 | AW78: =SUM(AN78:AV78) -> -110 | AX78: =+AW78/AW$13 -> -0.00020714695 | AZ78: 0 | BA78: 0 | BB78: 0 | BC78: 0 | BD78: -110 | BE78: 0 | BF78: 0 | BG78: 0 | BH78: 0 | BI78: =SUM(AZ78:BH78) -> -110 | BJ78: =+BI78/BI$13 -> -0.00022179924 | BL78: 0 | BM78: 0 | BN78: 0 | BO78: 0 | BP78: -110 | BQ78: 0 | BR78: 0 | BS78: 0 | BT78: 0 | BU78: =SUM(BL78:BT78) -> -110 | BV78: =+BU78/BU$13 -> -0.00022129502 | BX78: 0 | BY78: 0 | BZ78: 0 | CA78: 0 | CB78: -110 | CC78: 0 | CD78: 0 | CE78: 0 | CF78: 0 | CG78: =SUM(BX78:CF78) -> -110 | CH78: =+CG78/CG$13 -> -0.0002291724 | CJ78: =+CG78-BU78 -> 0 | CK78: =IFERROR(+CJ78/BU78,0%) -> 0 | CM78: =-DATOS!D160 -> -659 | CN78: =+CM78/CM$13 -> -0.00021662913 | CP78: =-DATOS!F160 -> -387.5 | CQ78: =+CP78/CP$13 -> -0.0007521402 | CS78: =-DATOS!G160 -> -1106 | CT78: =+CS78/CS$13 -> -0.00037632712 | CV78: =+CM78-CS78 -> 447 | CW78: =+IFERROR(CV78/CS78,0) -> -0.40415913
A79: 52359503 | B79: Servicios Administrativo P.Tva | D79: -456 | E79: -566 | F79: -456 | G79: -566 | H79: -456 | I79: -456 | J79: -566 | K79: 0 | L79: -566 | M79: =SUM(D79:L79) -> -4088 | N79: =+M79/M$13 -> -0.0080987541 | P79: 0 | Q79: 0 | R79: 0 | S79: 0 | T79: -2222 | U79: 0 | V79: 0 | W79: 0 | X79: 0 | Y79: =SUM(P79:X79) -> -2222 | Z79: =+Y79/Y$13 -> -0.0042220711 | AB79: 0 | AC79: 0 | AD79: 0 | AE79: 0 | AF79: -3633 | AG79: 0 | AH79: 0 | AI79: 0 | AJ79: 0 | AK79: =SUM(AB79:AJ79) -> -3633 | AL79: =+AK79/AK$13 -> -0.0070992389 | AN79: 0 | AO79: 0 | AP79: 0 | AQ79: 0 | AR79: -5547 | AS79: 0 | AT79: 0 | AU79: 0 | AV79: 0 | AW79: =SUM(AN79:AV79) -> -5547 | AX79: =+AW79/AW$13 -> -0.010445856 | AZ79: -456 | BA79: -456 | BB79: -456 | BC79: -456 | BD79: -7149 | BE79: -456 | BF79: -456 | BG79: 0 | BH79: -456 | BI79: =SUM(AZ79:BH79) -> -10341 | BJ79: =+BI79/BI$13 -> -0.020851144 | BL79: -456 | BM79: -456 | BN79: -456 | BO79: -456 | BP79: -29843 | BQ79: -456 | BR79: -456 | BS79: -20108 | BT79: -456 | BU79: =SUM(BL79:BT79) -> -53143 | BV79: =+BU79/BU$13 -> -0.10691165 | BX79: -456 | BY79: -456 | BZ79: -456 | CA79: -456 | CB79: -2386 | CC79: -456 | CD79: -456 | CE79: 0 | CF79: -456 | CG79: =SUM(BX79:CF79) -> -5578 | CH79: =+CG79/CG$13 -> -0.011621124 | CJ79: =+CG79-BU79 -> 47565 | CK79: =IFERROR(+CJ79/BU79,0%) -> -0.89503792 | CM79: =-DATOS!D161 -> -80470 | CN79: =+CM79/CM$13 -> -0.026452422 | CP79: =-DATOS!F161 -> -16825.5 | CQ79: =+CP79/CP$13 -> -0.032658413 | CS79: =-DATOS!G161 -> -79623.5 | CT79: =+CS79/CS$13 -> -0.02709266 | CV79: =+CM79-CS79 -> -846.5 | CW79: =+IFERROR(CV79/CS79,0) -> 0.010631283
A80: 52359504 | B80: PRESTAMOS A EMPLEADOS | D80: 0 | E80: 0 | F80: 0 | G80: 0 | H80: 0 | I80: 0 | J80: 0 | K80: -1036 | L80: 0 | M80: =SUM(D80:L80) -> -1036 | N80: =+M80/M$13 -> -0.002052424 | P80: 0 | Q80: -1110 | R80: 0 | S80: 0 | T80: 0 | U80: 0 | V80: 0 | W80: 0 | X80: 0 | Y80: =SUM(P80:X80) -> -1110 | Z80: =+Y80/Y$13 -> -0.0021091354 | AB80: 0 | AC80: 0 | AD80: -1368 | AE80: 0 | AF80: -2197 | AG80: 0 | AH80: 0 | AI80: 0 | AJ80: 0 | AK80: =SUM(AB80:AJ80) -> -3565 | AL80: =+AK80/AK$13 -> -0.0069663602 | AN80: 0 | AO80: 0 | AP80: 0 | AQ80: -514 | AR80: 0 | AS80: 0 | AT80: 0 | AU80: 0 | AV80: -581 | AW80: =SUM(AN80:AV80) -> -1095 | AX80: =+AW80/AW$13 -> -0.0020620537 | AZ80: 0 | BA80: 0 | BB80: 0 | BC80: -2370 | BD80: 0 | BE80: 0 | BF80: 0 | BG80: 0 | BH80: 0 | BI80: =SUM(AZ80:BH80) -> -2370 | BJ80: =+BI80/BI$13 -> -0.0047787653 | BL80: 0 | BM80: 0 | BN80: 0 | BO80: -4448 | BP80: 0 | BQ80: 0 | BR80: 0 | BS80: 0 | BT80: 0 | BU80: =SUM(BL80:BT80) -> -4448 | BV80: =+BU80/BU$13 -> -0.0089483658 | BX80: -811 | BY80: 0 | BZ80: 0 | CA80: -1737 | CB80: 0 | CC80: 0 | CD80: 0 | CE80: 0 | CF80: 0 | CG80: =SUM(BX80:CF80) -> -2548 | CH80: =+CG80/CG$13 -> -0.005308466 | CJ80: =+CG80-BU80 -> 1900 | CK80: =IFERROR(+CJ80/BU80,0%) -> -0.42715827 | CM80: =-DATOS!D162 -> -15136 | CN80: =+CM80/CM$13 -> -0.0049755668 | CP80: =-DATOS!F162 -> 0 | CQ80: =+CP80/CP$13 -> 0 | CS80: =-DATOS!G162 -> -4495 | CT80: =+CS80/CS$13 -> -0.0015294669 | CV80: =+CM80-CS80 -> -10641 | CW80: =+IFERROR(CV80/CS80,0) -> 2.367297
A81: 52359505 | B81: Servicio Plataforma Rappi | D81: 0 | E81: 0 | F81: 0 | G81: -318 | H81: 0 | I81: 0 | J81: -229 | K81: 0 | L81: -59 | M81: =SUM(D81:L81) -> -606 | N81: =+M81/M$13 -> -0.0012005492 | P81: 0 | Q81: 0 | R81: 0 | S81: -479 | T81: 0 | U81: 0 | V81: -107 | W81: 0 | X81: -300 | Y81: =SUM(P81:X81) -> -886 | Z81: =+Y81/Y$13 -> -0.0016835081 | AB81: 0 | AC81: 0 | AD81: 0 | AE81: -220 | AF81: 0 | AG81: 0 | AH81: -143 | AI81: 0 | AJ81: -185 | AK81: =SUM(AB81:AJ81) -> -548 | AL81: =+AK81/AK$13 -> -0.0010708458 | AN81: 0 | AO81: 0 | AP81: 0 | AQ81: -1135 | AR81: 0 | AS81: 0 | AT81: -135 | AU81: 0 | AV81: -150 | AW81: =SUM(AN81:AV81) -> -1420 | AX81: =+AW81/AW$13 -> -0.0026740788 | AZ81: 0 | BA81: 0 | BB81: 0 | BC81: -2065 | BD81: 0 | BE81: 0 | BF81: -144 | BG81: 0 | BH81: -361 | BI81: =SUM(AZ81:BH81) -> -2570 | BJ81: =+BI81/BI$13 -> -0.0051820367 | BL81: 0 | BM81: 0 | BN81: 0 | BO81: -138 | BP81: 0 | BQ81: 0 | BR81: 0 | BS81: 0 | BT81: -331 | BU81: =SUM(BL81:BT81) -> -469 | BV81: =+BU81/BU$13 -> -0.00094352149 | BX81: 0 | BY81: 0 | BZ81: 0 | CA81: -324 | CB81: 0 | CC81: 0 | CD81: 0 | CE81: 0 | CF81: -311 | CG81: =SUM(BX81:CF81) -> -635 | CH81: =+CG81/CG$13 -> -0.0013229497 | CJ81: =+CG81-BU81 -> -166 | CK81: =IFERROR(+CJ81/BU81,0%) -> 0.35394456 | CM81: =-DATOS!D163 -> -6527 | CN81: =+CM81/CM$13 -> -0.0021455817 | CP81: =-DATOS!F163 -> -1399 | CQ81: =+CP81/CP$13 -> -0.0027154688 | CS81: =-DATOS!G163 -> -4828 | CT81: =+CS81/CS$13 -> -0.0016427734 | CV81: =+CM81-CS81 -> -1699 | CW81: =+IFERROR(CV81/CS81,0) -> 0.35190555
A82: 52359506 | B82: Servicio Adm P. TVA ARR | D82: 0 | E82: 0 | F82: 0 | G82: 0 | H82: 0 | I82: 0 | J82: 0 | K82: 0 | L82: 0 | M82: =SUM(D82:L82) -> 0 | N82: =+M82/M$13 -> 0 | P82: 0 | Q82: 0 | R82: 0 | S82: 0 | T82: 0 | U82: 0 | V82: 0 | W82: 0 | X82: 0 | Y82: =SUM(P82:X82) -> 0 | Z82: =+Y82/Y$13 -> 0 | AB82: 0 | AC82: 0 | AD82: 0 | AE82: 0 | AF82: 0 | AG82: 0 | AH82: 0 | AI82: 0 | AJ82: 0 | AK82: =SUM(AB82:AJ82) -> 0 | AL82: =+AK82/AK$13 -> 0 | AN82: 0 | AO82: 0 | AP82: 0 | AQ82: 0 | AR82: 0 | AS82: 0 | AT82: 0 | AU82: 0 | AV82: 0 | AW82: =SUM(AN82:AV82) -> 0 | AX82: =+AW82/AW$13 -> 0 | AZ82: 0 | BA82: 0 | BB82: 0 | BC82: 0 | BD82: 0 | BE82: 0 | BF82: 0 | BG82: 0 | BH82: 0 | BI82: =SUM(AZ82:BH82) -> 0 | BJ82: =+BI82/BI$13 -> 0 | BL82: 0 | BM82: 0 | BN82: 0 | BO82: 0 | BP82: 0 | BQ82: 0 | BR82: 0 | BS82: 0 | BT82: 0 | BU82: =SUM(BL82:BT82) -> 0 | BV82: =+BU82/BU$13 -> 0 | BX82: 0 | BY82: 0 | BZ82: 0 | CA82: 0 | CB82: 0 | CC82: 0 | CD82: 0 | CE82: 0 | CF82: 0 | CG82: =SUM(BX82:CF82) -> 0 | CH82: =+CG82/CG$13 -> 0 | CJ82: =+CG82-BU82 -> 0 | CK82: =IFERROR(+CJ82/BU82,0%) -> 0 | CM82: =-DATOS!D164 -> 0 | CN82: =+CM82/CM$13 -> 0 | CP82: =-+DATOS!F164 -> 0 | CQ82: =+CP82/CP$13 -> 0 | CS82: =+-DATOS!G164 -> 0 | CT82: =+CS82/CS$13 -> 0 | CV82: =+CM82-CS82 -> 0 | CW82: =+IFERROR(CV82/CS82,0) -> 0
A83: 52359506 | B83: Avisos de señalización | D83: 0 | E83: 0 | F83: 0 | G83: 0 | H83: 0 | I83: 0 | J83: 0 | K83: 0 | L83: 0 | M83: =SUM(D83:L83) -> 0 | N83: =+M83/M$13 -> 0 | P83: 0 | Q83: 0 | R83: 0 | S83: 0 | T83: 0 | U83: 0 | V83: 0 | W83: 0 | X83: 0 | Y83: =SUM(P83:X83) -> 0 | Z83: =+Y83/Y$13 -> 0 | AB83: 0 | AC83: 0 | AD83: 0 | AE83: 0 | AF83: 0 | AG83: 0 | AH83: 0 | AI83: 0 | AJ83: 0 | AK83: =SUM(AB83:AJ83) -> 0 | AL83: =+AK83/AK$13 -> 0 | AN83: 0 | AO83: 0 | AP83: 0 | AQ83: 0 | AR83: 0 | AS83: 0 | AT83: 0 | AU83: 0 | AV83: 0 | AW83: =SUM(AN83:AV83) -> 0 | AX83: =+AW83/AW$13 -> 0 | AZ83: -8 | BA83: -7 | BB83: 0 | BC83: -8 | BD83: 0 | BE83: 0 | BF83: -8 | BG83: 0 | BH83: 0 | BI83: =SUM(AZ83:BH83) -> -31 | BJ83: =+BI83/BI$13 -> -6.2507057e-05 | BL83: 0 | BM83: 0 | BN83: 0 | BO83: 0 | BP83: 0 | BQ83: 0 | BR83: 0 | BS83: 0 | BT83: 0 | BU83: =SUM(BL83:BT83) -> 0 | BV83: =+BU83/BU$13 -> 0 | BX83: 0 | BY83: 0 | BZ83: 0 | CA83: 0 | CB83: 0 | CC83: 0 | CD83: 0 | CE83: 0 | CF83: 0 | CG83: =SUM(BX83:CF83) -> 0 | CH83: =+CG83/CG$13 -> 0 | CJ83: =+CG83-BU83 -> 0 | CK83: =IFERROR(+CJ83/BU83,0%) -> 0 | CM83: =-DATOS!D165 -> -30 | CP83: =-DATOS!F165 -> 0 | CQ83: =+CP83/CP$13 -> 0 | CS83: =-DATOS!G165 -> 0 | CT83: =+CS83/CS$13 -> 0
A84: 52359509 | B84: Recarga Extintores | D84: 0 | E84: 0 | F84: 0 | G84: 0 | H84: 0 | I84: 0 | J84: 0 | K84: 0 | L84: -6 | M84: =SUM(D84:L84) -> -6 | N84: =+M84/M$13 -> -1.1886625e-05 | P84: 0 | Q84: 0 | R84: 0 | S84: 0 | T84: 0 | U84: 0 | V84: 0 | W84: 0 | X84: -6 | Y84: =SUM(P84:X84) -> -6 | Z84: =+Y84/Y$13 -> -1.1400732e-05 | AB84: 0 | AC84: -22 | AD84: 0 | AE84: 0 | AF84: -22 | AG84: 0 | AH84: 0 | AI84: 0 | AJ84: 0 | AK84: =SUM(AB84:AJ84) -> -44 | AL84: =+AK84/AK$13 -> -8.5980322e-05 | AN84: 0 | AO84: 0 | AP84: 0 | AQ84: 0 | AR84: -22 | AS84: 0 | AT84: -22 | AU84: 0 | AV84: 0 | AW84: =SUM(AN84:AV84) -> -44 | AX84: =+AW84/AW$13 -> -8.2858779e-05 | AZ84: 0 | BA84: 0 | BB84: 0 | BC84: -22 | BD84: 0 | BE84: 0 | BF84: 0 | BG84: 0 | BH84: 0 | BI84: =SUM(AZ84:BH84) -> -22 | BJ84: =+BI84/BI$13 -> -4.4359847e-05 | BL84: 0 | BM84: 0 | BN84: 0 | BO84: 0 | BP84: 0 | BQ84: 0 | BR84: 0 | BS84: 0 | BT84: 0 | BU84: =SUM(BL84:BT84) -> 0 | BV84: =+BU84/BU$13 -> 0 | BX84: 0 | BY84: 0 | BZ84: 0 | CA84: 0 | CB84: 0 | CC84: 0 | CD84: 0 | CE84: 0 | CF84: 0 | CG84: =SUM(BX84:CF84) -> 0 | CH84: =+CG84/CG$13 -> 0 | CJ84: =+CG84-BU84 -> 0 | CK84: =IFERROR(+CJ84/BU84,0%) -> 0 | CM84: =+Y84 -> -6 | CN84: =+CM84/CM$13 -> -1.9723441e-06 | CP84: =-DATOS!F166 -> 0 | CQ84: =+CP84/CP$13 -> 0 | CS84: =-DATOS!G166 -> -95 | CT84: =+CS84/CS$13 -> -3.2324662e-05 | CV84: =+CM84-CS84 -> 89 | CW84: =+IFERROR(CV84/CS84,0) -> -0.93684211
A85: 52359595 | B85: Otros Servicios | D85: -224 | E85: -224 | F85: -112 | G85: -224 | H85: -308 | I85: -112 | J85: -224 | K85: 0 | L85: -224 | M85: =SUM(D85:L85) -> -1652 | N85: =+M85/M$13 -> -0.0032727842 | P85: -183 | Q85: -123 | R85: -123 | S85: -123 | T85: -123 | U85: -123 | V85: -123 | W85: 0 | X85: -123 | Y85: =SUM(P85:X85) -> -1044 | Z85: =+Y85/Y$13 -> -0.0019837274 | AB85: -123 | AC85: -123 | AD85: -342 | AE85: -123 | AF85: -123 | AG85: -123 | AH85: -123 | AI85: 0 | AJ85: -123 | AK85: =SUM(AB85:AJ85) -> -1203 | AL85: =+AK85/AK$13 -> -0.0023507802 | AN85: -123 | AO85: -123 | AP85: -123 | AQ85: -123 | AR85: -123 | AS85: -123 | AT85: -123 | AU85: 0 | AV85: -123 | AW85: =SUM(AN85:AV85) -> -984 | AX85: =+AW85/AW$13 -> -0.0018530236 | AZ85: -123 | BA85: -123 | BB85: -123 | BC85: -123 | BD85: -560 | BE85: -123 | BF85: -123 | BG85: 0 | BH85: -123 | BI85: =SUM(AZ85:BH85) -> -1421 | BJ85: =+BI85/BI$13 -> -0.0028652428 | BL85: -123 | BM85: -478 | BN85: -123 | BO85: -123 | BP85: -123 | BQ85: -123 | BR85: -123 | BS85: 0 | BT85: -123 | BU85: =SUM(BL85:BT85) -> -1339 | BV85: =+BU85/BU$13 -> -0.0026937639 | BX85: -123 | BY85: -123 | BZ85: -123 | CA85: -123 | CB85: -123 | CC85: -123 | CD85: -123 | CE85: 0 | CF85: -123 | CG85: =SUM(BX85:CF85) -> -984 | CH85: =+CG85/CG$13 -> -0.0020500513 | CJ85: =+CG85-BU85 -> 355 | CK85: =IFERROR(+CJ85/BU85,0%) -> -0.26512323 | CM85: =-DATOS!D167 -> -6984 | CN85: =+CM85/CM$13 -> -0.0022958086 | CP85: =-DATOS!F167 -> -1491 | CQ85: =+CP85/CP$13 -> -0.0028940414 | CS85: =-DATOS!G167 -> -9510 | CT85: =+CS85/CS$13 -> -0.0032358688 | CV85: =+CM85-CS85 -> 2526 | CW85: =+IFERROR(CV85/CS85,0) -> -0.26561514
A86: 52401501 | B86: tramites y licencias | D86: -12 | E86: 0 | F86: 0 | G86: 0 | H86: 0 | I86: 0 | J86: 0 | K86: 0 | L86: 0 | M86: =SUM(D86:L86) -> -12 | N86: =+M86/M$13 -> -2.3773251e-05 | P86: -12 | Q86: 0 | R86: 0 | S86: 0 | T86: 0 | U86: 0 | V86: 0 | W86: 0 | X86: 0 | Y86: =SUM(P86:X86) -> -12 | Z86: =+Y86/Y$13 -> -2.2801464e-05 | AB86: -24 | AC86: 0 | AD86: 0 | AE86: 0 | AF86: 0 | AG86: 0 | AH86: 0 | AI86: 0 | AJ86: 0 | AK86: =SUM(AB86:AJ86) -> -24 | AL86: =+AK86/AK$13 -> -4.6898358e-05 | AN86: -979 | AO86: -701 | AP86: -507 | AQ86: -548 | AR86: -1180 | AS86: -1162 | AT86: -936 | AU86: 0 | AV86: -485 | AW86: =SUM(AN86:AV86) -> -6498 | AX86: =+AW86/AW$13 -> -0.012236735 | AZ86: 0 | BA86: 0 | BB86: 0 | BC86: 0 | BD86: 0 | BE86: 0 | BF86: 0 | BG86: 0 | BH86: 0 | BI86: =SUM(AZ86:BH86) -> 0 | BJ86: =+BI86/BI$13 -> 0 | BL86: -23 | BM86: 0 | BN86: 0 | BO86: 0 | BP86: -12 | BQ86: 0 | BR86: 0 | BS86: 0 | BT86: 0 | BU86: =SUM(BL86:BT86) -> -35 | BV86: =+BU86/BU$13 -> -7.0412051e-05 | BX86: 0 | BY86: 0 | BZ86: 0 | CA86: 0 | CB86: -12 | CC86: 0 | CD86: 0 | CE86: 0 | CF86: 0 | CG86: =SUM(BX86:CF86) -> -12 | CH86: =+CG86/CG$13 -> -2.5000625e-05 | CJ86: =+CG86-BU86 -> 23 | CK86: =IFERROR(+CJ86/BU86,0%) -> -0.65714286 | CM86: =-DATOS!D168 -> -6582 | CN86: =+CM86/CM$13 -> -0.0021636615 | CP86: =-DATOS!F168 -> 0 | CQ86: =+CP86/CP$13 -> 0 | CS86: =-DATOS!G168 -> -6130 | CT86: =+CS86/CS$13 -> -0.0020857914 | CV86: =+CM86-CS86 -> -452 | CW86: =+IFERROR(CV86/CS86,0) -> 0.073735726
A87: 52451501 | B87: Mantenimiento Y Reparaciones | D87: -170 | E87: -170 | F87: -225 | G87: -170 | H87: -295 | I87: -540 | J87: -400 | K87: -120 | L87: -380 | M87: =SUM(D87:L87) -> -2470 | N87: =+M87/M$13 -> -0.0048933274 | P87: 0 | Q87: -2705 | R87: 0 | S87: 0 | T87: 0 | U87: -120 | V87: -250 | W87: 0 | X87: 0 | Y87: =SUM(P87:X87) -> -3075 | Z87: =+Y87/Y$13 -> -0.0058428751 | AB87: -370 | AC87: -2829 | AD87: -325 | AE87: -500 | AF87: -1514 | AG87: -1055 | AH87: -2087 | AI87: 0 | AJ87: -665 | AK87: =SUM(AB87:AJ87) -> -9345 | AL87: =+AK87/AK$13 -> -0.018261048 | AN87: -195 | AO87: -170 | AP87: 0 | AQ87: -390 | AR87: -180 | AS87: 0 | AT87: 0 | AU87: 0 | AV87: 0 | AW87: =SUM(AN87:AV87) -> -935 | AX87: =+AW87/AW$13 -> -0.001760749 | AZ87: -582 | BA87: -150 | BB87: -325 | BC87: -90 | BD87: -175 | BE87: -400 | BF87: -2682 | BG87: 0 | BH87: -200 | BI87: =SUM(AZ87:BH87) -> -4604 | BJ87: =+BI87/BI$13 -> -0.0092833062 | BL87: -348 | BM87: -440 | BN87: -440 | BO87: -345 | BP87: -1235 | BQ87: -310 | BR87: -420 | BS87: 0 | BT87: -250 | BU87: =SUM(BL87:BT87) -> -3788 | BV87: =+BU87/BU$13 -> -0.0076205957 | BX87: -580 | BY87: 0 | BZ87: -230 | CA87: -194 | CB87: -320 | CC87: -270 | CD87: -1080 | CE87: 0 | CF87: -104 | CG87: =SUM(BX87:CF87) -> -2778 | CH87: =+CG87/CG$13 -> -0.0057876447 | CJ87: =+CG87-BU87 -> 1010 | CK87: =IFERROR(+CJ87/BU87,0%) -> -0.26663147 | CM87: =-DATOS!D169 -> -24804 | CN87: =+CM87/CM$13 -> -0.0081536706 | CP87: =-DATOS!F169 -> -2795 | CQ87: =+CP87/CP$13 -> -0.0054251145 | CS87: =-DATOS!G169 -> -15052 | CT87: =+CS87/CS$13 -> -0.0051215875 | CV87: =+CM87-CS87 -> -9752 | CW87: =+IFERROR(CV87/CS87,0) -> 0.64788732
A88: 52459595 | B88: Otros | D88: 0 | E88: 0 | F88: 0 | G88: 0 | H88: 0 | I88: 0 | J88: 0 | K88: 0 | L88: 0 | M88: =SUM(D88:L88) -> 0 | N88: =+M88/M$13 -> 0 | P88: 0 | Q88: 0 | R88: 0 | S88: 0 | T88: 0 | U88: 0 | V88: 0 | W88: 0 | X88: 0 | Y88: =SUM(P88:X88) -> 0 | Z88: =+Y88/Y$13 -> 0 | AB88: 0 | AC88: -150 | AD88: 0 | AE88: 0 | AF88: 0 | AG88: 0 | AH88: 0 | AI88: 0 | AJ88: 0 | AK88: =SUM(AB88:AJ88) -> -150 | AL88: =+AK88/AK$13 -> -0.00029311473 | AN88: -129 | AO88: 0 | AP88: 0 | AQ88: 0 | AR88: 0 | AS88: 0 | AT88: 0 | AU88: 0 | AV88: 0 | AW88: =SUM(AN88:AV88) -> -129 | AX88: =+AW88/AW$13 -> -0.00024292687 | AZ88: 0 | BA88: 0 | BB88: 0 | BC88: 0 | BD88: 0 | BE88: 0 | BF88: 0 | BG88: 0 | BH88: 0 | BI88: =SUM(AZ88:BH88) -> 0 | BJ88: =+BI88/BI$13 -> 0 | BL88: 0 | BM88: 0 | BN88: 0 | BO88: 0 | BP88: 0 | BQ88: 0 | BR88: 0 | BS88: 0 | BT88: 0 | BU88: =SUM(BL88:BT88) -> 0 | BV88: =+BU88/BU$13 -> 0 | BX88: 0 | BY88: 0 | BZ88: 0 | CA88: 0 | CB88: 0 | CC88: 0 | CD88: 0 | CE88: 0 | CF88: 0 | CG88: =SUM(BX88:CF88) -> 0 | CH88: =+CG88/CG$13 -> 0 | CJ88: =+CG88-BU88 -> 0 | CK88: =IFERROR(+CJ88/BU88,0%) -> 0 | CM88: 0 | CN88: =+CM88/CM$13 -> 0 | CQ88: =+CP88/CP$13 -> 0 | CT88: =+CS88/CS$13 -> 0 | CV88: =+CM88-CS88 -> 0 | CW88: =+IFERROR(CV88/CS88,0) -> 0
A89: 5250 | B89: Adecuacion E Instalaciones | D89: -874 | E89: 0 | F89: 0 | G89: 0 | H89: 0 | I89: 0 | J89: 0 | K89: -4520 | L89: 0 | M89: =SUM(D89:L89) -> -5394 | N89: =+M89/M$13 -> -0.010686076 | P89: 0 | Q89: 0 | R89: 0 | S89: 0 | T89: 0 | U89: 0 | V89: 0 | W89: 0 | X89: 0 | Y89: =SUM(P89:X89) -> 0 | Z89: =+Y89/Y$13 -> 0 | AB89: 0 | AC89: 0 | AD89: 0 | AE89: 0 | AF89: -150 | AG89: 0 | AH89: 0 | AI89: 0 | AJ89: 0 | AK89: =SUM(AB89:AJ89) -> -150 | AL89: =+AK89/AK$13 -> -0.00029311473 | AN89: 0 | AO89: 0 | AP89: 0 | AQ89: -14 | AR89: 0 | AS89: 0 | AT89: 0 | AU89: 0 | AV89: 0 | AW89: =SUM(AN89:AV89) -> -14 | AX89: =+AW89/AW$13 -> -2.6364157e-05 | AZ89: -327 | BA89: 0 | BB89: 0 | BC89: 0 | BD89: 0 | BE89: 0 | BF89: 0 | BG89: 0 | BH89: 0 | BI89: =SUM(AZ89:BH89) -> -327 | BJ89: =+BI89/BI$13 -> -0.00065934864 | BL89: -907 | BM89: 0 | BN89: 0 | BO89: -390 | BP89: -767 | BQ89: 0 | BR89: 0 | BS89: 0 | BT89: 0 | BU89: =SUM(BL89:BT89) -> -2064 | BV89: =+BU89/BU$13 -> -0.0041522993 | BX89: 0 | BY89: 0 | BZ89: 0 | CA89: 0 | CB89: 0 | CC89: 0 | CD89: 0 | CE89: 0 | CF89: 0 | CG89: =SUM(BX89:CF89) -> 0 | CH89: =+CG89/CG$13 -> 0 | CJ89: =+CG89-BU89 -> 2064 | CK89: =IFERROR(+CJ89/BU89,0%) -> -1 | CM89: =-DATOS!D170 -> -2941 | CN89: =+CM89/CM$13 -> -0.00096677734 | CP89: =-DATOS!F170 -> -1387 | CQ89: =+CP89/CP$13 -> -0.0026921767 | CS89: =-DATOS!G170 -> -13492 | CT89: =+CS89/CS$13 -> -0.0045907825 | CV89: =+CM89-CS89 -> 10551 | CW89: =+IFERROR(CV89/CS89,0) -> -0.78201897
A90: 5250 | B90: Plomeria | D90: 0 | E90: 0 | F90: 0 | G90: 0 | H90: 0 | I90: 0 | J90: 0 | K90: 0 | L90: 0 | M90: =SUM(D90:L90) -> 0 | N90: =+M90/M$13 -> 0 | P90: 0 | Q90: 0 | R90: 0 | S90: 0 | T90: 0 | U90: 0 | V90: 0 | W90: 0 | X90: 0 | Y90: =SUM(P90:X90) -> 0 | Z90: =+Y90/Y$13 -> 0 | AB90: -253 | AC90: 0 | AD90: 0 | AE90: 0 | AF90: 0 | AG90: -133 | AH90: 0 | AI90: 0 | AJ90: 0 | AK90: =SUM(AB90:AJ90) -> -386 | AL90: =+AK90/AK$13 -> -0.00075428192 | AN90: 0 | AO90: 0 | AP90: 0 | AQ90: 0 | AR90: 0 | AS90: 0 | AT90: 0 | AU90: 0 | AV90: 0 | AW90: =SUM(AN90:AV90) -> 0 | AX90: =+AW90/AW$13 -> 0 | AZ90: 0 | BA90: 0 | BB90: 0 | BC90: 0 | BD90: 0 | BE90: 0 | BF90: 0 | BG90: 0 | BH90: 0 | BI90: =SUM(AZ90:BH90) -> 0 | BJ90: =+BI90/BI$13 -> 0 | BL90: 0 | BM90: 0 | BN90: 0 | BO90: 0 | BP90: 0 | BQ90: 0 | BR90: 0 | BS90: 0 | BT90: 0 | BU90: =SUM(BL90:BT90) -> 0 | BV90: =+BU90/BU$13 -> 0 | BX90: 0 | BY90: 0 | BZ90: 0 | CA90: 0 | CB90: 0 | CC90: 0 | CD90: 0 | CE90: 0 | CF90: 0 | CG90: =SUM(BX90:CF90) -> 0 | CH90: =+CG90/CG$13 -> 0 | CJ90: =+CG90-BU90 -> 0 | CK90: =IFERROR(+CJ90/BU90,0%) -> 0 | CM90: 0 | CN90: =+CM90/CM$13 -> 0 | CQ90: =+CP90/CP$13 -> 0 | CV90: =+CM90-CS90 -> 0 | CW90: =+IFERROR(CV90/CS90,0) -> 0
A91: 5255 | B91: Gastos De Viaje | D91: 0 | E91: 0 | F91: 0 | G91: 0 | H91: 0 | I91: 0 | J91: 0 | K91: 0 | L91: 0 | M91: =SUM(D91:L91) -> 0 | N91: =+M91/M$13 -> 0 | P91: 0 | Q91: 0 | R91: 0 | S91: 0 | T91: 0 | U91: 0 | V91: 0 | W91: 0 | X91: 0 | Y91: =SUM(P91:X91) -> 0 | Z91: =+Y91/Y$13 -> 0 | AB91: 0 | AC91: 0 | AD91: 0 | AE91: 0 | AF91: 0 | AG91: 0 | AH91: 0 | AI91: 0 | AJ91: 0 | AK91: =SUM(AB91:AJ91) -> 0 | AL91: =+AK91/AK$13 -> 0 | AN91: 0 | AO91: 0 | AP91: 0 | AQ91: 0 | AR91: 0 | AS91: 0 | AT91: 0 | AU91: 0 | AV91: 0 | AW91: =SUM(AN91:AV91) -> 0 | AX91: =+AW91/AW$13 -> 0 | AZ91: 0 | BA91: 0 | BB91: 0 | BC91: 0 | BD91: 0 | BE91: 0 | BF91: 0 | BG91: 0 | BH91: 0 | BI91: =SUM(AZ91:BH91) -> 0 | BJ91: =+BI91/BI$13 -> 0 | BL91: 0 | BM91: 0 | BN91: 0 | BO91: 0 | BP91: 0 | BQ91: 0 | BR91: 0 | BS91: 0 | BT91: 0 | BU91: =SUM(BL91:BT91) -> 0 | BV91: =+BU91/BU$13 -> 0 | BX91: 0 | BY91: 0 | BZ91: 0 | CA91: 0 | CB91: 0 | CC91: 0 | CD91: 0 | CE91: 0 | CF91: 0 | CG91: =SUM(BX91:CF91) -> 0 | CH91: =+CG91/CG$13 -> 0 | CJ91: =+CG91-BU91 -> 0 | CK91: =IFERROR(+CJ91/BU91,0%) -> 0 | CM91: 0 | CN91: =+CM91/CM$13 -> 0 | CP91: 0 | CQ91: =+CP91/CP$13 -> 0 | CS91: 0 | CT91: =+CS91/CS$13 -> 0 | CV91: =+CM91-CS91 -> 0 | CW91: =+IFERROR(CV91/CS91,0) -> 0
A92: 5260 | B92: Depreciacion | D92: 0 | E92: 0 | F92: 0 | G92: -445 | H92: -445 | I92: 0 | J92: 0 | K92: 0 | L92: -2 | M92: =SUM(D92:L92) -> -892 | N92: =+M92/M$13 -> -0.001767145 | P92: 0 | Q92: 0 | R92: 0 | S92: -445 | T92: -445 | U92: 0 | V92: 0 | W92: 0 | X92: -2 | Y92: =SUM(P92:X92) -> -892 | Z92: =+Y92/Y$13 -> -0.0016949088 | AB92: 0 | AC92: 0 | AD92: 0 | AE92: -445 | AF92: -445 | AG92: 0 | AH92: 0 | AI92: 0 | AJ92: -2 | AK92: =SUM(AB92:AJ92) -> -892 | AL92: =+AK92/AK$13 -> -0.0017430556 | AN92: 0 | AO92: 0 | AP92: 0 | AQ92: -457 | AR92: -445 | AS92: 0 | AT92: 0 | AU92: 0 | AV92: -2 | AW92: =SUM(AN92:AV92) -> -904 | AX92: =+AW92/AW$13 -> -0.0017023713 | AZ92: 0 | BA92: 0 | BB92: 0 | BC92: -457 | BD92: -445 | BE92: 0 | BF92: 0 | BG92: 0 | BH92: -2 | BI92: =SUM(AZ92:BH92) -> -904 | BJ92: =+BI92/BI$13 -> -0.0018227864 | BL92: 0 | BM92: 0 | BN92: 0 | BO92: -457 | BP92: -445 | BQ92: 0 | BR92: 0 | BS92: 0 | BT92: -2 | BU92: =SUM(BL92:BT92) -> -904 | BV92: =+BU92/BU$13 -> -0.0018186427 | BX92: 0 | BY92: 0 | BZ92: 0 | CA92: -457 | CB92: -445 | CC92: 0 | CD92: 0 | CE92: 0 | CF92: -2 | CG92: =SUM(BX92:CF92) -> -904 | CH92: =+CG92/CG$13 -> -0.0018833804 | CJ92: =+CG92-BU92 -> 0 | CK92: =IFERROR(+CJ92/BU92,0%) -> 0 | CM92: =-DATOS!D171 -> -5402 | CN92: =+CM92/CM$13 -> -0.0017757672 | CP92: =-DATOS!F171 -> -890 | CQ92: =+CP92/CP$13 -> -0.0017274962 | CS92: =-DATOS!G171 -> -5481 | CT92: =+CS92/CS$13 -> -0.0018649629 | CV92: =+CM92-CS92 -> 79 | CW92: =+IFERROR(CV92/CS92,0) -> -0.014413428
A93: 5265 | B93: Amortizacion | D93: 0 | E93: 0 | F93: 0 | G93: 0 | H93: 0 | I93: 0 | J93: 0 | K93: 0 | L93: 0 | M93: =SUM(D93:L93) -> 0 | N93: =+M93/M$13 -> 0 | P93: 0 | Q93: 0 | R93: 0 | S93: 0 | T93: 0 | U93: 0 | V93: 0 | W93: 0 | X93: 0 | Y93: =SUM(P93:X93) -> 0 | Z93: =+Y93/Y$13 -> 0 | AB93: 0 | AC93: 0 | AD93: 0 | AE93: 0 | AF93: 0 | AG93: 0 | AH93: 0 | AI93: 0 | AJ93: 0 | AK93: =SUM(AB93:AJ93) -> 0 | AL93: =+AK93/AK$13 -> 0 | AN93: 0 | AO93: 0 | AP93: 0 | AQ93: 0 | AR93: 0 | AS93: 0 | AT93: 0 | AU93: 0 | AV93: 0 | AW93: =SUM(AN93:AV93) -> 0 | AX93: =+AW93/AW$13 -> 0 | AZ93: 0 | BA93: 0 | BB93: 0 | BC93: 0 | BD93: 0 | BE93: 0 | BF93: 0 | BG93: 0 | BH93: 0 | BI93: =SUM(AZ93:BH93) -> 0 | BJ93: =+BI93/BI$13 -> 0 | BL93: 0 | BM93: 0 | BN93: 0 | BO93: 0 | BP93: 0 | BQ93: 0 | BR93: 0 | BS93: 0 | BT93: 0 | BU93: =SUM(BL93:BT93) -> 0 | BV93: =+BU93/BU$13 -> 0 | BX93: 0 | BY93: 0 | BZ93: 0 | CA93: 0 | CB93: 0 | CC93: 0 | CD93: 0 | CE93: 0 | CF93: 0 | CG93: =SUM(BX93:CF93) -> 0 | CH93: =+CG93/CG$13 -> 0 | CJ93: =+CG93-BU93 -> 0 | CK93: =IFERROR(+CJ93/BU93,0%) -> 0 | CM93: 0 | CN93: =+CM93/CM$13 -> 0 | CP93: 0 | CQ93: =+CP93/CP$13 -> 0 | CS93: 0 | CT93: =+CS93/CS$13 -> 0 | CV93: =+CM93-CS93 -> 0 | CW93: =+IFERROR(CV93/CS93,0) -> 0
A94: 5295 | B94: Diversos | D94: =+SUM(D95:D115) -> -315 | E94: =+SUM(E95:E115) -> -295 | F94: =+SUM(F95:F115) -> -238 | G94: =+SUM(G95:G115) -> -122 | H94: =+SUM(H95:H115) -> -1367 | I94: =+SUM(I95:I115) -> -389 | J94: =+SUM(J95:J115) -> -486 | K94: =+SUM(K95:K115) -> -119 | ... M94: =+SUM(M95:M115) -> -4045 | N94: =+M94/M$13 -> -0.0080135666 | P94: =+SUM(P95:P115) -> -333 | Q94: =+SUM(Q95:Q115) -> -283 | R94: =+SUM(R95:R115) -> -381 | S94: =+SUM(S95:S115) -> -524 | T94: =+SUM(T95:T115) -> -517 | U94: =+SUM(U95:U115) -> -644 | V94: =+SUM(V95:V115) -> -260 | W94: =+SUM(W95:W115) -> 0 | ... Y94: =+SUM(Y95:Y115) -> -3486 | Z94: =+Y94/Y$13 -> -0.0066238252 | AB94: =+SUM(AB95:AB115) -> -479 | AC94: =+SUM(AC95:AC115) -> -562 | AD94: =+SUM(AD95:AD115) -> -279 | AE94: =+SUM(AE95:AE115) -> -344 | AF94: =+SUM(AF95:AF115) -> -814 | AG94: =+SUM(AG95:AG115) -> -434 | AH94: =+SUM(AH95:AH115) -> -477 | AI94: =+SUM(AI95:AI115) -> 0 | ... AK94: =+SUM(AK95:AK115) -> -4285 | AL94: =+AK94/AK$13 -> -0.0083733109 | AN94: =+SUM(AN95:AN115) -> -462 | AO94: =+SUM(AO95:AO115) -> -586 | AP94: =+SUM(AP95:AP115) -> -211 | AQ94: =+SUM(AQ95:AQ115) -> -492 | AR94: =+SUM(AR95:AR115) -> -659 | AS94: =+SUM(AS95:AS115) -> -272 | AT94: =+SUM(AT95:AT115) -> -362 | AU94: =+SUM(AU95:AU115) -> 0 | ... AW94: =+SUM(AW95:AW115) -> -3288 | AX94: =+AW94/AW$13 -> -0.0061918105 | AZ94: =+SUM(AZ95:AZ115) -> -462 | BA94: =+SUM(BA95:BA115) -> -213 | BB94: =+SUM(BB95:BB115) -> -250 | BC94: =+SUM(BC95:BC115) -> -580 | BD94: =+SUM(BD95:BD115) -> -516 | BE94: =+SUM(BE95:BE115) -> -520 | BF94: =+SUM(BF95:BF115) -> -232 | BG94: =+SUM(BG95:BG115) -> 0 | ... BI94: =+SUM(BI95:BI115) -> -2938 | BJ94: =+BI94/BI$13 -> -0.0059240559 | BL94: =+SUM(BL95:BL115) -> -521 | BM94: =+SUM(BM95:BM115) -> -397 | BN94: =+SUM(BN95:BN115) -> -453 | BO94: =+SUM(BO95:BO115) -> -834 | BP94: =+SUM(BP95:BP115) -> -1118 | BQ94: =+SUM(BQ95:BQ115) -> -712 | BR94: =+SUM(BR95:BR115) -> -243 | BS94: =+SUM(BS95:BS115) -> 0 | ... BU94: =+SUM(BU95:BU115) -> -4373 | BV94: =+BU94/BU$13 -> -0.0087974829 | BX94: =+SUM(BX95:BX115) -> -359 | BY94: =+SUM(BY95:BY115) -> -527 | BZ94: =+SUM(BZ95:BZ115) -> -190 | CA94: =+SUM(CA95:CA115) -> -598 | CB94: =+SUM(CB95:CB115) -> -547 | CC94: =+SUM(CC95:CC115) -> -264 | CD94: =+SUM(CD95:CD115) -> -456 | CE94: =+SUM(CE95:CE115) -> 0 | ... CG94: =+SUM(CG95:CG115) -> -3268 | CH94: =+CG94/CG$13 -> -0.0068085035 | CJ94: =+CG94-BU94 -> 1105 | CK94: =IFERROR(+CJ94/BU94,0%) -> -0.25268694 | CM94: =+SUM(CM95:CM115) -> -21786.5 | CN94: =+CM94/CM$13 -> -0.0071617459 | CP94: =+SUM(CP95:CP115) -> -4003 | CQ94: =+CP94/CP$13 -> -0.0077698509 | CS94: =+SUM(CS95:CS115) -> -27620 | CT94: =+CS94/CS$13 -> -0.0093979702 | CV94: =+CM94-CS94 -> 5833.5 | CW94: =+IFERROR(CV94/CS94,0) -> -0.21120565
A95: 52952501 | B95: Refrigerios Al Personal | D95: 0 | E95: 0 | F95: 0 | G95: 0 | H95: 0 | I95: 0 | J95: 0 | K95: 0 | L95: 0 | M95: =SUM(D95:L95) -> 0 | N95: =+M95/M$13 -> 0 | P95: 0 | Q95: 0 | R95: 0 | S95: 0 | T95: 0 | U95: 0 | V95: 0 | W95: 0 | X95: 0 | Y95: =SUM(P95:X95) -> 0 | Z95: =+Y95/Y$13 -> 0 | AB95: 0 | AC95: 0 | AD95: -47 | AE95: 0 | AF95: -65 | AG95: 0 | AH95: 0 | AI95: 0 | AJ95: 0 | AK95: =SUM(AB95:AJ95) -> -112 | AL95: =+AK95/AK$13 -> -0.000218859 | AN95: 0 | AO95: 0 | AP95: 0 | AQ95: 0 | AR95: 0 | AS95: 0 | AT95: 0 | AU95: 0 | AV95: 0 | AW95: =SUM(AN95:AV95) -> 0 | AX95: =+AW95/AW$13 -> 0 | AZ95: 0 | BA95: 0 | BB95: 0 | BC95: 0 | BD95: 0 | BE95: 0 | BF95: 0 | BG95: 0 | BH95: 0 | BI95: =SUM(AZ95:BH95) -> 0 | BJ95: =+BI95/BI$13 -> 0 | BL95: 0 | BM95: 0 | BN95: 0 | BO95: 0 | BP95: 0 | BQ95: 0 | BR95: 0 | BS95: 0 | BT95: 0 | BU95: =SUM(BL95:BT95) -> 0 | BV95: =+BU95/BU$13 -> 0 | BX95: 0 | BY95: 0 | BZ95: 0 | CA95: 0 | CB95: 0 | CC95: 0 | CD95: 0 | CE95: 0 | CF95: 0 | CG95: =SUM(BX95:CF95) -> 0 | CH95: =+CG95/CG$13 -> 0 | CJ95: =+CG95-BU95 -> 0 | CK95: =IFERROR(+CJ95/BU95,0%) -> 0 | CM95: =-DATOS!D173 -> -112 | CN95: =+CM95/CM$13 -> -3.681709e-05 | CP95: =-DATOS!F173 -> 0 | CQ95: =+CP95/CP$13 -> 0 | CS95: =-DATOS!G173 -> 0 | CT95: =+CS95/CS$13 -> 0 | CV95: =+CM95-CS95 -> -112 | CW95: =+IFERROR(CV95/CS95,0) -> 0
A96: 52952502 | B96: Utiles De Aseo Y Cafeteria | D96: -62 | E96: 0 | F96: -141 | G96: 48 | H96: -487 | I96: -9 | J96: -298 | K96: -119 | L96: -145 | M96: =SUM(D96:L96) -> -1213 | N96: =+M96/M$13 -> -0.0024030794 | P96: -126 | Q96: -131 | R96: -200 | S96: -229 | T96: -73 | U96: -99 | V96: -124 | W96: 0 | X96: -80 | Y96: =SUM(P96:X96) -> -1062 | Z96: =+Y96/Y$13 -> -0.0020179296 | AB96: -91 | AC96: -208 | AD96: 0 | AE96: -35 | AF96: -295 | AG96: -27 | AH96: -132 | AI96: 0 | AJ96: -141 | AK96: =SUM(AB96:AJ96) -> -929 | AL96: =+AK96/AK$13 -> -0.0018153573 | AN96: -201 | AO96: -400 | AP96: 0 | AQ96: -64 | AR96: -201 | AS96: -25 | AT96: -147 | AU96: 0 | AV96: -43 | AW96: =SUM(AN96:AV96) -> -1081 | AX96: =+AW96/AW$13 -> -0.0020356895 | AZ96: -164 | BA96: 0 | BB96: -121 | BC96: -226 | BD96: -219 | BE96: -41 | BF96: -125 | BG96: 0 | BH96: 0 | BI96: =SUM(AZ96:BH96) -> -896 | BJ96: =+BI96/BI$13 -> -0.0018066556 | BL96: -136 | BM96: -149 | BN96: -189 | BO96: -214 | BP96: -322 | BQ96: -392 | BR96: -84 | BS96: 0 | BT96: 0 | BU96: =SUM(BL96:BT96) -> -1486 | BV96: =+BU96/BU$13 -> -0.0029894945 | BX96: -54 | BY96: -341 | BZ96: -62 | CA96: -120 | CB96: -325 | CC96: -141 | CD96: -180 | CE96: 0 | CF96: -153 | CG96: =SUM(BX96:CF96) -> -1376 | CH96: =+CG96/CG$13 -> -0.0028667383 | CJ96: =+CG96-BU96 -> 110 | CK96: =IFERROR(+CJ96/BU96,0%) -> -0.074024226 | CM96: =-DATOS!D174 -> -6826.5 | CN96: =+CM96/CM$13 -> -0.0022440345 | CP96: =-DATOS!F174-28 -> -1449 | CQ96: =+CP96/CP$13 -> -0.0028125191 | CS96: =-DATOS!G174 -> -7623 | CT96: =+CS96/CS$13 -> -0.0025937989 | CV96: =+CM96-CS96 -> 796.5 | CW96: =+IFERROR(CV96/CS96,0) -> -0.10448642
A97: 52953001 | B97: Utiles Papeleria Y Fotocopias | D97: -106 | E97: -73 | F97: -25 | G97: -28 | H97: -62 | I97: -121 | J97: -45 | K97: 0 | L97: -14 | M97: =SUM(D97:L97) -> -474 | N97: =+M97/M$13 -> -0.0009390434 | P97: -74 | Q97: -56 | R97: -70 | S97: -98 | T97: -67 | U97: -60 | V97: -51 | W97: 0 | X97: -128 | Y97: =SUM(P97:X97) -> -604 | Z97: =+Y97/Y$13 -> -0.0011476737 | AB97: -100 | AC97: -43 | AD97: -2 | AE97: -60 | AF97: -105 | AG97: -81 | AH97: -41 | AI97: 0 | AJ97: -8 | AK97: =SUM(AB97:AJ97) -> -440 | AL97: =+AK97/AK$13 -> -0.00085980322 | AN97: -83 | AO97: -67 | AP97: 0 | AQ97: -144 | AR97: -114 | AS97: -109 | AT97: -99 | AU97: 0 | AV97: -41 | AW97: =SUM(AN97:AV97) -> -657 | AX97: =+AW97/AW$13 -> -0.0012372322 | AZ97: -49 | BA97: -76 | BB97: -63 | BC97: -25 | BD97: -63 | BE97: -21 | BF97: -23 | BG97: 0 | BH97: -58 | BI97: =SUM(AZ97:BH97) -> -378 | BJ97: =+BI97/BI$13 -> -0.00076218283 | BL97: 0 | BM97: -93 | BN97: -59 | BO97: -152 | BP97: -135 | BQ97: -83 | BR97: -56 | BS97: 0 | BT97: -64 | BU97: =SUM(BL97:BT97) -> -642 | BV97: =+BU97/BU$13 -> -0.0012915582 | BX97: -126 | BY97: -55 | BZ97: -26 | CA97: -126 | CB97: -26 | CC97: -56 | CD97: -22 | CE97: 0 | CF97: -62 | CG97: =SUM(BX97:CF97) -> -499 | CH97: =+CG97/CG$13 -> -0.0010396093 | CJ97: =+CG97-BU97 -> 143 | CK97: =IFERROR(+CJ97/BU97,0%) -> -0.22274143 | CM97: =-DATOS!D175 -> -3219.5 | CN97: =+CM97/CM$13 -> -0.001058327 | CP97: =-DATOS!F175 -> -361 | CQ97: =+CP97/CP$13 -> -0.00070070352 | CS97: =-DATOS!G175 -> -3767.5 | CT97: =+CS97/CS$13 -> -0.001281928 | CV97: =+CM97-CS97 -> 548 | CW97: =+IFERROR(CV97/CS97,0) -> -0.14545455
A98: 52953501 | B98: Combustibles Y Lubricantes | D98: 0 | E98: 0 | F98: 0 | G98: 0 | H98: 0 | I98: 0 | J98: 0 | K98: 0 | L98: 0 | M98: =SUM(D98:L98) -> 0 | N98: =+M98/M$13 -> 0 | P98: 0 | Q98: 0 | R98: 0 | S98: 0 | T98: 0 | U98: 0 | V98: 0 | W98: 0 | X98: 0 | Y98: =SUM(P98:X98) -> 0 | Z98: =+Y98/Y$13 -> 0 | AB98: 0 | AC98: 0 | AD98: 0 | AE98: 0 | AF98: 0 | AG98: 0 | AH98: 0 | AI98: 0 | AJ98: 0 | AK98: =SUM(AB98:AJ98) -> 0 | AL98: =+AK98/AK$13 -> 0 | AN98: 0 | AO98: 0 | AP98: 0 | AQ98: 0 | AR98: 0 | AS98: 0 | AT98: 0 | AU98: 0 | AV98: 0 | AW98: =SUM(AN98:AV98) -> 0 | AX98: =+AW98/AW$13 -> 0 | AZ98: 0 | BA98: 0 | BB98: 0 | BC98: 0 | BD98: 0 | BE98: 0 | BF98: 0 | BG98: 0 | BH98: 0 | BI98: =SUM(AZ98:BH98) -> 0 | BJ98: =+BI98/BI$13 -> 0 | BL98: 0 | BM98: 0 | BN98: 0 | BO98: 0 | BP98: 0 | BQ98: 0 | BR98: 0 | BS98: 0 | BT98: 0 | BU98: =SUM(BL98:BT98) -> 0 | BV98: =+BU98/BU$13 -> 0 | BX98: 0 | BY98: 0 | BZ98: 0 | CA98: 0 | CB98: 0 | CC98: 0 | CD98: 0 | CE98: 0 | CF98: 0 | CG98: =SUM(BX98:CF98) -> 0 | CH98: =+CG98/CG$13 -> 0 | CJ98: =+CG98-BU98 -> 0 | CK98: =IFERROR(+CJ98/BU98,0%) -> 0 | CM98: 0 | CN98: =+CM98/CM$13 -> 0 | CP98: =-DATOS!F176 -> 0 | CQ98: =+CP98/CP$13 -> 0 | CS98: =-DATOS!G176 -> 0 | CT98: =+CS98/CS$13 -> 0 | CV98: =+CM98-CS98 -> 0 | CW98: =+IFERROR(CV98/CS98,0) -> 0
A99: 52954001 | B99: Envases Y Empaques | D99: -2 | E99: 0 | F99: 0 | G99: 0 | H99: -1 | I99: -2 | J99: 0 | K99: 0 | L99: -1 | M99: =SUM(D99:L99) -> -6 | N99: =+M99/M$13 -> -1.1886625e-05 | P99: 0 | Q99: 0 | R99: 0 | S99: 0 | T99: -13 | U99: 0 | V99: 0 | W99: 0 | X99: 0 | Y99: =SUM(P99:X99) -> -13 | Z99: =+Y99/Y$13 -> -2.4701586e-05 | AB99: 0 | AC99: 0 | AD99: 0 | AE99: 0 | AF99: -1 | AG99: 0 | AH99: 0 | AI99: 0 | AJ99: -4 | AK99: =SUM(AB99:AJ99) -> -5 | AL99: =+AK99/AK$13 -> -9.7704912e-06 | AN99: 0 | AO99: 0 | AP99: 0 | AQ99: 0 | AR99: 0 | AS99: 0 | AT99: 0 | AU99: 0 | AV99: 0 | AW99: =SUM(AN99:AV99) -> 0 | AX99: =+AW99/AW$13 -> 0 | AZ99: -24 | BA99: 0 | BB99: 0 | BC99: -1 | BD99: 0 | BE99: 0 | BF99: 0 | BG99: 0 | BH99: 0 | BI99: =SUM(AZ99:BH99) -> -25 | BJ99: =+BI99/BI$13 -> -5.0408917e-05 | BL99: -1 | BM99: 0 | BN99: 0 | BO99: -1 | BP99: -11 | BQ99: 0 | BR99: 0 | BS99: 0 | BT99: -13 | BU99: =SUM(BL99:BT99) -> -26 | BV99: =+BU99/BU$13 -> -5.2306095e-05 | BX99: 0 | BY99: 0 | BZ99: 0 | CA99: 0 | CB99: 0 | CC99: 0 | CD99: 0 | CE99: 0 | CF99: 0 | CG99: =SUM(BX99:CF99) -> 0 | CH99: =+CG99/CG$13 -> 0 | CJ99: =+CG99-BU99 -> 26 | CK99: =IFERROR(+CJ99/BU99,0%) -> -1 | CM99: =-DATOS!D177 -> -69 | CN99: =+CM99/CM$13 -> -2.2681957e-05 | CP99: =-DATOS!F177 -> -190.5 | CQ99: =+CP99/CP$13 -> -0.00036976183 | CS99: =-DATOS!G177 -> -420 | CT99: =+CS99/CS$13 -> -0.00014290903 | CV99: =+CM99-CS99 -> 351 | CW99: =+IFERROR(CV99/CS99,0) -> -0.83571429
